Workbook

Sheet 🏠 PORTADA
B4: IMPULSO · Máster en Dirección de Proyectos · Universidad de Valladolid · Álvar del Prado Suárez · 2026
B6: ='⚙️ SUPUESTOS'!C28 -> 203 | C6: ='📊 PANEL'!V2&" / "&'📊 PANEL'!V3&" / "&'📊 PANEL'!V4 -> 67 / 68 / 68
B7: portales certificados | C7: Fases 1 / 2 / 3
B9: INSTRUCCIONES DE USO
B10: 1. Introduce o edita los datos de cada edificio en la hoja INVENTARIO (punto de entrada único). 2. El RANKING, las fases y el PANEL se recalculan automáticamente. 3. Ajusta los pesos del AHP y los demás parámetros en la hoja SUPUESTOS. 4. Selecciona el ámbito (barrio) en el desplegable superior. 5. Para visualizarlo sobre el mapa, carga este libro en la herramienta IMPULSO (botón 📂 Cargar Excel).
B16: CRITERIOS DEL MODELO AHP (Saaty, 1994 · RC = 0,053)
B17: C1 · Consumo EP individual | C17: 55% | D17: Energía primaria kWh/m²·año (certificado JCyL), min–max sobre el ranking
B18: C2 · Vulnerabilidad económica | C18: 22% | D18: 40%·paro + 40% · (1−renta) + 20%·alquiler (INE, 2021 + ADRH, 2023)
B19: C3 · Vulnerabilidad social | C19: 14% | D19: % población sin estudios superiores (INE, 2021, invertido)
B20: C4 · Vuln. demográfica (envejecimiento) | C20: 9% | D20: % población >64 años (Padrón, INE, 2023)
B22: Índice Pk = 0,55·C1n + 0,22·C2n + 0,14·C3n + 0,09·C4n → Ranking 1–203 → 3 fases
B24: ¿POR QUÉ ESTAS ACTUACIONES?
B25: La intervención propuesta se asigna en función de la calificación energética del edificio: cuanto peor es la calificación de partida, más profunda es la actuación recomendada. Esta lógica es coherente con las exigencias del programa estatal de rehabilitación (RD 853/2021), que condiciona las ayudas a una reducción mínima del 30 % del consumo de energía primaria no renovable.
B27: Cal. G / F | D27: Renovación integral: SATE integral + cubierta + carpinterías triple + aerotermia + instalación fotovoltaica.
B28: Cal. E | D28: Envolvente parcial: SATE fachada + carpinterías doble + instalación fotovoltaica.
B29: Cal. D | D29: Mantenimiento de envolvente + instalación fotovoltaica en cubierta.
B30: Accesibilidad | D30: No hay dato por edificio de si ya tiene ascensor: se marca "valorar ascensor (verificar)" solo en 4+ plantas, a confirmar en campo.
B32: ENERGÍA SOLAR:
B33: Estimación del potencial solar fotovoltaico por cubierta: kWp a partir de la superficie disponible, producción según la radiación del IGN y ahorro económico asociado, con parámetros calibrados contra el visor solar del IGN (desviación aproximada del ±5%). La amortización varía según la cubierta y la columna se colorea automáticamente (verde = mejor retorno; rojo = peor). Cifras orientativas, a contrastar en proyecto.
B36: LEYENDA DE COLORES
B37: Calificación energética: | E37: G | F37: F | G37: E | H37: D
B38: Fases: | E38: F1 | F38: F2 | G38: F3
B39: Azul = editable · Verde = enlace entre hojas · Negro = fórmula · Barras/escalas = magnitud relativa
B41: Barrio (contorno del mapa) ▼
B43: Se lee al pulsar “Cargar Excel” en el mapa) | D43: Pajarillos Bajos
O130: 41.650674
O160: 41.650743 | P160: -4.708165

Sheet 📇 INVENTARIO
A1: 📇 INVENTARIO DE EDIFICIOS — entrada de datos
B2: ⬇ Añada un edificio para calcular el RANKING.
A3: # | B3: Dirección | C3: Ref. catastral | D3: Sección | E3: Certificado | F3: Cal. | G3: EP kWh/m² | H3: CO₂ kg/m² | I3: Dcal kWh/m² | J3: Año | K3: Plantas | L3: Sup.cub m² | M3: Sup.fach m² (auto) | N3: Rad.IGN | O3: Lat | P3: Lon
A4: =IF($B4="","",COUNTA($B$4:B4)) -> 1 | B4: C/ Salud, 19 | C4: 7625401UM5172F | D4: 4718606026 | E4: Sí | F4: G | G4: 713 | H4: 151 | I4: 368.8 | J4: 1958 | K4: 5 | L4: 330.5 | M4: =IF(OR($K4="",$L4=""),"",ROUND('⚙️ SUPUESTOS'!$C$14*'⚙️ SUPUESTOS'!$C$18*SQRT($L4)*$K4,0)) -> 1227 | N4: 1373 | O4: 41.649797 | P4: -4.710882
A5: =IF($B5="","",COUNTA($B$4:B5)) -> 2 | B5: C/ Pavo Real, 21 | C5: 7625404UM5172F | D5: 4718606026 | E5: Sí | F5: G | G5: 630 | H5: 107 | I5: 178.9 | J5: 1965 | K5: 3 | L5: 96.2 | M5: =IF(OR($K5="",$L5=""),"",ROUND('⚙️ SUPUESTOS'!$C$14*'⚙️ SUPUESTOS'!$C$18*SQRT($L5)*$K5,0)) -> 397 | N5: 1477 | O5: 41.64943 | P5: -4.71056
A6: =IF($B6="","",COUNTA($B$4:B6)) -> 3 | B6: C/ Salud, 17 | C6: 7625401UM5172F | D6: 4718606026 | E6: Sí | F6: G | G6: 528 | H6: 90 | I6: 211 | J6: 1958 | K6: 5 | L6: 330.5 | M6: =IF(OR($K6="",$L6=""),"",ROUND('⚙️ SUPUESTOS'!$C$14*'⚙️ SUPUESTOS'!$C$18*SQRT($L6)*$K6,0)) -> 1227 | N6: 1373 | O6: 41.649497 | P6: -4.711089
A7: =IF($B7="","",COUNTA($B$4:B7)) -> 4 | B7: C/ Halcón, 2 | C7: 7925705UM5172F | D7: 4718606023 | E7: Sí | F7: G | G7: 646 | H7: 110 | I7: 218.2 | J7: 1965 | K7: 3 | L7: 102.1 | M7: =IF(OR($K7="",$L7=""),"",ROUND('⚙️ SUPUESTOS'!$C$14*'⚙️ SUPUESTOS'!$C$18*SQRT($L7)*$K7,0)) -> 409 | N7: 1380 | O7: 41.64986 | P7: -4.70842
A8: =IF($B8="","",COUNTA($B$4:B8)) -> 5 | B8: C/ Rincón del Esgueva, 13 | C8: 7726409UM5172F | D8: 4718606023 | E8: Sí | F8: G | G8: 634 | H8: 134 | I8: 334.2 | J8: 1936 | K8: 1 | L8: 53.6 | M8: =IF(OR($K8="",$L8=""),"",ROUND('⚙️ SUPUESTOS'!$C$14*'⚙️ SUPUESTOS'!$C$18*SQRT($L8)*$K8,0)) -> 99 | N8: 1515 | O8: 41.65012 | P8: -4.70963
A9: =IF($B9="","",COUNTA($B$4:B9)) -> 6 | B9: C/ Calandria, 4 | C9: 7925710UM5172F | D9: 4718606023 | E9: Sí | F9: G | G9: 632 | H9: 134 | I9: 251.9 | J9: 1965 | K9: 3 | L9: 101.6 | M9: =IF(OR($K9="",$L9=""),"",ROUND('⚙️ SUPUESTOS'!$C$14*'⚙️ SUPUESTOS'!$C$18*SQRT($L9)*$K9,0)) -> 408 | N9: 1366 | O9: 41.64975 | P9: -4.70784
A10: =IF($B10="","",COUNTA($B$4:B10)) -> 7 | B10: C/ Pavo Real, 17 | C10: 7625406UM5172F | D10: 4718606026 | E10: Sí | F10: G | G10: 464 | H10: 118 | I10: 180.2 | J10: 1965 | K10: 3 | L10: 95.1 | M10: =IF(OR($K10="",$L10=""),"",ROUND('⚙️ SUPUESTOS'!$C$14*'⚙️ SUPUESTOS'!$C$18*SQRT($L10)*$K10,0)) -> 395 | N10: 1467 | O10: 41.64922 | P10: -4.71073
A11: =IF($B11="","",COUNTA($B$4:B11)) -> 8 | B11: C/ Marabú, 1 | C11: 7924213UM5172D | D11: 4718606024 | E11: Sí | F11: G | G11: 724 | H11: 148 | I11: 374.5 | J11: 1965 | K11: 3 | L11: 97.4 | M11: =IF(OR($K11="",$L11=""),"",ROUND('⚙️ SUPUESTOS'!$C$14*'⚙️ SUPUESTOS'!$C$18*SQRT($L11)*$K11,0)) -> 400 | N11: 1394 | O11: 41.64934 | P11: -4.70757
A12: =IF($B12="","",COUNTA($B$4:B12)) -> 9 | B12: C/ Águila, 20 | C12: 7824519UM5172D | D12: 4718606026 | E12: Sí | F12: G | G12: 461 | H12: 79 | I12: 155.4 | J12: 1965 | K12: 3 | L12: 110.7 | M12: =IF(OR($K12="",$L12=""),"",ROUND('⚙️ SUPUESTOS'!$C$14*'⚙️ SUPUESTOS'!$C$18*SQRT($L12)*$K12,0)) -> 426 | N12: 1517 | O12: 41.64889 | P12: -4.70906
A13: =IF($B13="","",COUNTA($B$4:B13)) -> 10 | B13: C/ Albatros, 1 | C13: 7724226UM5172D | D13: 4718606026 | E13: Sí | F13: G | G13: 454 | H13: 96 | I13: 173.2 | J13: 1965 | K13: 3 | L13: 95.5 | M13: =IF(OR($K13="",$L13=""),"",ROUND('⚙️ SUPUESTOS'!$C$14*'⚙️ SUPUESTOS'!$C$18*SQRT($L13)*$K13,0)) -> 396 | N13: 1431 | O13: 41.64887 | P13: -4.71047
A14: =IF($B14="","",COUNTA($B$4:B14)) -> 11 | B14: C/ Papagayo, 6 | C14: 7825411UM5172F | D14: 4718606023 | E14: Sí | F14: G | G14: 589 | H14: 100 | I14: 242.3 | J14: 1965 | K14: 3 | L14: 100.8 | M14: =IF(OR($K14="",$L14=""),"",ROUND('⚙️ SUPUESTOS'!$C$14*'⚙️ SUPUESTOS'!$C$18*SQRT($L14)*$K14,0)) -> 407 | N14: 1399 | O14: 41.64956 | P14: -4.70818
A15: =IF($B15="","",COUNTA($B$4:B15)) -> 12 | B15: C/ Villabáñez, 18 | C15: 7824502UM5172D | D15: 4718606026 | E15: Sí | F15: G | G15: 442 | H15: 93 | I15: 200 | J15: 1965 | K15: 3 | L15: 113.4 | M15: =IF(OR($K15="",$L15=""),"",ROUND('⚙️ SUPUESTOS'!$C$14*'⚙️ SUPUESTOS'!$C$18*SQRT($L15)*$K15,0)) -> 431 | N15: 1421 | O15: 41.64896 | P15: -4.70864
... A206: =IF($B206="","",COUNTA($B$4:B206)) -> 203 | B206: C/ Juan Carlos I, 87 | C206: 7922508UM5172B | D206: 4718606025 | E206: Sí | F206: E | G206: 174 | H206: 37 | I206: 65.2 | J206: 1970 | K206: 5 | L206: 417 | M206: =IF(OR($K206="",$L206=""),"",ROUND('⚙️ SUPUESTOS'!$C$14*'⚙️ SUPUESTOS'!$C$18*SQRT($L206)*$K206,0)) -> 1378 | N206: 1519 | O206: 41.64665 | P206: -4.70723
A207: =IF($B207="","",COUNTA($B$4:B207))
A208: =IF($B208="","",COUNTA($B$4:B208))
A209: =IF($B209="","",COUNTA($B$4:B209))
A210: =IF($B210="","",COUNTA($B$4:B210))
A211: =IF($B211="","",COUNTA($B$4:B211))
A212: =IF($B212="","",COUNTA($B$4:B212))
A213: =IF($B213="","",COUNTA($B$4:B213))
A214: =IF($B214="","",COUNTA($B$4:B214))
A215: =IF($B215="","",COUNTA($B$4:B215))
A216: =IF($B216="","",COUNTA($B$4:B216))
A217: =IF($B217="","",COUNTA($B$4:B217))
A218: =IF($B218="","",COUNTA($B$4:B218))
... A266: =IF($B266="","",COUNTA($B$4:B266))
A268: =IF($B268="","",COUNTA($B$4:B268)) -> 204 | B268: C/ Villabáñez, 3 | C268: 7825710UM5172F | E268: No | F268: ? | G268: 0 | H268: 0 | J268: 1963 | K268: 3 | L268: 180 | M268: =IF(OR($K268="",$L268=""),"",ROUND('⚙️ SUPUESTOS'!$C$14*'⚙️ SUPUESTOS'!$C$18*SQRT($L268)*$K268,0)) -> 543 | O268: 41.64994 | P268: -4.71035
A269: =IF($B269="","",COUNTA($B$4:B269)) -> 205 | B269: C/ Cigüeña, 32 | C269: 7923013UM5172D | E269: No | F269: ? | G269: 0 | H269: 0 | J269: 1962 | K269: 3 | L269: 395 | M269: =IF(OR($K269="",$L269=""),"",ROUND('⚙️ SUPUESTOS'!$C$14*'⚙️ SUPUESTOS'!$C$18*SQRT($L269)*$K269,0)) -> 805 | O269: 41.64837 | P269: -4.70852
A270: =IF($B270="","",COUNTA($B$4:B270)) -> 206 | B270: C/ Villabáñez, 13 | C270: 7825418UM5172F | E270: No | F270: ? | G270: 0 | H270: 0 | J270: 1965 | K270: 5 | L270: 722 | M270: =IF(OR($K270="",$L270=""),"",ROUND('⚙️ SUPUESTOS'!$C$14*'⚙️ SUPUESTOS'!$C$18*SQRT($L270)*$K270,0)) -> 1814 | O270: 41.64955 | P270: -4.7092
A271: =IF($B271="","",COUNTA($B$4:B271)) -> 207 | B271: C/ Gavilán, 2 | C271: 7825403UM5172F | E271: No | F271: ? | G271: 0 | H271: 0 | J271: 1965 | K271: 3 | L271: 101 | M271: =IF(OR($K271="",$L271=""),"",ROUND('⚙️ SUPUESTOS'!$C$14*'⚙️ SUPUESTOS'!$C$18*SQRT($L271)*$K271,0)) -> 407 | O271: 41.64962 | P271: -4.7089
A272: =IF($B272="","",COUNTA($B$4:B272)) -> 208 | B272: C/ Cigüeña, 49 | C272: 7825414UM5172F | E272: No | F272: ? | G272: 0 | H272: 0 | J272: 1965 | K272: 3 | L272: 98 | M272: =IF(OR($K272="",$L272=""),"",ROUND('⚙️ SUPUESTOS'!$C$14*'⚙️ SUPUESTOS'!$C$18*SQRT($L272)*$K272,0)) -> 401 | O272: 41.64915 | P272: -4.70828
A273: =IF($B273="","",COUNTA($B$4:B273)) -> 209 | B273: C/ Halcón, 4 | C273: 7925706UM5172F | E273: No | F273: ? | G273: 0 | H273: 0 | J273: 1965 | K273: 3 | L273: 102 | M273: =IF(OR($K273="",$L273=""),"",ROUND('⚙️ SUPUESTOS'!$C$14*'⚙️ SUPUESTOS'!$C$18*SQRT($L273)*$K273,0)) -> 409 | O273: 41.64993 | P273: -4.70821
A274: =IF($B274="","",COUNTA($B$4:B274)) -> 210 | B274: C/ Gorrión, 2 | C274: 7925704UM5172F | E274: No | F274: ? | G274: 0 | H274: 0 | J274: 1965 | K274: 3 | L274: 102 | M274: =IF(OR($K274="",$L274=""),"",ROUND('⚙️ SUPUESTOS'!$C$14*'⚙️ SUPUESTOS'!$C$18*SQRT($L274)*$K274,0)) -> 409 | O274: 41.64994 | P274: -4.70865
A275: =IF($B275="","",COUNTA($B$4:B275)) -> 211 | B275: C/ Cisne, 2 | C275: 7925701UM5172F | E275: No | F275: ? | G275: 0 | H275: 0 | J275: 1965 | K275: 3 | L275: 98 | M275: =IF(OR($K275="",$L275=""),"",ROUND('⚙️ SUPUESTOS'!$C$14*'⚙️ SUPUESTOS'!$C$18*SQRT($L275)*$K275,0)) -> 401 | O275: 41.65004 | P275: -4.70881
A276: =IF($B276="","",COUNTA($B$4:B276)) -> 212 | B276: C/ Calandria, 2 | C276: 7925709UM5172F | E276: No | F276: ? | G276: 0 | H276: 0 | J276: 1965 | K276: 3 | L276: 100 | M276: =IF(OR($K276="",$L276=""),"",ROUND('⚙️ SUPUESTOS'!$C$14*'⚙️ SUPUESTOS'!$C$18*SQRT($L276)*$K276,0)) -> 405 | O276: 41.64969 | P276: -4.70803
A277: =IF($B277="","",COUNTA($B$4:B277)) -> 213 | B277: C/ Villabáñez, 10 | C277: 7724202UM5172D | E277: No | F277: ? | G277: 0 | H277: 0 | J277: 1965 | K277: 3 | L277: 117 | M277: =IF(OR($K277="",$L277=""),"",ROUND('⚙️ SUPUESTOS'!$C$14*'⚙️ SUPUESTOS'!$C$18*SQRT($L277)*$K277,0)) -> 438 | O277: 41.64945 | P277: -4.7098
A278: =IF($B278="","",COUNTA($B$4:B278)) -> 214 | B278: C/ Cuclillo, 1 | C278: 7724211UM5172D | E278: No | F278: ? | G278: 0 | H278: 0 | J278: 1965 | K278: 3 | L278: 107 | M278: =IF(OR($K278="",$L278=""),"",ROUND('⚙️ SUPUESTOS'!$C$14*'⚙️ SUPUESTOS'!$C$18*SQRT($L278)*$K278,0)) -> 419 | O278: 41.64893 | P278: -4.7095
A279: =IF($B279="","",COUNTA($B$4:B279)) -> 215 | B279: C/ Paloma, 3 | C279: 7724213UM5172D | E279: No | F279: ? | G279: 0 | H279: 0 | J279: 1965 | K279: 3 | L279: 106 | M279: =IF(OR($K279="",$L279=""),"",ROUND('⚙️ SUPUESTOS'!$C$14*'⚙️ SUPUESTOS'!$C$18*SQRT($L279)*$K279,0)) -> 417 | O279: 41.64902 | P279: -4.70966
... A291: =IF($B291="","",COUNTA($B$4:B291)) -> 227 | B291: C/ Salud, 23 | C291: 7726416UM5172F | E291: No | F291: ? | G291: 0 | H291: 0 | J291: 1965 | K291: 5 | L291: 219 | M291: =IF(OR($K291="",$L291=""),"",ROUND('⚙️ SUPUESTOS'!$C$14*'⚙️ SUPUESTOS'!$C$18*SQRT($L291)*$K291,0)) -> 999 | O291: 41.65078 | P291: -4.71018

Sheet 📋 RANKING
A1: IDENTIFICACIÓN Y PRIORIDAD | F1: CERT. ENERGÉTICO — JCyL 2026 | K1: CRITERIOS AHP (0–1) | P1: SOCIOECONÓMICO (sección) | S1: CATASTRO ⚠ | T1: ACTUACIÓN PROPUESTA | V1: ☀️ SOLAR FV — IGN + cálculo paramétrico ⚠ | AG1: COORDENADAS
A2: # | B2: Fase | C2: Dirección | D2: Ref. catastral | E2: Sección | F2: Cal. EP | G2: EP kWh/m² | H2: CO₂ kg/m² | I2: Demanda calef. kWh/m² | J2: Año constr. | K2: C1n | L2: C2n | M2: C3n | N2: C4n | O2: Índice Pk | P2: Paro % | Q2: Renta €/hog | R2: Edad>64 % | S2: Plantas ⚠ | T2: Actuación energética (según calificación) | U2: Accesibilidad | V2: Sup. cub. m² | W2: kWp | X2: Rad. IGN kWh/m²·a | Y2: Producción kWh/año | Z2: Inversión € (sin subv.) | AA2: Ahorro €/año | AB2: Ahorro consumo €/año ⚡ | AC2: Ahorro compensación €/año 🔌 | AD2: Ahorro acumulado vida útil 25 años € | AE2: Amort. años | AF2: FV recomendada | AG2: Lat | AH2: Lon
A3: =IF($C3="","",RANK(O3,$O$3:$O$265,0)+COUNTIF($O$3:O3,O3)-1) -> 1 | B3: =IF($C3="","",IF(A3<='⚙️ SUPUESTOS'!$C$29,"Fase 1",IF(A3<='⚙️ SUPUESTOS'!$C$30,"Fase 2","Fase 3"))) -> Fase 1 | C3: =IF('📇 INVENTARIO'!B4="","",'📇 INVENTARIO'!B4) -> C/ Salud, 19 | D3: =IF('📇 INVENTARIO'!C4="","",'📇 INVENTARIO'!C4) -> 7625401UM5172F | E3: =IF('📇 INVENTARIO'!D4="","",'📇 INVENTARIO'!D4) -> 4718606026 | F3: =IF('📇 INVENTARIO'!F4="","",'📇 INVENTARIO'!F4) -> G | G3: =IF('📇 INVENTARIO'!G4="","",'📇 INVENTARIO'!G4) -> 713 | H3: =IF('📇 INVENTARIO'!H4="","",'📇 INVENTARIO'!H4) -> 151 | I3: =IF('📇 INVENTARIO'!I4="","",'📇 INVENTARIO'!I4) -> 368.8 | J3: =IF('📇 INVENTARIO'!J4="","",'📇 INVENTARIO'!J4) -> 1958 | K3: =IF($C3="","",(G3-'⚙️ SUPUESTOS'!$C$20)/('⚙️ SUPUESTOS'!$C$25-'⚙️ SUPUESTOS'!$C$20)) -> 0.98106713 | L3: =IF($C3="","",VLOOKUP($E3,'📊 SECCIONES'!$B$4:$S$9,16,FALSE())) -> 1 | M3: =IF($C3="","",VLOOKUP($E3,'📊 SECCIONES'!$B$4:$S$9,17,FALSE())) -> 1 | N3: =IF($C3="","",VLOOKUP($E3,'📊 SECCIONES'!$B$4:$S$9,18,FALSE())) -> 0 | O3: =IF($C3="","",ROUND('⚙️ SUPUESTOS'!$C$21*K3+'⚙️ SUPUESTOS'!$C$22*L3+'⚙️ SUPUESTOS'!$C$23*M3+'⚙️ SUPUESTOS'!$C$24*N3,4)) -> 0.8996 | P3: =IF($C3="","",VLOOKUP($E3,'📊 SECCIONES'!$B$4:$S$9,7,FALSE())) -> 66.51 | Q3: =IF($C3="","",VLOOKUP($E3,'📊 SECCIONES'!$B$4:$S$9,8,FALSE())) -> 17450 | R3: =IF($C3="","",VLOOKUP($E3,'📊 SECCIONES'!$B$4:$S$9,10,FALSE())) -> 10.6 | S3: =IF('📇 INVENTARIO'!K4="","",'📇 INVENTARIO'!K4) -> 5 | T3: =IF($C3="","","Objetivo: alcanzar calificación C. Actual: Cal."&F3&". "&IF(OR(F3="G",F3="F"),"SATE integral + cubierta + carpinterías triple + aerotermia + instalación fotovoltaica",IF(F3="E","SATE fachada + carpinterías doble + instalación fotovoltaica",IF(F3="D","Mantenimiento de envolvente + instalación fotovoltaica en cubierta","Optimización energética + instalación fotovoltaica")))) -> Objetivo: alcanzar calificación C. Actual: Cal.G. SATE integral + cubierta + carpinterías triple + aerotermia + instalación fotovoltaica | U3: =IF($C3="","",IF(S3=0,"s/d",IF(S3>=4,"Valorar ascensor (verificar)","—"))) -> Valorar ascensor (verificar) | V3: =IF('📇 INVENTARIO'!L4="","",'📇 INVENTARIO'!L4) -> 330.5 | W3: =IF($C3="","",V3*'⚙️ SUPUESTOS'!$C$8*'⚙️ SUPUESTOS'!$C$9) -> 69.405 | X3: =IF('📇 INVENTARIO'!N4="","",'📇 INVENTARIO'!N4) -> 1373 | Y3: =IF($C3="","",W3*X3*'⚙️ SUPUESTOS'!$C$7) -> 85763.759 | Z3: =IF($C3="","",W3*'⚙️ SUPUESTOS'!$C$10) -> 92655.675 | AA3: =IF($C3="","",Y3*('⚙️ SUPUESTOS'!$C$12*'⚙️ SUPUESTOS'!$C$11+(1-'⚙️ SUPUESTOS'!$C$12)*'⚙️ SUPUESTOS'!$C$13)) -> 5849.0883 | AB3: =IF($C3="","",IF(Y3>0,ROUND(Y3*'⚙️ SUPUESTOS'!$C$12*'⚙️ SUPUESTOS'!$C$11,0),"")) -> 2144 | AC3: =IF($C3="","",IF(Y3>0,ROUND(Y3*(1-'⚙️ SUPUESTOS'!$C$12)*'⚙️ SUPUESTOS'!$C$13,0),"")) -> 3705 | AD3: =IF($C3="","",IF(AND(ISNUMBER(AA3),ISNUMBER(AE3),AA3>0,AE3>0),ROUND(AA3*MAX(0,25-AE3),0),"")) -> 53572 | AE3: =IF($C3="","",IF(AA3>0,Z3/AA3,"")) -> 15.841046 | AF3: =IF($C3="","",IF(AE3="","—",IF(AE3<='⚙️ SUPUESTOS'!$C$32,"✔ Muy recomendable",IF(AE3<='⚙️ SUPUESTOS'!$C$33,"✔ Recomendable","Valorar")))) -> ✔ Recomendable | AG3: =IF('📇 INVENTARIO'!O4="","",'📇 INVENTARIO'!O4) -> 41.649797 | AH3: =IF('📇 INVENTARIO'!P4="","",'📇 INVENTARIO'!P4) -> -4.710882
A4: =IF($C4="","",RANK(O4,$O$3:$O$265,0)+COUNTIF($O$3:O4,O4)-1) -> 2 | B4: =IF($C4="","",IF(A4<='⚙️ SUPUESTOS'!$C$29,"Fase 1",IF(A4<='⚙️ SUPUESTOS'!$C$30,"Fase 2","Fase 3"))) -> Fase 1 | C4: =IF('📇 INVENTARIO'!B5="","",'📇 INVENTARIO'!B5) -> C/ Pavo Real, 21 | D4: =IF('📇 INVENTARIO'!C5="","",'📇 INVENTARIO'!C5) -> 7625404UM5172F | E4: =IF('📇 INVENTARIO'!D5="","",'📇 INVENTARIO'!D5) -> 4718606026 | F4: =IF('📇 INVENTARIO'!F5="","",'📇 INVENTARIO'!F5) -> G | G4: =IF('📇 INVENTARIO'!G5="","",'📇 INVENTARIO'!G5) -> 630 | H4: =IF('📇 INVENTARIO'!H5="","",'📇 INVENTARIO'!H5) -> 107 | I4: =IF('📇 INVENTARIO'!I5="","",'📇 INVENTARIO'!I5) -> 178.9 | J4: =IF('📇 INVENTARIO'!J5="","",'📇 INVENTARIO'!J5) -> 1965 | K4: =IF($C4="","",(G4-'⚙️ SUPUESTOS'!$C$20)/('⚙️ SUPUESTOS'!$C$25-'⚙️ SUPUESTOS'!$C$20)) -> 0.83820998 | L4: =IF($C4="","",VLOOKUP($E4,'📊 SECCIONES'!$B$4:$S$9,16,FALSE())) -> 1 | M4: =IF($C4="","",VLOOKUP($E4,'📊 SECCIONES'!$B$4:$S$9,17,FALSE())) -> 1 | N4: =IF($C4="","",VLOOKUP($E4,'📊 SECCIONES'!$B$4:$S$9,18,FALSE())) -> 0 | O4: =IF($C4="","",ROUND('⚙️ SUPUESTOS'!$C$21*K4+'⚙️ SUPUESTOS'!$C$22*L4+'⚙️ SUPUESTOS'!$C$23*M4+'⚙️ SUPUESTOS'!$C$24*N4,4)) -> 0.821 | P4: =IF($C4="","",VLOOKUP($E4,'📊 SECCIONES'!$B$4:$S$9,7,FALSE())) -> 66.51 | Q4: =IF($C4="","",VLOOKUP($E4,'📊 SECCIONES'!$B$4:$S$9,8,FALSE())) -> 17450 | R4: =IF($C4="","",VLOOKUP($E4,'📊 SECCIONES'!$B$4:$S$9,10,FALSE())) -> 10.6 | S4: =IF('📇 INVENTARIO'!K5="","",'📇 INVENTARIO'!K5) -> 3 | T4: =IF($C4="","","Objetivo: alcanzar calificación C. Actual: Cal."&F4&". "&IF(OR(F4="G",F4="F"),"SATE integral + cubierta + carpinterías triple + aerotermia + instalación fotovoltaica",IF(F4="E","SATE fachada + carpinterías doble + instalación fotovoltaica",IF(F4="D","Mantenimiento de envolvente + instalación fotovoltaica en cubierta","Optimización energética + instalación fotovoltaica")))) -> Objetivo: alcanzar calificación C. Actual: Cal.G. SATE integral + cubierta + carpinterías triple + aerotermia + instalación fotovoltaica | U4: =IF($C4="","",IF(S4=0,"s/d",IF(S4>=4,"Valorar ascensor (verificar)","—"))) -> — | V4: =IF('📇 INVENTARIO'!L5="","",'📇 INVENTARIO'!L5) -> 96.2 | W4: =IF($C4="","",V4*'⚙️ SUPUESTOS'!$C$8*'⚙️ SUPUESTOS'!$C$9) -> 20.202 | X4: =IF('📇 INVENTARIO'!N5="","",'📇 INVENTARIO'!N5) -> 1477 | Y4: =IF($C4="","",W4*X4*'⚙️ SUPUESTOS'!$C$7) -> 26854.519 | Z4: =IF($C4="","",W4*'⚙️ SUPUESTOS'!$C$10) -> 26969.67 | AA4: =IF($C4="","",Y4*('⚙️ SUPUESTOS'!$C$12*'⚙️ SUPUESTOS'!$C$11+(1-'⚙️ SUPUESTOS'!$C$12)*'⚙️ SUPUESTOS'!$C$13)) -> 1831.4782 | AB4: =IF($C4="","",IF(Y4>0,ROUND(Y4*'⚙️ SUPUESTOS'!$C$12*'⚙️ SUPUESTOS'!$C$11,0),"")) -> 671 | AC4: =IF($C4="","",IF(Y4>0,ROUND(Y4*(1-'⚙️ SUPUESTOS'!$C$12)*'⚙️ SUPUESTOS'!$C$13,0),"")) -> 1160 | AD4: =IF($C4="","",IF(AND(ISNUMBER(AA4),ISNUMBER(AE4),AA4>0,AE4>0),ROUND(AA4*MAX(0,25-AE4),0),"")) -> 18817 | AE4: =IF($C4="","",IF(AA4>0,Z4/AA4,"")) -> 14.72563 | AF4: =IF($C4="","",IF(AE4="","—",IF(AE4<='⚙️ SUPUESTOS'!$C$32,"✔ Muy recomendable",IF(AE4<='⚙️ SUPUESTOS'!$C$33,"✔ Recomendable","Valorar")))) -> ✔ Muy recomendable | AG4: =IF('📇 INVENTARIO'!O5="","",'📇 INVENTARIO'!O5) -> 41.64943 | AH4: =IF('📇 INVENTARIO'!P5="","",'📇 INVENTARIO'!P5) -> -4.71056
A5: =IF($C5="","",RANK(O5,$O$3:$O$265,0)+COUNTIF($O$3:O5,O5)-1) -> 3 | B5: =IF($C5="","",IF(A5<='⚙️ SUPUESTOS'!$C$29,"Fase 1",IF(A5<='⚙️ SUPUESTOS'!$C$30,"Fase 2","Fase 3"))) -> Fase 1 | C5: =IF('📇 INVENTARIO'!B6="","",'📇 INVENTARIO'!B6) -> C/ Salud, 17 | D5: =IF('📇 INVENTARIO'!C6="","",'📇 INVENTARIO'!C6) -> 7625401UM5172F | E5: =IF('📇 INVENTARIO'!D6="","",'📇 INVENTARIO'!D6) -> 4718606026 | F5: =IF('📇 INVENTARIO'!F6="","",'📇 INVENTARIO'!F6) -> G | G5: =IF('📇 INVENTARIO'!G6="","",'📇 INVENTARIO'!G6) -> 528 | H5: =IF('📇 INVENTARIO'!H6="","",'📇 INVENTARIO'!H6) -> 90 | I5: =IF('📇 INVENTARIO'!I6="","",'📇 INVENTARIO'!I6) -> 211 | J5: =IF('📇 INVENTARIO'!J6="","",'📇 INVENTARIO'!J6) -> 1958 | K5: =IF($C5="","",(G5-'⚙️ SUPUESTOS'!$C$20)/('⚙️ SUPUESTOS'!$C$25-'⚙️ SUPUESTOS'!$C$20)) -> 0.6626506 | L5: =IF($C5="","",VLOOKUP($E5,'📊 SECCIONES'!$B$4:$S$9,16,FALSE())) -> 1 | M5: =IF($C5="","",VLOOKUP($E5,'📊 SECCIONES'!$B$4:$S$9,17,FALSE())) -> 1 | N5: =IF($C5="","",VLOOKUP($E5,'📊 SECCIONES'!$B$4:$S$9,18,FALSE())) -> 0 | O5: =IF($C5="","",ROUND('⚙️ SUPUESTOS'!$C$21*K5+'⚙️ SUPUESTOS'!$C$22*L5+'⚙️ SUPUESTOS'!$C$23*M5+'⚙️ SUPUESTOS'!$C$24*N5,4)) -> 0.7245 | P5: =IF($C5="","",VLOOKUP($E5,'📊 SECCIONES'!$B$4:$S$9,7,FALSE())) -> 66.51 | Q5: =IF($C5="","",VLOOKUP($E5,'📊 SECCIONES'!$B$4:$S$9,8,FALSE())) -> 17450 | R5: =IF($C5="","",VLOOKUP($E5,'📊 SECCIONES'!$B$4:$S$9,10,FALSE())) -> 10.6 | S5: =IF('📇 INVENTARIO'!K6="","",'📇 INVENTARIO'!K6) -> 5 | T5: =IF($C5="","","Objetivo: alcanzar calificación C. Actual: Cal."&F5&". "&IF(OR(F5="G",F5="F"),"SATE integral + cubierta + carpinterías triple + aerotermia + instalación fotovoltaica",IF(F5="E","SATE fachada + carpinterías doble + instalación fotovoltaica",IF(F5="D","Mantenimiento de envolvente + instalación fotovoltaica en cubierta","Optimización energética + instalación fotovoltaica")))) -> Objetivo: alcanzar calificación C. Actual: Cal.G. SATE integral + cubierta + carpinterías triple + aerotermia + instalación fotovoltaica | U5: =IF($C5="","",IF(S5=0,"s/d",IF(S5>=4,"Valorar ascensor (verificar)","—"))) -> Valorar ascensor (verificar) | V5: =IF('📇 INVENTARIO'!L6="","",'📇 INVENTARIO'!L6) -> 330.5 | W5: =IF($C5="","",V5*'⚙️ SUPUESTOS'!$C$8*'⚙️ SUPUESTOS'!$C$9) -> 69.405 | X5: =IF('📇 INVENTARIO'!N6="","",'📇 INVENTARIO'!N6) -> 1373 | Y5: =IF($C5="","",W5*X5*'⚙️ SUPUESTOS'!$C$7) -> 85763.759 | Z5: =IF($C5="","",W5*'⚙️ SUPUESTOS'!$C$10) -> 92655.675 | AA5: =IF($C5="","",Y5*('⚙️ SUPUESTOS'!$C$12*'⚙️ SUPUESTOS'!$C$11+(1-'⚙️ SUPUESTOS'!$C$12)*'⚙️ SUPUESTOS'!$C$13)) -> 5849.0883 | AB5: =IF($C5="","",IF(Y5>0,ROUND(Y5*'⚙️ SUPUESTOS'!$C$12*'⚙️ SUPUESTOS'!$C$11,0),"")) -> 2144 | AC5: =IF($C5="","",IF(Y5>0,ROUND(Y5*(1-'⚙️ SUPUESTOS'!$C$12)*'⚙️ SUPUESTOS'!$C$13,0),"")) -> 3705 | AD5: =IF($C5="","",IF(AND(ISNUMBER(AA5),ISNUMBER(AE5),AA5>0,AE5>0),ROUND(AA5*MAX(0,25-AE5),0),"")) -> 53572 | AE5: =IF($C5="","",IF(AA5>0,Z5/AA5,"")) -> 15.841046 | AF5: =IF($C5="","",IF(AE5="","—",IF(AE5<='⚙️ SUPUESTOS'!$C$32,"✔ Muy recomendable",IF(AE5<='⚙️ SUPUESTOS'!$C$33,"✔ Recomendable","Valorar")))) -> ✔ Recomendable | AG5: =IF('📇 INVENTARIO'!O6="","",'📇 INVENTARIO'!O6) -> 41.649497 | AH5: =IF('📇 INVENTARIO'!P6="","",'📇 INVENTARIO'!P6) -> -4.711089
A6: =IF($C6="","",RANK(O6,$O$3:$O$265,0)+COUNTIF($O$3:O6,O6)-1) -> 4 | B6: =IF($C6="","",IF(A6<='⚙️ SUPUESTOS'!$C$29,"Fase 1",IF(A6<='⚙️ SUPUESTOS'!$C$30,"Fase 2","Fase 3"))) -> Fase 1 | C6: =IF('📇 INVENTARIO'!B7="","",'📇 INVENTARIO'!B7) -> C/ Halcón, 2 | D6: =IF('📇 INVENTARIO'!C7="","",'📇 INVENTARIO'!C7) -> 7925705UM5172F | E6: =IF('📇 INVENTARIO'!D7="","",'📇 INVENTARIO'!D7) -> 4718606023 | F6: =IF('📇 INVENTARIO'!F7="","",'📇 INVENTARIO'!F7) -> G | G6: =IF('📇 INVENTARIO'!G7="","",'📇 INVENTARIO'!G7) -> 646 | H6: =IF('📇 INVENTARIO'!H7="","",'📇 INVENTARIO'!H7) -> 110 | I6: =IF('📇 INVENTARIO'!I7="","",'📇 INVENTARIO'!I7) -> 218.2 | J6: =IF('📇 INVENTARIO'!J7="","",'📇 INVENTARIO'!J7) -> 1965 | K6: =IF($C6="","",(G6-'⚙️ SUPUESTOS'!$C$20)/('⚙️ SUPUESTOS'!$C$25-'⚙️ SUPUESTOS'!$C$20)) -> 0.86574871 | L6: =IF($C6="","",VLOOKUP($E6,'📊 SECCIONES'!$B$4:$S$9,16,FALSE())) -> 0.54128061 | M6: =IF($C6="","",VLOOKUP($E6,'📊 SECCIONES'!$B$4:$S$9,17,FALSE())) -> 0.59585492 | N6: =IF($C6="","",VLOOKUP($E6,'📊 SECCIONES'!$B$4:$S$9,18,FALSE())) -> 0.28636364 | O6: =IF($C6="","",ROUND('⚙️ SUPUESTOS'!$C$21*K6+'⚙️ SUPUESTOS'!$C$22*L6+'⚙️ SUPUESTOS'!$C$23*M6+'⚙️ SUPUESTOS'!$C$24*N6,4)) -> 0.7044 | P6: =IF($C6="","",VLOOKUP($E6,'📊 SECCIONES'!$B$4:$S$9,7,FALSE())) -> 39.41 | Q6: =IF($C6="","",VLOOKUP($E6,'📊 SECCIONES'!$B$4:$S$9,8,FALSE())) -> 22486 | R6: =IF($C6="","",VLOOKUP($E6,'📊 SECCIONES'!$B$4:$S$9,10,FALSE())) -> 16.9 | S6: =IF('📇 INVENTARIO'!K7="","",'📇 INVENTARIO'!K7) -> 3 | T6: =IF($C6="","","Objetivo: alcanzar calificación C. Actual: Cal."&F6&". "&IF(OR(F6="G",F6="F"),"SATE integral + cubierta + carpinterías triple + aerotermia + instalación fotovoltaica",IF(F6="E","SATE fachada + carpinterías doble + instalación fotovoltaica",IF(F6="D","Mantenimiento de envolvente + instalación fotovoltaica en cubierta","Optimización energética + instalación fotovoltaica")))) -> Objetivo: alcanzar calificación C. Actual: Cal.G. SATE integral + cubierta + carpinterías triple + aerotermia + instalación fotovoltaica | U6: =IF($C6="","",IF(S6=0,"s/d",IF(S6>=4,"Valorar ascensor (verificar)","—"))) -> — | V6: =IF('📇 INVENTARIO'!L7="","",'📇 INVENTARIO'!L7) -> 102.1 | W6: =IF($C6="","",V6*'⚙️ SUPUESTOS'!$C$8*'⚙️ SUPUESTOS'!$C$9) -> 21.441 | X6: =IF('📇 INVENTARIO'!N7="","",'📇 INVENTARIO'!N7) -> 1380 | Y6: =IF($C6="","",W6*X6*'⚙️ SUPUESTOS'!$C$7) -> 26629.722 | Z6: =IF($C6="","",W6*'⚙️ SUPUESTOS'!$C$10) -> 28623.735 | AA6: =IF($C6="","",Y6*('⚙️ SUPUESTOS'!$C$12*'⚙️ SUPUESTOS'!$C$11+(1-'⚙️ SUPUESTOS'!$C$12)*'⚙️ SUPUESTOS'!$C$13)) -> 1816.147 | AB6: =IF($C6="","",IF(Y6>0,ROUND(Y6*'⚙️ SUPUESTOS'!$C$12*'⚙️ SUPUESTOS'!$C$11,0),"")) -> 666 | AC6: =IF($C6="","",IF(Y6>0,ROUND(Y6*(1-'⚙️ SUPUESTOS'!$C$12)*'⚙️ SUPUESTOS'!$C$13,0),"")) -> 1150 | AD6: =IF($C6="","",IF(AND(ISNUMBER(AA6),ISNUMBER(AE6),AA6>0,AE6>0),ROUND(AA6*MAX(0,25-AE6),0),"")) -> 16780 | AE6: =IF($C6="","",IF(AA6>0,Z6/AA6,"")) -> 15.760692 | AF6: =IF($C6="","",IF(AE6="","—",IF(AE6<='⚙️ SUPUESTOS'!$C$32,"✔ Muy recomendable",IF(AE6<='⚙️ SUPUESTOS'!$C$33,"✔ Recomendable","Valorar")))) -> ✔ Recomendable | AG6: =IF('📇 INVENTARIO'!O7="","",'📇 INVENTARIO'!O7) -> 41.64986 | AH6: =IF('📇 INVENTARIO'!P7="","",'📇 INVENTARIO'!P7) -> -4.70842
A7: =IF($C7="","",RANK(O7,$O$3:$O$265,0)+COUNTIF($O$3:O7,O7)-1) -> 5 | B7: =IF($C7="","",IF(A7<='⚙️ SUPUESTOS'!$C$29,"Fase 1",IF(A7<='⚙️ SUPUESTOS'!$C$30,"Fase 2","Fase 3"))) -> Fase 1 | C7: =IF('📇 INVENTARIO'!B8="","",'📇 INVENTARIO'!B8) -> C/ Rincón del Esgueva, 13 | D7: =IF('📇 INVENTARIO'!C8="","",'📇 INVENTARIO'!C8) -> 7726409UM5172F | E7: =IF('📇 INVENTARIO'!D8="","",'📇 INVENTARIO'!D8) -> 4718606023 | F7: =IF('📇 INVENTARIO'!F8="","",'📇 INVENTARIO'!F8) -> G | G7: =IF('📇 INVENTARIO'!G8="","",'📇 INVENTARIO'!G8) -> 634 | H7: =IF('📇 INVENTARIO'!H8="","",'📇 INVENTARIO'!H8) -> 134 | I7: =IF('📇 INVENTARIO'!I8="","",'📇 INVENTARIO'!I8) -> 334.2 | J7: =IF('📇 INVENTARIO'!J8="","",'📇 INVENTARIO'!J8) -> 1936 | K7: =IF($C7="","",(G7-'⚙️ SUPUESTOS'!$C$20)/('⚙️ SUPUESTOS'!$C$25-'⚙️ SUPUESTOS'!$C$20)) -> 0.84509466 | L7: =IF($C7="","",VLOOKUP($E7,'📊 SECCIONES'!$B$4:$S$9,16,FALSE())) -> 0.54128061 | M7: =IF($C7="","",VLOOKUP($E7,'📊 SECCIONES'!$B$4:$S$9,17,FALSE())) -> 0.59585492 | N7: =IF($C7="","",VLOOKUP($E7,'📊 SECCIONES'!$B$4:$S$9,18,FALSE())) -> 0.28636364 | O7: =IF($C7="","",ROUND('⚙️ SUPUESTOS'!$C$21*K7+'⚙️ SUPUESTOS'!$C$22*L7+'⚙️ SUPUESTOS'!$C$23*M7+'⚙️ SUPUESTOS'!$C$24*N7,4)) -> 0.6931 | P7: =IF($C7="","",VLOOKUP($E7,'📊 SECCIONES'!$B$4:$S$9,7,FALSE())) -> 39.41 | Q7: =IF($C7="","",VLOOKUP($E7,'📊 SECCIONES'!$B$4:$S$9,8,FALSE())) -> 22486 | R7: =IF($C7="","",VLOOKUP($E7,'📊 SECCIONES'!$B$4:$S$9,10,FALSE())) -> 16.9 | S7: =IF('📇 INVENTARIO'!K8="","",'📇 INVENTARIO'!K8) -> 1 | T7: =IF($C7="","","Objetivo: alcanzar calificación C. Actual: Cal."&F7&". "&IF(OR(F7="G",F7="F"),"SATE integral + cubierta + carpinterías triple + aerotermia + instalación fotovoltaica",IF(F7="E","SATE fachada + carpinterías doble + instalación fotovoltaica",IF(F7="D","Mantenimiento de envolvente + instalación fotovoltaica en cubierta","Optimización energética + instalación fotovoltaica")))) -> Objetivo: alcanzar calificación C. Actual: Cal.G. SATE integral + cubierta + carpinterías triple + aerotermia + instalación fotovoltaica | U7: =IF($C7="","",IF(S7=0,"s/d",IF(S7>=4,"Valorar ascensor (verificar)","—"))) -> — | V7: =IF('📇 INVENTARIO'!L8="","",'📇 INVENTARIO'!L8) -> 53.6 | W7: =IF($C7="","",V7*'⚙️ SUPUESTOS'!$C$8*'⚙️ SUPUESTOS'!$C$9) -> 11.256 | X7: =IF('📇 INVENTARIO'!N8="","",'📇 INVENTARIO'!N8) -> 1515 | Y7: =IF($C7="","",W7*X7*'⚙️ SUPUESTOS'!$C$7) -> 15347.556 | Z7: =IF($C7="","",W7*'⚙️ SUPUESTOS'!$C$10) -> 15026.76 | AA7: =IF($C7="","",Y7*('⚙️ SUPUESTOS'!$C$12*'⚙️ SUPUESTOS'!$C$11+(1-'⚙️ SUPUESTOS'!$C$12)*'⚙️ SUPUESTOS'!$C$13)) -> 1046.7033 | AB7: =IF($C7="","",IF(Y7>0,ROUND(Y7*'⚙️ SUPUESTOS'!$C$12*'⚙️ SUPUESTOS'!$C$11,0),"")) -> 384 | AC7: =IF($C7="","",IF(Y7>0,ROUND(Y7*(1-'⚙️ SUPUESTOS'!$C$12)*'⚙️ SUPUESTOS'!$C$13,0),"")) -> 663 | AD7: =IF($C7="","",IF(AND(ISNUMBER(AA7),ISNUMBER(AE7),AA7>0,AE7>0),ROUND(AA7*MAX(0,25-AE7),0),"")) -> 11141 | AE7: =IF($C7="","",IF(AA7>0,Z7/AA7,"")) -> 14.356274 | AF7: =IF($C7="","",IF(AE7="","—",IF(AE7<='⚙️ SUPUESTOS'!$C$32,"✔ Muy recomendable",IF(AE7<='⚙️ SUPUESTOS'!$C$33,"✔ Recomendable","Valorar")))) -> ✔ Muy recomendable | AG7: =IF('📇 INVENTARIO'!O8="","",'📇 INVENTARIO'!O8) -> 41.65012 | AH7: =IF('📇 INVENTARIO'!P8="","",'📇 INVENTARIO'!P8) -> -4.70963
A8: =IF($C8="","",RANK(O8,$O$3:$O$265,0)+COUNTIF($O$3:O8,O8)-1) -> 6 | B8: =IF($C8="","",IF(A8<='⚙️ SUPUESTOS'!$C$29,"Fase 1",IF(A8<='⚙️ SUPUESTOS'!$C$30,"Fase 2","Fase 3"))) -> Fase 1 | C8: =IF('📇 INVENTARIO'!B9="","",'📇 INVENTARIO'!B9) -> C/ Calandria, 4 | D8: =IF('📇 INVENTARIO'!C9="","",'📇 INVENTARIO'!C9) -> 7925710UM5172F | E8: =IF('📇 INVENTARIO'!D9="","",'📇 INVENTARIO'!D9) -> 4718606023 | F8: =IF('📇 INVENTARIO'!F9="","",'📇 INVENTARIO'!F9) -> G | G8: =IF('📇 INVENTARIO'!G9="","",'📇 INVENTARIO'!G9) -> 632 | H8: =IF('📇 INVENTARIO'!H9="","",'📇 INVENTARIO'!H9) -> 134 | I8: =IF('📇 INVENTARIO'!I9="","",'📇 INVENTARIO'!I9) -> 251.9 | J8: =IF('📇 INVENTARIO'!J9="","",'📇 INVENTARIO'!J9) -> 1965 | K8: =IF($C8="","",(G8-'⚙️ SUPUESTOS'!$C$20)/('⚙️ SUPUESTOS'!$C$25-'⚙️ SUPUESTOS'!$C$20)) -> 0.84165232 | L8: =IF($C8="","",VLOOKUP($E8,'📊 SECCIONES'!$B$4:$S$9,16,FALSE())) -> 0.54128061 | M8: =IF($C8="","",VLOOKUP($E8,'📊 SECCIONES'!$B$4:$S$9,17,FALSE())) -> 0.59585492 | N8: =IF($C8="","",VLOOKUP($E8,'📊 SECCIONES'!$B$4:$S$9,18,FALSE())) -> 0.28636364 | O8: =IF($C8="","",ROUND('⚙️ SUPUESTOS'!$C$21*K8+'⚙️ SUPUESTOS'!$C$22*L8+'⚙️ SUPUESTOS'!$C$23*M8+'⚙️ SUPUESTOS'!$C$24*N8,4)) -> 0.6912 | P8: =IF($C8="","",VLOOKUP($E8,'📊 SECCIONES'!$B$4:$S$9,7,FALSE())) -> 39.41 | Q8: =IF($C8="","",VLOOKUP($E8,'📊 SECCIONES'!$B$4:$S$9,8,FALSE())) -> 22486 | R8: =IF($C8="","",VLOOKUP($E8,'📊 SECCIONES'!$B$4:$S$9,10,FALSE())) -> 16.9 | S8: =IF('📇 INVENTARIO'!K9="","",'📇 INVENTARIO'!K9) -> 3 | T8: =IF($C8="","","Objetivo: alcanzar calificación C. Actual: Cal."&F8&". "&IF(OR(F8="G",F8="F"),"SATE integral + cubierta + carpinterías triple + aerotermia + instalación fotovoltaica",IF(F8="E","SATE fachada + carpinterías doble + instalación fotovoltaica",IF(F8="D","Mantenimiento de envolvente + instalación fotovoltaica en cubierta","Optimización energética + instalación fotovoltaica")))) -> Objetivo: alcanzar calificación C. Actual: Cal.G. SATE integral + cubierta + carpinterías triple + aerotermia + instalación fotovoltaica | U8: =IF($C8="","",IF(S8=0,"s/d",IF(S8>=4,"Valorar ascensor (verificar)","—"))) -> — | V8: =IF('📇 INVENTARIO'!L9="","",'📇 INVENTARIO'!L9) -> 101.6 | W8: =IF($C8="","",V8*'⚙️ SUPUESTOS'!$C$8*'⚙️ SUPUESTOS'!$C$9) -> 21.336 | X8: =IF('📇 INVENTARIO'!N9="","",'📇 INVENTARIO'!N9) -> 1366 | Y8: =IF($C8="","",W8*X8*'⚙️ SUPUESTOS'!$C$7) -> 26230.478 | Z8: =IF($C8="","",W8*'⚙️ SUPUESTOS'!$C$10) -> 28483.56 | AA8: =IF($C8="","",Y8*('⚙️ SUPUESTOS'!$C$12*'⚙️ SUPUESTOS'!$C$11+(1-'⚙️ SUPUESTOS'!$C$12)*'⚙️ SUPUESTOS'!$C$13)) -> 1788.9186 | AB8: =IF($C8="","",IF(Y8>0,ROUND(Y8*'⚙️ SUPUESTOS'!$C$12*'⚙️ SUPUESTOS'!$C$11,0),"")) -> 656 | AC8: =IF($C8="","",IF(Y8>0,ROUND(Y8*(1-'⚙️ SUPUESTOS'!$C$12)*'⚙️ SUPUESTOS'!$C$13,0),"")) -> 1133 | AD8: =IF($C8="","",IF(AND(ISNUMBER(AA8),ISNUMBER(AE8),AA8>0,AE8>0),ROUND(AA8*MAX(0,25-AE8),0),"")) -> 16239 | AE8: =IF($C8="","",IF(AA8>0,Z8/AA8,"")) -> 15.922222 | AF8: =IF($C8="","",IF(AE8="","—",IF(AE8<='⚙️ SUPUESTOS'!$C$32,"✔ Muy recomendable",IF(AE8<='⚙️ SUPUESTOS'!$C$33,"✔ Recomendable","Valorar")))) -> ✔ Recomendable | AG8: =IF('📇 INVENTARIO'!O9="","",'📇 INVENTARIO'!O9) -> 41.64975 | AH8: =IF('📇 INVENTARIO'!P9="","",'📇 INVENTARIO'!P9) -> -4.70784
A9: =IF($C9="","",RANK(O9,$O$3:$O$265,0)+COUNTIF($O$3:O9,O9)-1) -> 7 | B9: =IF($C9="","",IF(A9<='⚙️ SUPUESTOS'!$C$29,"Fase 1",IF(A9<='⚙️ SUPUESTOS'!$C$30,"Fase 2","Fase 3"))) -> Fase 1 | C9: =IF('📇 INVENTARIO'!B11="","",'📇 INVENTARIO'!B11) -> C/ Marabú, 1 | D9: =IF('📇 INVENTARIO'!C11="","",'📇 INVENTARIO'!C11) -> 7924213UM5172D | E9: =IF('📇 INVENTARIO'!D11="","",'📇 INVENTARIO'!D11) -> 4718606024 | F9: =IF('📇 INVENTARIO'!F11="","",'📇 INVENTARIO'!F11) -> G | G9: =IF('📇 INVENTARIO'!G11="","",'📇 INVENTARIO'!G11) -> 724 | H9: =IF('📇 INVENTARIO'!H11="","",'📇 INVENTARIO'!H11) -> 148 | I9: =IF('📇 INVENTARIO'!I11="","",'📇 INVENTARIO'!I11) -> 374.5 | J9: =IF('📇 INVENTARIO'!J11="","",'📇 INVENTARIO'!J11) -> 1965 | K9: =IF($C9="","",(G9-'⚙️ SUPUESTOS'!$C$20)/('⚙️ SUPUESTOS'!$C$25-'⚙️ SUPUESTOS'!$C$20)) -> 1 | L9: =IF($C9="","",VLOOKUP($E9,'📊 SECCIONES'!$B$4:$S$9,16,FALSE())) -> 0.13391193 | M9: =IF($C9="","",VLOOKUP($E9,'📊 SECCIONES'!$B$4:$S$9,17,FALSE())) -> 0.16476684 | N9: =IF($C9="","",VLOOKUP($E9,'📊 SECCIONES'!$B$4:$S$9,18,FALSE())) -> 0.79545455 | O9: =IF($C9="","",ROUND('⚙️ SUPUESTOS'!$C$21*K9+'⚙️ SUPUESTOS'!$C$22*L9+'⚙️ SUPUESTOS'!$C$23*M9+'⚙️ SUPUESTOS'!$C$24*N9,4)) -> 0.6741 | P9: =IF($C9="","",VLOOKUP($E9,'📊 SECCIONES'!$B$4:$S$9,7,FALSE())) -> 30.06 | Q9: =IF($C9="","",VLOOKUP($E9,'📊 SECCIONES'!$B$4:$S$9,8,FALSE())) -> 25132 | R9: =IF($C9="","",VLOOKUP($E9,'📊 SECCIONES'!$B$4:$S$9,10,FALSE())) -> 28.1 | S9: =IF('📇 INVENTARIO'!K11="","",'📇 INVENTARIO'!K11) -> 3 | T9: =IF($C9="","","Objetivo: alcanzar calificación C. Actual: Cal."&F9&". "&IF(OR(F9="G",F9="F"),"SATE integral + cubierta + carpinterías triple + aerotermia + instalación fotovoltaica",IF(F9="E","SATE fachada + carpinterías doble + instalación fotovoltaica",IF(F9="D","Mantenimiento de envolvente + instalación fotovoltaica en cubierta","Optimización energética + instalación fotovoltaica")))) -> Objetivo: alcanzar calificación C. Actual: Cal.G. SATE integral + cubierta + carpinterías triple + aerotermia + instalación fotovoltaica | U9: =IF($C9="","",IF(S9=0,"s/d",IF(S9>=4,"Valorar ascensor (verificar)","—"))) -> — | V9: =IF('📇 INVENTARIO'!L11="","",'📇 INVENTARIO'!L11) -> 97.4 | W9: =IF($C9="","",V9*'⚙️ SUPUESTOS'!$C$8*'⚙️ SUPUESTOS'!$C$9) -> 20.454 | X9: =IF('📇 INVENTARIO'!N11="","",'📇 INVENTARIO'!N11) -> 1394 | Y9: =IF($C9="","",W9*X9*'⚙️ SUPUESTOS'!$C$7) -> 25661.588 | Z9: =IF($C9="","",W9*'⚙️ SUPUESTOS'!$C$10) -> 27306.09 | AA9: =IF($C9="","",Y9*('⚙️ SUPUESTOS'!$C$12*'⚙️ SUPUESTOS'!$C$11+(1-'⚙️ SUPUESTOS'!$C$12)*'⚙️ SUPUESTOS'!$C$13)) -> 1750.1203 | AB9: =IF($C9="","",IF(Y9>0,ROUND(Y9*'⚙️ SUPUESTOS'!$C$12*'⚙️ SUPUESTOS'!$C$11,0),"")) -> 642 | AC9: =IF($C9="","",IF(Y9>0,ROUND(Y9*(1-'⚙️ SUPUESTOS'!$C$12)*'⚙️ SUPUESTOS'!$C$13,0),"")) -> 1109 | AD9: =IF($C9="","",IF(AND(ISNUMBER(AA9),ISNUMBER(AE9),AA9>0,AE9>0),ROUND(AA9*MAX(0,25-AE9),0),"")) -> 16447 | AE9: =IF($C9="","",IF(AA9>0,Z9/AA9,"")) -> 15.602407 | AF9: =IF($C9="","",IF(AE9="","—",IF(AE9<='⚙️ SUPUESTOS'!$C$32,"✔ Muy recomendable",IF(AE9<='⚙️ SUPUESTOS'!$C$33,"✔ Recomendable","Valorar")))) -> ✔ Recomendable | AG9: =IF('📇 INVENTARIO'!O10="","",'📇 INVENTARIO'!O10) -> 41.64922 | AH9: =IF('📇 INVENTARIO'!P10="","",'📇 INVENTARIO'!P10) -> -4.71073
A10: =IF($C10="","",RANK(O10,$O$3:$O$265,0)+COUNTIF($O$3:O10,O10)-1) -> 8 | B10: =IF($C10="","",IF(A10<='⚙️ SUPUESTOS'!$C$29,"Fase 1",IF(A10<='⚙️ SUPUESTOS'!$C$30,"Fase 2","Fase 3"))) -> Fase 1 | C10: =IF('📇 INVENTARIO'!B10="","",'📇 INVENTARIO'!B10) -> C/ Pavo Real, 17 | D10: =IF('📇 INVENTARIO'!C10="","",'📇 INVENTARIO'!C10) -> 7625406UM5172F | E10: =IF('📇 INVENTARIO'!D10="","",'📇 INVENTARIO'!D10) -> 4718606026 | F10: =IF('📇 INVENTARIO'!F10="","",'📇 INVENTARIO'!F10) -> G | G10: =IF('📇 INVENTARIO'!G10="","",'📇 INVENTARIO'!G10) -> 464 | H10: =IF('📇 INVENTARIO'!H10="","",'📇 INVENTARIO'!H10) -> 118 | I10: =IF('📇 INVENTARIO'!I10="","",'📇 INVENTARIO'!I10) -> 180.2 | J10: =IF('📇 INVENTARIO'!J10="","",'📇 INVENTARIO'!J10) -> 1965 | K10: =IF($C10="","",(G10-'⚙️ SUPUESTOS'!$C$20)/('⚙️ SUPUESTOS'!$C$25-'⚙️ SUPUESTOS'!$C$20)) -> 0.5524957 | L10: =IF($C10="","",VLOOKUP($E10,'📊 SECCIONES'!$B$4:$S$9,16,FALSE())) -> 1 | M10: =IF($C10="","",VLOOKUP($E10,'📊 SECCIONES'!$B$4:$S$9,17,FALSE())) -> 1 | N10: =IF($C10="","",VLOOKUP($E10,'📊 SECCIONES'!$B$4:$S$9,18,FALSE())) -> 0 | O10: =IF($C10="","",ROUND('⚙️ SUPUESTOS'!$C$21*K10+'⚙️ SUPUESTOS'!$C$22*L10+'⚙️ SUPUESTOS'!$C$23*M10+'⚙️ SUPUESTOS'!$C$24*N10,4)) -> 0.6639 | P10: =IF($C10="","",VLOOKUP($E10,'📊 SECCIONES'!$B$4:$S$9,7,FALSE())) -> 66.51 | Q10: =IF($C10="","",VLOOKUP($E10,'📊 SECCIONES'!$B$4:$S$9,8,FALSE())) -> 17450 | R10: =IF($C10="","",VLOOKUP($E10,'📊 SECCIONES'!$B$4:$S$9,10,FALSE())) -> 10.6 | S10: =IF('📇 INVENTARIO'!K10="","",'📇 INVENTARIO'!K10) -> 3 | T10: =IF($C10="","","Objetivo: alcanzar calificación C. Actual: Cal."&F10&". "&IF(OR(F10="G",F10="F"),"SATE integral + cubierta + carpinterías triple + aerotermia + instalación fotovoltaica",IF(F10="E","SATE fachada + carpinterías doble + instalación fotovoltaica",IF(F10="D","Mantenimiento de envolvente + instalación fotovoltaica en cubierta","Optimización energética + instalación fotovoltaica")))) -> Objetivo: alcanzar calificación C. Actual: Cal.G. SATE integral + cubierta + carpinterías triple + aerotermia + instalación fotovoltaica | U10: =IF($C10="","",IF(S10=0,"s/d",IF(S10>=4,"Valorar ascensor (verificar)","—"))) -> — | V10: =IF('📇 INVENTARIO'!L10="","",'📇 INVENTARIO'!L10) -> 95.1 | W10: =IF($C10="","",V10*'⚙️ SUPUESTOS'!$C$8*'⚙️ SUPUESTOS'!$C$9) -> 19.971 | X10: =IF('📇 INVENTARIO'!N10="","",'📇 INVENTARIO'!N10) -> 1467 | Y10: =IF($C10="","",W10*X10*'⚙️ SUPUESTOS'!$C$7) -> 26367.711 | Z10: =IF($C10="","",W10*'⚙️ SUPUESTOS'!$C$10) -> 26661.285 | AA10: =IF($C10="","",Y10*('⚙️ SUPUESTOS'!$C$12*'⚙️ SUPUESTOS'!$C$11+(1-'⚙️ SUPUESTOS'!$C$12)*'⚙️ SUPUESTOS'!$C$13)) -> 1798.2779 | AB10: =IF($C10="","",IF(Y10>0,ROUND(Y10*'⚙️ SUPUESTOS'!$C$12*'⚙️ SUPUESTOS'!$C$11,0),"")) -> 659 | AC10: =IF($C10="","",IF(Y10>0,ROUND(Y10*(1-'⚙️ SUPUESTOS'!$C$12)*'⚙️ SUPUESTOS'!$C$13,0),"")) -> 1139 | AD10: =IF($C10="","",IF(AND(ISNUMBER(AA10),ISNUMBER(AE10),AA10>0,AE10>0),ROUND(AA10*MAX(0,25-AE10),0),"")) -> 18296 | AE10: =IF($C10="","",IF(AA10>0,Z10/AA10,"")) -> 14.826009 | AF10: =IF($C10="","",IF(AE10="","—",IF(AE10<='⚙️ SUPUESTOS'!$C$32,"✔ Muy recomendable",IF(AE10<='⚙️ SUPUESTOS'!$C$33,"✔ Recomendable","Valorar")))) -> ✔ Muy recomendable | AG10: =IF('📇 INVENTARIO'!O11="","",'📇 INVENTARIO'!O11) -> 41.64934 | AH10: =IF('📇 INVENTARIO'!P11="","",'📇 INVENTARIO'!P11) -> -4.70757
A11: =IF($C11="","",RANK(O11,$O$3:$O$265,0)+COUNTIF($O$3:O11,O11)-1) -> 9 | B11: =IF($C11="","",IF(A11<='⚙️ SUPUESTOS'!$C$29,"Fase 1",IF(A11<='⚙️ SUPUESTOS'!$C$30,"Fase 2","Fase 3"))) -> Fase 1 | C11: =IF('📇 INVENTARIO'!B12="","",'📇 INVENTARIO'!B12) -> C/ Águila, 20 | D11: =IF('📇 INVENTARIO'!C12="","",'📇 INVENTARIO'!C12) -> 7824519UM5172D | E11: =IF('📇 INVENTARIO'!D12="","",'📇 INVENTARIO'!D12) -> 4718606026 | F11: =IF('📇 INVENTARIO'!F12="","",'📇 INVENTARIO'!F12) -> G | G11: =IF('📇 INVENTARIO'!G12="","",'📇 INVENTARIO'!G12) -> 461 | H11: =IF('📇 INVENTARIO'!H12="","",'📇 INVENTARIO'!H12) -> 79 | I11: =IF('📇 INVENTARIO'!I12="","",'📇 INVENTARIO'!I12) -> 155.4 | J11: =IF('📇 INVENTARIO'!J12="","",'📇 INVENTARIO'!J12) -> 1965 | K11: =IF($C11="","",(G11-'⚙️ SUPUESTOS'!$C$20)/('⚙️ SUPUESTOS'!$C$25-'⚙️ SUPUESTOS'!$C$20)) -> 0.54733219 | L11: =IF($C11="","",VLOOKUP($E11,'📊 SECCIONES'!$B$4:$S$9,16,FALSE())) -> 1 | M11: =IF($C11="","",VLOOKUP($E11,'📊 SECCIONES'!$B$4:$S$9,17,FALSE())) -> 1 | N11: =IF($C11="","",VLOOKUP($E11,'📊 SECCIONES'!$B$4:$S$9,18,FALSE())) -> 0 | O11: =IF($C11="","",ROUND('⚙️ SUPUESTOS'!$C$21*K11+'⚙️ SUPUESTOS'!$C$22*L11+'⚙️ SUPUESTOS'!$C$23*M11+'⚙️ SUPUESTOS'!$C$24*N11,4)) -> 0.661 | P11: =IF($C11="","",VLOOKUP($E11,'📊 SECCIONES'!$B$4:$S$9,7,FALSE())) -> 66.51 | Q11: =IF($C11="","",VLOOKUP($E11,'📊 SECCIONES'!$B$4:$S$9,8,FALSE())) -> 17450 | R11: =IF($C11="","",VLOOKUP($E11,'📊 SECCIONES'!$B$4:$S$9,10,FALSE())) -> 10.6 | S11: =IF('📇 INVENTARIO'!K12="","",'📇 INVENTARIO'!K12) -> 3 | T11: =IF($C11="","","Objetivo: alcanzar calificación C. Actual: Cal."&F11&". "&IF(OR(F11="G",F11="F"),"SATE integral + cubierta + carpinterías triple + aerotermia + instalación fotovoltaica",IF(F11="E","SATE fachada + carpinterías doble + instalación fotovoltaica",IF(F11="D","Mantenimiento de envolvente + instalación fotovoltaica en cubierta","Optimización energética + instalación fotovoltaica")))) -> Objetivo: alcanzar calificación C. Actual: Cal.G. SATE integral + cubierta + carpinterías triple + aerotermia + instalación fotovoltaica | U11: =IF($C11="","",IF(S11=0,"s/d",IF(S11>=4,"Valorar ascensor (verificar)","—"))) -> — | V11: =IF('📇 INVENTARIO'!L12="","",'📇 INVENTARIO'!L12) -> 110.7 | W11: =IF($C11="","",V11*'⚙️ SUPUESTOS'!$C$8*'⚙️ SUPUESTOS'!$C$9) -> 23.247 | X11: =IF('📇 INVENTARIO'!N12="","",'📇 INVENTARIO'!N12) -> 1517 | Y11: =IF($C11="","",W11*X11*'⚙️ SUPUESTOS'!$C$7) -> 31739.129 | Z11: =IF($C11="","",W11*'⚙️ SUPUESTOS'!$C$10) -> 31034.745 | AA11: =IF($C11="","",Y11*('⚙️ SUPUESTOS'!$C$12*'⚙️ SUPUESTOS'!$C$11+(1-'⚙️ SUPUESTOS'!$C$12)*'⚙️ SUPUESTOS'!$C$13)) -> 2164.6086 | AB11: =IF($C11="","",IF(Y11>0,ROUND(Y11*'⚙️ SUPUESTOS'!$C$12*'⚙️ SUPUESTOS'!$C$11,0),"")) -> 793 | AC11: =IF($C11="","",IF(Y11>0,ROUND(Y11*(1-'⚙️ SUPUESTOS'!$C$12)*'⚙️ SUPUESTOS'!$C$13,0),"")) -> 1371 | AD11: =IF($C11="","",IF(AND(ISNUMBER(AA11),ISNUMBER(AE11),AA11>0,AE11>0),ROUND(AA11*MAX(0,25-AE11),0),"")) -> 23080 | AE11: =IF($C11="","",IF(AA11>0,Z11/AA11,"")) -> 14.337347 | AF11: =IF($C11="","",IF(AE11="","—",IF(AE11<='⚙️ SUPUESTOS'!$C$32,"✔ Muy recomendable",IF(AE11<='⚙️ SUPUESTOS'!$C$33,"✔ Recomendable","Valorar")))) -> ✔ Muy recomendable | AG11: =IF('📇 INVENTARIO'!O12="","",'📇 INVENTARIO'!O12) -> 41.64889 | AH11: =IF('📇 INVENTARIO'!P12="","",'📇 INVENTARIO'!P12) -> -4.70906
A12: =IF($C12="","",RANK(O12,$O$3:$O$265,0)+COUNTIF($O$3:O12,O12)-1) -> 10 | B12: =IF($C12="","",IF(A12<='⚙️ SUPUESTOS'!$C$29,"Fase 1",IF(A12<='⚙️ SUPUESTOS'!$C$30,"Fase 2","Fase 3"))) -> Fase 1 | C12: =IF('📇 INVENTARIO'!B13="","",'📇 INVENTARIO'!B13) -> C/ Albatros, 1 | D12: =IF('📇 INVENTARIO'!C13="","",'📇 INVENTARIO'!C13) -> 7724226UM5172D | E12: =IF('📇 INVENTARIO'!D13="","",'📇 INVENTARIO'!D13) -> 4718606026 | F12: =IF('📇 INVENTARIO'!F13="","",'📇 INVENTARIO'!F13) -> G | G12: =IF('📇 INVENTARIO'!G13="","",'📇 INVENTARIO'!G13) -> 454 | H12: =IF('📇 INVENTARIO'!H13="","",'📇 INVENTARIO'!H13) -> 96 | I12: =IF('📇 INVENTARIO'!I13="","",'📇 INVENTARIO'!I13) -> 173.2 | J12: =IF('📇 INVENTARIO'!J13="","",'📇 INVENTARIO'!J13) -> 1965 | K12: =IF($C12="","",(G12-'⚙️ SUPUESTOS'!$C$20)/('⚙️ SUPUESTOS'!$C$25-'⚙️ SUPUESTOS'!$C$20)) -> 0.53528399 | L12: =IF($C12="","",VLOOKUP($E12,'📊 SECCIONES'!$B$4:$S$9,16,FALSE())) -> 1 | M12: =IF($C12="","",VLOOKUP($E12,'📊 SECCIONES'!$B$4:$S$9,17,FALSE())) -> 1 | N12: =IF($C12="","",VLOOKUP($E12,'📊 SECCIONES'!$B$4:$S$9,18,FALSE())) -> 0 | O12: =IF($C12="","",ROUND('⚙️ SUPUESTOS'!$C$21*K12+'⚙️ SUPUESTOS'!$C$22*L12+'⚙️ SUPUESTOS'!$C$23*M12+'⚙️ SUPUESTOS'!$C$24*N12,4)) -> 0.6544 | P12: =IF($C12="","",VLOOKUP($E12,'📊 SECCIONES'!$B$4:$S$9,7,FALSE())) -> 66.51 | Q12: =IF($C12="","",VLOOKUP($E12,'📊 SECCIONES'!$B$4:$S$9,8,FALSE())) -> 17450 | R12: =IF($C12="","",VLOOKUP($E12,'📊 SECCIONES'!$B$4:$S$9,10,FALSE())) -> 10.6 | S12: =IF('📇 INVENTARIO'!K13="","",'📇 INVENTARIO'!K13) -> 3 | T12: =IF($C12="","","Objetivo: alcanzar calificación C. Actual: Cal."&F12&". "&IF(OR(F12="G",F12="F"),"SATE integral + cubierta + carpinterías triple + aerotermia + instalación fotovoltaica",IF(F12="E","SATE fachada + carpinterías doble + instalación fotovoltaica",IF(F12="D","Mantenimiento de envolvente + instalación fotovoltaica en cubierta","Optimización energética + instalación fotovoltaica")))) -> Objetivo: alcanzar calificación C. Actual: Cal.G. SATE integral + cubierta + carpinterías triple + aerotermia + instalación fotovoltaica | U12: =IF($C12="","",IF(S12=0,"s/d",IF(S12>=4,"Valorar ascensor (verificar)","—"))) -> — | V12: =IF('📇 INVENTARIO'!L13="","",'📇 INVENTARIO'!L13) -> 95.5 | W12: =IF($C12="","",V12*'⚙️ SUPUESTOS'!$C$8*'⚙️ SUPUESTOS'!$C$9) -> 20.055 | X12: =IF('📇 INVENTARIO'!N13="","",'📇 INVENTARIO'!N13) -> 1431 | Y12: =IF($C12="","",W12*X12*'⚙️ SUPUESTOS'!$C$7) -> 25828.834 | Z12: =IF($C12="","",W12*'⚙️ SUPUESTOS'!$C$10) -> 26773.425 | AA12: =IF($C12="","",Y12*('⚙️ SUPUESTOS'!$C$12*'⚙️ SUPUESTOS'!$C$11+(1-'⚙️ SUPUESTOS'!$C$12)*'⚙️ SUPUESTOS'!$C$13)) -> 1761.5265 | AB12: =IF($C12="","",IF(Y12>0,ROUND(Y12*'⚙️ SUPUESTOS'!$C$12*'⚙️ SUPUESTOS'!$C$11,0),"")) -> 646 | AC12: =IF($C12="","",IF(Y12>0,ROUND(Y12*(1-'⚙️ SUPUESTOS'!$C$12)*'⚙️ SUPUESTOS'!$C$13,0),"")) -> 1116 | AD12: =IF($C12="","",IF(AND(ISNUMBER(AA12),ISNUMBER(AE12),AA12>0,AE12>0),ROUND(AA12*MAX(0,25-AE12),0),"")) -> 17265 | AE12: =IF($C12="","",IF(AA12>0,Z12/AA12,"")) -> 15.198991 | AF12: =IF($C12="","",IF(AE12="","—",IF(AE12<='⚙️ SUPUESTOS'!$C$32,"✔ Muy recomendable",IF(AE12<='⚙️ SUPUESTOS'!$C$33,"✔ Recomendable","Valorar")))) -> ✔ Recomendable | AG12: =IF('📇 INVENTARIO'!O13="","",'📇 INVENTARIO'!O13) -> 41.64887 | AH12: =IF('📇 INVENTARIO'!P13="","",'📇 INVENTARIO'!P13) -> -4.71047
A13: =IF($C13="","",RANK(O13,$O$3:$O$265,0)+COUNTIF($O$3:O13,O13)-1) -> 11 | B13: =IF($C13="","",IF(A13<='⚙️ SUPUESTOS'!$C$29,"Fase 1",IF(A13<='⚙️ SUPUESTOS'!$C$30,"Fase 2","Fase 3"))) -> Fase 1 | C13: =IF('📇 INVENTARIO'!B14="","",'📇 INVENTARIO'!B14) -> C/ Papagayo, 6 | D13: =IF('📇 INVENTARIO'!C14="","",'📇 INVENTARIO'!C14) -> 7825411UM5172F | E13: =IF('📇 INVENTARIO'!D14="","",'📇 INVENTARIO'!D14) -> 4718606023 | F13: =IF('📇 INVENTARIO'!F14="","",'📇 INVENTARIO'!F14) -> G | G13: =IF('📇 INVENTARIO'!G14="","",'📇 INVENTARIO'!G14) -> 589 | H13: =IF('📇 INVENTARIO'!H14="","",'📇 INVENTARIO'!H14) -> 100 | I13: =IF('📇 INVENTARIO'!I14="","",'📇 INVENTARIO'!I14) -> 242.3 | J13: =IF('📇 INVENTARIO'!J14="","",'📇 INVENTARIO'!J14) -> 1965 | K13: =IF($C13="","",(G13-'⚙️ SUPUESTOS'!$C$20)/('⚙️ SUPUESTOS'!$C$25-'⚙️ SUPUESTOS'!$C$20)) -> 0.767642 | L13: =IF($C13="","",VLOOKUP($E13,'📊 SECCIONES'!$B$4:$S$9,16,FALSE())) -> 0.54128061 | M13: =IF($C13="","",VLOOKUP($E13,'📊 SECCIONES'!$B$4:$S$9,17,FALSE())) -> 0.59585492 | N13: =IF($C13="","",VLOOKUP($E13,'📊 SECCIONES'!$B$4:$S$9,18,FALSE())) -> 0.28636364 | O13: =IF($C13="","",ROUND('⚙️ SUPUESTOS'!$C$21*K13+'⚙️ SUPUESTOS'!$C$22*L13+'⚙️ SUPUESTOS'!$C$23*M13+'⚙️ SUPUESTOS'!$C$24*N13,4)) -> 0.6505 | P13: =IF($C13="","",VLOOKUP($E13,'📊 SECCIONES'!$B$4:$S$9,7,FALSE())) -> 39.41 | Q13: =IF($C13="","",VLOOKUP($E13,'📊 SECCIONES'!$B$4:$S$9,8,FALSE())) -> 22486 | R13: =IF($C13="","",VLOOKUP($E13,'📊 SECCIONES'!$B$4:$S$9,10,FALSE())) -> 16.9 | S13: =IF('📇 INVENTARIO'!K14="","",'📇 INVENTARIO'!K14) -> 3 | T13: =IF($C13="","","Objetivo: alcanzar calificación C. Actual: Cal."&F13&". "&IF(OR(F13="G",F13="F"),"SATE integral + cubierta + carpinterías triple + aerotermia + instalación fotovoltaica",IF(F13="E","SATE fachada + carpinterías doble + instalación fotovoltaica",IF(F13="D","Mantenimiento de envolvente + instalación fotovoltaica en cubierta","Optimización energética + instalación fotovoltaica")))) -> Objetivo: alcanzar calificación C. Actual: Cal.G. SATE integral + cubierta + carpinterías triple + aerotermia + instalación fotovoltaica | U13: =IF($C13="","",IF(S13=0,"s/d",IF(S13>=4,"Valorar ascensor (verificar)","—"))) -> — | V13: =IF('📇 INVENTARIO'!L14="","",'📇 INVENTARIO'!L14) -> 100.8 | W13: =IF($C13="","",V13*'⚙️ SUPUESTOS'!$C$8*'⚙️ SUPUESTOS'!$C$9) -> 21.168 | X13: =IF('📇 INVENTARIO'!N14="","",'📇 INVENTARIO'!N14) -> 1399 | Y13: =IF($C13="","",W13*X13*'⚙️ SUPUESTOS'!$C$7) -> 26652.629 | Z13: =IF($C13="","",W13*'⚙️ SUPUESTOS'!$C$10) -> 28259.28 | AA13: =IF($C13="","",Y13*('⚙️ SUPUESTOS'!$C$12*'⚙️ SUPUESTOS'!$C$11+(1-'⚙️ SUPUESTOS'!$C$12)*'⚙️ SUPUESTOS'!$C$13)) -> 1817.7093 | AB13: =IF($C13="","",IF(Y13>0,ROUND(Y13*'⚙️ SUPUESTOS'!$C$12*'⚙️ SUPUESTOS'!$C$11,0),"")) -> 666 | AC13: =IF($C13="","",IF(Y13>0,ROUND(Y13*(1-'⚙️ SUPUESTOS'!$C$12)*'⚙️ SUPUESTOS'!$C$13,0),"")) -> 1151 | AD13: =IF($C13="","",IF(AND(ISNUMBER(AA13),ISNUMBER(AE13),AA13>0,AE13>0),ROUND(AA13*MAX(0,25-AE13),0),"")) -> 17183 | AE13: =IF($C13="","",IF(AA13>0,Z13/AA13,"")) -> 15.546644 | AF13: =IF($C13="","",IF(AE13="","—",IF(AE13<='⚙️ SUPUESTOS'!$C$32,"✔ Muy recomendable",IF(AE13<='⚙️ SUPUESTOS'!$C$33,"✔ Recomendable","Valorar")))) -> ✔ Recomendable | AG13: =IF('📇 INVENTARIO'!O14="","",'📇 INVENTARIO'!O14) -> 41.64956 | AH13: =IF('📇 INVENTARIO'!P14="","",'📇 INVENTARIO'!P14) -> -4.70818
A14: =IF($C14="","",RANK(O14,$O$3:$O$265,0)+COUNTIF($O$3:O14,O14)-1) -> 12 | B14: =IF($C14="","",IF(A14<='⚙️ SUPUESTOS'!$C$29,"Fase 1",IF(A14<='⚙️ SUPUESTOS'!$C$30,"Fase 2","Fase 3"))) -> Fase 1 | C14: =IF('📇 INVENTARIO'!B15="","",'📇 INVENTARIO'!B15) -> C/ Villabáñez, 18 | D14: =IF('📇 INVENTARIO'!C15="","",'📇 INVENTARIO'!C15) -> 7824502UM5172D | E14: =IF('📇 INVENTARIO'!D15="","",'📇 INVENTARIO'!D15) -> 4718606026 | F14: =IF('📇 INVENTARIO'!F15="","",'📇 INVENTARIO'!F15) -> G | G14: =IF('📇 INVENTARIO'!G15="","",'📇 INVENTARIO'!G15) -> 442 | H14: =IF('📇 INVENTARIO'!H15="","",'📇 INVENTARIO'!H15) -> 93 | I14: =IF('📇 INVENTARIO'!I15="","",'📇 INVENTARIO'!I15) -> 200 | J14: =IF('📇 INVENTARIO'!J15="","",'📇 INVENTARIO'!J15) -> 1965 | K14: =IF($C14="","",(G14-'⚙️ SUPUESTOS'!$C$20)/('⚙️ SUPUESTOS'!$C$25-'⚙️ SUPUESTOS'!$C$20)) -> 0.51462995 | L14: =IF($C14="","",VLOOKUP($E14,'📊 SECCIONES'!$B$4:$S$9,16,FALSE())) -> 1 | M14: =IF($C14="","",VLOOKUP($E14,'📊 SECCIONES'!$B$4:$S$9,17,FALSE())) -> 1 | N14: =IF($C14="","",VLOOKUP($E14,'📊 SECCIONES'!$B$4:$S$9,18,FALSE())) -> 0 | O14: =IF($C14="","",ROUND('⚙️ SUPUESTOS'!$C$21*K14+'⚙️ SUPUESTOS'!$C$22*L14+'⚙️ SUPUESTOS'!$C$23*M14+'⚙️ SUPUESTOS'!$C$24*N14,4)) -> 0.643 | P14: =IF($C14="","",VLOOKUP($E14,'📊 SECCIONES'!$B$4:$S$9,7,FALSE())) -> 66.51 | Q14: =IF($C14="","",VLOOKUP($E14,'📊 SECCIONES'!$B$4:$S$9,8,FALSE())) -> 17450 | R14: =IF($C14="","",VLOOKUP($E14,'📊 SECCIONES'!$B$4:$S$9,10,FALSE())) -> 10.6 | S14: =IF('📇 INVENTARIO'!K15="","",'📇 INVENTARIO'!K15) -> 3 | T14: =IF($C14="","","Objetivo: alcanzar calificación C. Actual: Cal."&F14&". "&IF(OR(F14="G",F14="F"),"SATE integral + cubierta + carpinterías triple + aerotermia + instalación fotovoltaica",IF(F14="E","SATE fachada + carpinterías doble + instalación fotovoltaica",IF(F14="D","Mantenimiento de envolvente + instalación fotovoltaica en cubierta","Optimización energética + instalación fotovoltaica")))) -> Objetivo: alcanzar calificación C. Actual: Cal.G. SATE integral + cubierta + carpinterías triple + aerotermia + instalación fotovoltaica | U14: =IF($C14="","",IF(S14=0,"s/d",IF(S14>=4,"Valorar ascensor (verificar)","—"))) -> — | V14: =IF('📇 INVENTARIO'!L15="","",'📇 INVENTARIO'!L15) -> 113.4 | W14: =IF($C14="","",V14*'⚙️ SUPUESTOS'!$C$8*'⚙️ SUPUESTOS'!$C$9) -> 23.814 | X14: =IF('📇 INVENTARIO'!N15="","",'📇 INVENTARIO'!N15) -> 1421 | Y14: =IF($C14="","",W14*X14*'⚙️ SUPUESTOS'!$C$7) -> 30455.725 | Z14: =IF($C14="","",W14*'⚙️ SUPUESTOS'!$C$10) -> 31791.69 | AA14: =IF($C14="","",Y14*('⚙️ SUPUESTOS'!$C$12*'⚙️ SUPUESTOS'!$C$11+(1-'⚙️ SUPUESTOS'!$C$12)*'⚙️ SUPUESTOS'!$C$13)) -> 2077.0804 | AB14: =IF($C14="","",IF(Y14>0,ROUND(Y14*'⚙️ SUPUESTOS'!$C$12*'⚙️ SUPUESTOS'!$C$11,0),"")) -> 761 | AC14: =IF($C14="","",IF(Y14>0,ROUND(Y14*(1-'⚙️ SUPUESTOS'!$C$12)*'⚙️ SUPUESTOS'!$C$13,0),"")) -> 1316 | AD14: =IF($C14="","",IF(AND(ISNUMBER(AA14),ISNUMBER(AE14),AA14>0,AE14>0),ROUND(AA14*MAX(0,25-AE14),0),"")) -> 20135 | AE14: =IF($C14="","",IF(AA14>0,Z14/AA14,"")) -> 15.30595 | AF14: =IF($C14="","",IF(AE14="","—",IF(AE14<='⚙️ SUPUESTOS'!$C$32,"✔ Muy recomendable",IF(AE14<='⚙️ SUPUESTOS'!$C$33,"✔ Recomendable","Valorar")))) -> ✔ Recomendable | AG14: =IF('📇 INVENTARIO'!O15="","",'📇 INVENTARIO'!O15) -> 41.64896 | AH14: =IF('📇 INVENTARIO'!P15="","",'📇 INVENTARIO'!P15) -> -4.70864
A15: =IF($C15="","",RANK(O15,$O$3:$O$265,0)+COUNTIF($O$3:O15,O15)-1) -> 13 | B15: =IF($C15="","",IF(A15<='⚙️ SUPUESTOS'!$C$29,"Fase 1",IF(A15<='⚙️ SUPUESTOS'!$C$30,"Fase 2","Fase 3"))) -> Fase 1 | C15: =IF('📇 INVENTARIO'!B16="","",'📇 INVENTARIO'!B16) -> C/ Cuclillo, 3 | D15: =IF('📇 INVENTARIO'!C16="","",'📇 INVENTARIO'!C16) -> 7724216UM5172D | E15: =IF('📇 INVENTARIO'!D16="","",'📇 INVENTARIO'!D16) -> 4718606026 | F15: =IF('📇 INVENTARIO'!F16="","",'📇 INVENTARIO'!F16) -> G | G15: =IF('📇 INVENTARIO'!G16="","",'📇 INVENTARIO'!G16) -> 442 | H15: =IF('📇 INVENTARIO'!H16="","",'📇 INVENTARIO'!H16) -> 88 | I15: =IF('📇 INVENTARIO'!I16="","",'📇 INVENTARIO'!I16) -> 223.4 | J15: =IF('📇 INVENTARIO'!J16="","",'📇 INVENTARIO'!J16) -> 1965 | K15: =IF($C15="","",(G15-'⚙️ SUPUESTOS'!$C$20)/('⚙️ SUPUESTOS'!$C$25-'⚙️ SUPUESTOS'!$C$20)) -> 0.51462995 | L15: =IF($C15="","",VLOOKUP($E15,'📊 SECCIONES'!$B$4:$S$9,16,FALSE())) -> 1 | M15: =IF($C15="","",VLOOKUP($E15,'📊 SECCIONES'!$B$4:$S$9,17,FALSE())) -> 1 | N15: =IF($C15="","",VLOOKUP($E15,'📊 SECCIONES'!$B$4:$S$9,18,FALSE())) -> 0 | O15: =IF($C15="","",ROUND('⚙️ SUPUESTOS'!$C$21*K15+'⚙️ SUPUESTOS'!$C$22*L15+'⚙️ SUPUESTOS'!$C$23*M15+'⚙️ SUPUESTOS'!$C$24*N15,4)) -> 0.643 | P15: =IF($C15="","",VLOOKUP($E15,'📊 SECCIONES'!$B$4:$S$9,7,FALSE())) -> 66.51 | Q15: =IF($C15="","",VLOOKUP($E15,'📊 SECCIONES'!$B$4:$S$9,8,FALSE())) -> 17450 | R15: =IF($C15="","",VLOOKUP($E15,'📊 SECCIONES'!$B$4:$S$9,10,FALSE())) -> 10.6 | S15: =IF('📇 INVENTARIO'!K16="","",'📇 INVENTARIO'!K16) -> 3 | T15: =IF($C15="","","Objetivo: alcanzar calificación C. Actual: Cal."&F15&". "&IF(OR(F15="G",F15="F"),"SATE integral + cubierta + carpinterías triple + aerotermia + instalación fotovoltaica",IF(F15="E","SATE fachada + carpinterías doble + instalación fotovoltaica",IF(F15="D","Mantenimiento de envolvente + instalación fotovoltaica en cubierta","Optimización energética + instalación fotovoltaica")))) -> Objetivo: alcanzar calificación C. Actual: Cal.G. SATE integral + cubierta + carpinterías triple + aerotermia + instalación fotovoltaica | U15: =IF($C15="","",IF(S15=0,"s/d",IF(S15>=4,"Valorar ascensor (verificar)","—"))) -> — | V15: =IF('📇 INVENTARIO'!L16="","",'📇 INVENTARIO'!L16) -> 104.6 | W15: =IF($C15="","",V15*'⚙️ SUPUESTOS'!$C$8*'⚙️ SUPUESTOS'!$C$9) -> 21.966 | X15: =IF('📇 INVENTARIO'!N16="","",'📇 INVENTARIO'!N16) -> 1328 | Y15: =IF($C15="","",W15*X15*'⚙️ SUPUESTOS'!$C$7) -> 26253.763 | Z15: =IF($C15="","",W15*'⚙️ SUPUESTOS'!$C$10) -> 29324.61 | AA15: =IF($C15="","",Y15*('⚙️ SUPUESTOS'!$C$12*'⚙️ SUPUESTOS'!$C$11+(1-'⚙️ SUPUESTOS'!$C$12)*'⚙️ SUPUESTOS'!$C$13)) -> 1790.5067 | AB15: =IF($C15="","",IF(Y15>0,ROUND(Y15*'⚙️ SUPUESTOS'!$C$12*'⚙️ SUPUESTOS'!$C$11,0),"")) -> 656 | AC15: =IF($C15="","",IF(Y15>0,ROUND(Y15*(1-'⚙️ SUPUESTOS'!$C$12)*'⚙️ SUPUESTOS'!$C$13,0),"")) -> 1134 | AD15: =IF($C15="","",IF(AND(ISNUMBER(AA15),ISNUMBER(AE15),AA15>0,AE15>0),ROUND(AA15*MAX(0,25-AE15),0),"")) -> 15438 | AE15: =IF($C15="","",IF(AA15>0,Z15/AA15,"")) -> 16.377828 | AF15: =IF($C15="","",IF(AE15="","—",IF(AE15<='⚙️ SUPUESTOS'!$C$32,"✔ Muy recomendable",IF(AE15<='⚙️ SUPUESTOS'!$C$33,"✔ Recomendable","Valorar")))) -> Valorar | AG15: =IF('📇 INVENTARIO'!O16="","",'📇 INVENTARIO'!O16) -> 41.648759 | AH15: =IF('📇 INVENTARIO'!P16="","",'📇 INVENTARIO'!P16) -> -4.709681
A16: =IF($C16="","",RANK(O16,$O$3:$O$265,0)+COUNTIF($O$3:O16,O16)-1) -> 14 | B16: =IF($C16="","",IF(A16<='⚙️ SUPUESTOS'!$C$29,"Fase 1",IF(A16<='⚙️ SUPUESTOS'!$C$30,"Fase 2","Fase 3"))) -> Fase 1 | C16: =IF('📇 INVENTARIO'!B17="","",'📇 INVENTARIO'!B17) -> C/ Águila, 21 | D16: =IF('📇 INVENTARIO'!C17="","",'📇 INVENTARIO'!C17) -> 7724217UM5172D | E16: =IF('📇 INVENTARIO'!D17="","",'📇 INVENTARIO'!D17) -> 4718606026 | F16: =IF('📇 INVENTARIO'!F17="","",'📇 INVENTARIO'!F17) -> E | G16: =IF('📇 INVENTARIO'!G17="","",'📇 INVENTARIO'!G17) -> 442 | H16: =IF('📇 INVENTARIO'!H17="","",'📇 INVENTARIO'!H17) -> 92.5 | I16: =IF('📇 INVENTARIO'!I17="","",'📇 INVENTARIO'!I17) -> 203.3 | J16: =IF('📇 INVENTARIO'!J17="","",'📇 INVENTARIO'!J17) -> 1965 | K16: =IF($C16="","",(G16-'⚙️ SUPUESTOS'!$C$20)/('⚙️ SUPUESTOS'!$C$25-'⚙️ SUPUESTOS'!$C$20)) -> 0.51462995 | L16: =IF($C16="","",VLOOKUP($E16,'📊 SECCIONES'!$B$4:$S$9,16,FALSE())) -> 1 | M16: =IF($C16="","",VLOOKUP($E16,'📊 SECCIONES'!$B$4:$S$9,17,FALSE())) -> 1 | N16: =IF($C16="","",VLOOKUP($E16,'📊 SECCIONES'!$B$4:$S$9,18,FALSE())) -> 0 | O16: =IF($C16="","",ROUND('⚙️ SUPUESTOS'!$C$21*K16+'⚙️ SUPUESTOS'!$C$22*L16+'⚙️ SUPUESTOS'!$C$23*M16+'⚙️ SUPUESTOS'!$C$24*N16,4)) -> 0.643 | P16: =IF($C16="","",VLOOKUP($E16,'📊 SECCIONES'!$B$4:$S$9,7,FALSE())) -> 66.51 | Q16: =IF($C16="","",VLOOKUP($E16,'📊 SECCIONES'!$B$4:$S$9,8,FALSE())) -> 17450 | R16: =IF($C16="","",VLOOKUP($E16,'📊 SECCIONES'!$B$4:$S$9,10,FALSE())) -> 10.6 | S16: =IF('📇 INVENTARIO'!K17="","",'📇 INVENTARIO'!K17) -> 3 | T16: =IF($C16="","","Objetivo: alcanzar calificación C. Actual: Cal."&F16&". "&IF(OR(F16="G",F16="F"),"SATE integral + cubierta + carpinterías triple + aerotermia + instalación fotovoltaica",IF(F16="E","SATE fachada + carpinterías doble + instalación fotovoltaica",IF(F16="D","Mantenimiento de envolvente + instalación fotovoltaica en cubierta","Optimización energética + instalación fotovoltaica")))) -> Objetivo: alcanzar calificación C. Actual: Cal.E. SATE fachada + carpinterías doble + instalación fotovoltaica | U16: =IF($C16="","",IF(S16=0,"s/d",IF(S16>=4,"Valorar ascensor (verificar)","—"))) -> — | V16: =IF('📇 INVENTARIO'!L17="","",'📇 INVENTARIO'!L17) -> 98.1 | W16: =IF($C16="","",V16*'⚙️ SUPUESTOS'!$C$8*'⚙️ SUPUESTOS'!$C$9) -> 20.601 | X16: =IF('📇 INVENTARIO'!N17="","",'📇 INVENTARIO'!N17) -> 1396 | Y16: =IF($C16="","",W16*X16*'⚙️ SUPUESTOS'!$C$7) -> 25883.096 | Z16: =IF($C16="","",W16*'⚙️ SUPUESTOS'!$C$10) -> 27502.335 | AA16: =IF($C16="","",Y16*('⚙️ SUPUESTOS'!$C$12*'⚙️ SUPUESTOS'!$C$11+(1-'⚙️ SUPUESTOS'!$C$12)*'⚙️ SUPUESTOS'!$C$13)) -> 1765.2272 | AB16: =IF($C16="","",IF(Y16>0,ROUND(Y16*'⚙️ SUPUESTOS'!$C$12*'⚙️ SUPUESTOS'!$C$11,0),"")) -> 647 | AC16: =IF($C16="","",IF(Y16>0,ROUND(Y16*(1-'⚙️ SUPUESTOS'!$C$12)*'⚙️ SUPUESTOS'!$C$13,0),"")) -> 1118 | AD16: =IF($C16="","",IF(AND(ISNUMBER(AA16),ISNUMBER(AE16),AA16>0,AE16>0),ROUND(AA16*MAX(0,25-AE16),0),"")) -> 16628 | AE16: =IF($C16="","",IF(AA16>0,Z16/AA16,"")) -> 15.580054 | AF16: =IF($C16="","",IF(AE16="","—",IF(AE16<='⚙️ SUPUESTOS'!$C$32,"✔ Muy recomendable",IF(AE16<='⚙️ SUPUESTOS'!$C$33,"✔ Recomendable","Valorar")))) -> ✔ Recomendable | AG16: =IF('📇 INVENTARIO'!O17="","",'📇 INVENTARIO'!O17) -> 41.64858 | AH16: =IF('📇 INVENTARIO'!P17="","",'📇 INVENTARIO'!P17) -> -4.70948
A17: =IF($C17="","",RANK(O17,$O$3:$O$265,0)+COUNTIF($O$3:O17,O17)-1) -> 15 | B17: =IF($C17="","",IF(A17<='⚙️ SUPUESTOS'!$C$29,"Fase 1",IF(A17<='⚙️ SUPUESTOS'!$C$30,"Fase 2","Fase 3"))) -> Fase 1 | C17: =IF('📇 INVENTARIO'!B18="","",'📇 INVENTARIO'!B18) -> C/ Pavo Real, 19 | D17: =IF('📇 INVENTARIO'!C18="","",'📇 INVENTARIO'!C18) -> 7625405UM5172F | E17: =IF('📇 INVENTARIO'!D18="","",'📇 INVENTARIO'!D18) -> 4718606026 | F17: =IF('📇 INVENTARIO'!F18="","",'📇 INVENTARIO'!F18) -> G | G17: =IF('📇 INVENTARIO'!G18="","",'📇 INVENTARIO'!G18) -> 434 | H17: =IF('📇 INVENTARIO'!H18="","",'📇 INVENTARIO'!H18) -> 73 | I17: =IF('📇 INVENTARIO'!I18="","",'📇 INVENTARIO'!I18) -> 135.8 | J17: =IF('📇 INVENTARIO'!J18="","",'📇 INVENTARIO'!J18) -> 1965 | K17: =IF($C17="","",(G17-'⚙️ SUPUESTOS'!$C$20)/('⚙️ SUPUESTOS'!$C$25-'⚙️ SUPUESTOS'!$C$20)) -> 0.50086059 | L17: =IF($C17="","",VLOOKUP($E17,'📊 SECCIONES'!$B$4:$S$9,16,FALSE())) -> 1 | M17: =IF($C17="","",VLOOKUP($E17,'📊 SECCIONES'!$B$4:$S$9,17,FALSE())) -> 1 | N17: =IF($C17="","",VLOOKUP($E17,'📊 SECCIONES'!$B$4:$S$9,18,FALSE())) -> 0 | O17: =IF($C17="","",ROUND('⚙️ SUPUESTOS'!$C$21*K17+'⚙️ SUPUESTOS'!$C$22*L17+'⚙️ SUPUESTOS'!$C$23*M17+'⚙️ SUPUESTOS'!$C$24*N17,4)) -> 0.6355 | P17: =IF($C17="","",VLOOKUP($E17,'📊 SECCIONES'!$B$4:$S$9,7,FALSE())) -> 66.51 | Q17: =IF($C17="","",VLOOKUP($E17,'📊 SECCIONES'!$B$4:$S$9,8,FALSE())) -> 17450 | R17: =IF($C17="","",VLOOKUP($E17,'📊 SECCIONES'!$B$4:$S$9,10,FALSE())) -> 10.6 | S17: =IF('📇 INVENTARIO'!K18="","",'📇 INVENTARIO'!K18) -> 3 | T17: =IF($C17="","","Objetivo: alcanzar calificación C. Actual: Cal."&F17&". "&IF(OR(F17="G",F17="F"),"SATE integral + cubierta + carpinterías triple + aerotermia + instalación fotovoltaica",IF(F17="E","SATE fachada + carpinterías doble + instalación fotovoltaica",IF(F17="D","Mantenimiento de envolvente + instalación fotovoltaica en cubierta","Optimización energética + instalación fotovoltaica")))) -> Objetivo: alcanzar calificación C. Actual: Cal.G. SATE integral + cubierta + carpinterías triple + aerotermia + instalación fotovoltaica | U17: =IF($C17="","",IF(S17=0,"s/d",IF(S17>=4,"Valorar ascensor (verificar)","—"))) -> — | V17: =IF('📇 INVENTARIO'!L18="","",'📇 INVENTARIO'!L18) -> 95.3 | W17: =IF($C17="","",V17*'⚙️ SUPUESTOS'!$C$8*'⚙️ SUPUESTOS'!$C$9) -> 20.013 | X17: =IF('📇 INVENTARIO'!N18="","",'📇 INVENTARIO'!N18) -> 1483 | Y17: =IF($C17="","",W17*X17*'⚙️ SUPUESTOS'!$C$7) -> 26711.351 | Z17: =IF($C17="","",W17*'⚙️ SUPUESTOS'!$C$10) -> 26717.355 | AA17: =IF($C17="","",Y17*('⚙️ SUPUESTOS'!$C$12*'⚙️ SUPUESTOS'!$C$11+(1-'⚙️ SUPUESTOS'!$C$12)*'⚙️ SUPUESTOS'!$C$13)) -> 1821.7141 | AB17: =IF($C17="","",IF(Y17>0,ROUND(Y17*'⚙️ SUPUESTOS'!$C$12*'⚙️ SUPUESTOS'!$C$11,0),"")) -> 668 | AC17: =IF($C17="","",IF(Y17>0,ROUND(Y17*(1-'⚙️ SUPUESTOS'!$C$12)*'⚙️ SUPUESTOS'!$C$13,0),"")) -> 1154 | AD17: =IF($C17="","",IF(AND(ISNUMBER(AA17),ISNUMBER(AE17),AA17>0,AE17>0),ROUND(AA17*MAX(0,25-AE17),0),"")) -> 18825 | AE17: =IF($C17="","",IF(AA17>0,Z17/AA17,"")) -> 14.666052 | AF17: =IF($C17="","",IF(AE17="","—",IF(AE17<='⚙️ SUPUESTOS'!$C$32,"✔ Muy recomendable",IF(AE17<='⚙️ SUPUESTOS'!$C$33,"✔ Recomendable","Valorar")))) -> ✔ Muy recomendable | AG17: =IF('📇 INVENTARIO'!O18="","",'📇 INVENTARIO'!O18) -> 41.64932 | AH17: =IF('📇 INVENTARIO'!P18="","",'📇 INVENTARIO'!P18) -> -4.71065
A18: =IF($C18="","",RANK(O18,$O$3:$O$265,0)+COUNTIF($O$3:O18,O18)-1) -> 16 | B18: =IF($C18="","",IF(A18<='⚙️ SUPUESTOS'!$C$29,"Fase 1",IF(A18<='⚙️ SUPUESTOS'!$C$30,"Fase 2","Fase 3"))) -> Fase 1 | C18: =IF('📇 INVENTARIO'!B20="","",'📇 INVENTARIO'!B20) -> C/ Oropéndola, 4 | D18: =IF('📇 INVENTARIO'!C20="","",'📇 INVENTARIO'!C20) -> 7825407UM5172F | E18: =IF('📇 INVENTARIO'!D20="","",'📇 INVENTARIO'!D20) -> 4718606023 | F18: =IF('📇 INVENTARIO'!F20="","",'📇 INVENTARIO'!F20) -> G | G18: =IF('📇 INVENTARIO'!G20="","",'📇 INVENTARIO'!G20) -> 569 | H18: =IF('📇 INVENTARIO'!H20="","",'📇 INVENTARIO'!H20) -> 113 | I18: =IF('📇 INVENTARIO'!I20="","",'📇 INVENTARIO'!I20) -> 251.8 | J18: =IF('📇 INVENTARIO'!J20="","",'📇 INVENTARIO'!J20) -> 1965 | K18: =IF($C18="","",(G18-'⚙️ SUPUESTOS'!$C$20)/('⚙️ SUPUESTOS'!$C$25-'⚙️ SUPUESTOS'!$C$20)) -> 0.73321859 | L18: =IF($C18="","",VLOOKUP($E18,'📊 SECCIONES'!$B$4:$S$9,16,FALSE())) -> 0.54128061 | M18: =IF($C18="","",VLOOKUP($E18,'📊 SECCIONES'!$B$4:$S$9,17,FALSE())) -> 0.59585492 | N18: =IF($C18="","",VLOOKUP($E18,'📊 SECCIONES'!$B$4:$S$9,18,FALSE())) -> 0.28636364 | O18: =IF($C18="","",ROUND('⚙️ SUPUESTOS'!$C$21*K18+'⚙️ SUPUESTOS'!$C$22*L18+'⚙️ SUPUESTOS'!$C$23*M18+'⚙️ SUPUESTOS'!$C$24*N18,4)) -> 0.6315 | P18: =IF($C18="","",VLOOKUP($E18,'📊 SECCIONES'!$B$4:$S$9,7,FALSE())) -> 39.41 | Q18: =IF($C18="","",VLOOKUP($E18,'📊 SECCIONES'!$B$4:$S$9,8,FALSE())) -> 22486 | R18: =IF($C18="","",VLOOKUP($E18,'📊 SECCIONES'!$B$4:$S$9,10,FALSE())) -> 16.9 | S18: =IF('📇 INVENTARIO'!K20="","",'📇 INVENTARIO'!K20) -> 3 | T18: =IF($C18="","","Objetivo: alcanzar calificación C. Actual: Cal."&F18&". "&IF(OR(F18="G",F18="F"),"SATE integral + cubierta + carpinterías triple + aerotermia + instalación fotovoltaica",IF(F18="E","SATE fachada + carpinterías doble + instalación fotovoltaica",IF(F18="D","Mantenimiento de envolvente + instalación fotovoltaica en cubierta","Optimización energética + instalación fotovoltaica")))) -> Objetivo: alcanzar calificación C. Actual: Cal.G. SATE integral + cubierta + carpinterías triple + aerotermia + instalación fotovoltaica | U18: =IF($C18="","",IF(S18=0,"s/d",IF(S18>=4,"Valorar ascensor (verificar)","—"))) -> — | V18: =IF('📇 INVENTARIO'!L20="","",'📇 INVENTARIO'!L20) -> 100.5 | W18: =IF($C18="","",V18*'⚙️ SUPUESTOS'!$C$8*'⚙️ SUPUESTOS'!$C$9) -> 21.105 | X18: =IF('📇 INVENTARIO'!N20="","",'📇 INVENTARIO'!N20) -> 1293 | Y18: =IF($C18="","",W18*X18*'⚙️ SUPUESTOS'!$C$7) -> 24559.889 | Z18: =IF($C18="","",W18*'⚙️ SUPUESTOS'!$C$10) -> 28175.175 | AA18: =IF($C18="","",Y18*('⚙️ SUPUESTOS'!$C$12*'⚙️ SUPUESTOS'!$C$11+(1-'⚙️ SUPUESTOS'!$C$12)*'⚙️ SUPUESTOS'!$C$13)) -> 1674.9844 | AB18: =IF($C18="","",IF(Y18>0,ROUND(Y18*'⚙️ SUPUESTOS'!$C$12*'⚙️ SUPUESTOS'!$C$11,0),"")) -> 614 | AC18: =IF($C18="","",IF(Y18>0,ROUND(Y18*(1-'⚙️ SUPUESTOS'!$C$12)*'⚙️ SUPUESTOS'!$C$13,0),"")) -> 1061 | AD18: =IF($C18="","",IF(AND(ISNUMBER(AA18),ISNUMBER(AE18),AA18>0,AE18>0),ROUND(AA18*MAX(0,25-AE18),0),"")) -> 13699 | AE18: =IF($C18="","",IF(AA18>0,Z18/AA18,"")) -> 16.821157 | AF18: =IF($C18="","",IF(AE18="","—",IF(AE18<='⚙️ SUPUESTOS'!$C$32,"✔ Muy recomendable",IF(AE18<='⚙️ SUPUESTOS'!$C$33,"✔ Recomendable","Valorar")))) -> Valorar | AG18: =IF('📇 INVENTARIO'!O19="","",'📇 INVENTARIO'!O19) -> 41.64883 | AH18: =IF('📇 INVENTARIO'!P19="","",'📇 INVENTARIO'!P19) -> -4.71008
A19: =IF($C19="","",RANK(O19,$O$3:$O$265,0)+COUNTIF($O$3:O19,O19)-1) -> 17 | B19: =IF($C19="","",IF(A19<='⚙️ SUPUESTOS'!$C$29,"Fase 1",IF(A19<='⚙️ SUPUESTOS'!$C$30,"Fase 2","Fase 3"))) -> Fase 1 | C19: =IF('📇 INVENTARIO'!B19="","",'📇 INVENTARIO'!B19) -> C/ Zorzal, 14 | D19: =IF('📇 INVENTARIO'!C19="","",'📇 INVENTARIO'!C19) -> 7724221UM5172D | E19: =IF('📇 INVENTARIO'!D19="","",'📇 INVENTARIO'!D19) -> 4718606026 | F19: =IF('📇 INVENTARIO'!F19="","",'📇 INVENTARIO'!F19) -> G | G19: =IF('📇 INVENTARIO'!G19="","",'📇 INVENTARIO'!G19) -> 429 | H19: =IF('📇 INVENTARIO'!H19="","",'📇 INVENTARIO'!H19) -> 87 | I19: =IF('📇 INVENTARIO'!I19="","",'📇 INVENTARIO'!I19) -> 201.4 | J19: =IF('📇 INVENTARIO'!J19="","",'📇 INVENTARIO'!J19) -> 1965 | K19: =IF($C19="","",(G19-'⚙️ SUPUESTOS'!$C$20)/('⚙️ SUPUESTOS'!$C$25-'⚙️ SUPUESTOS'!$C$20)) -> 0.49225473 | L19: =IF($C19="","",VLOOKUP($E19,'📊 SECCIONES'!$B$4:$S$9,16,FALSE())) -> 1 | M19: =IF($C19="","",VLOOKUP($E19,'📊 SECCIONES'!$B$4:$S$9,17,FALSE())) -> 1 | N19: =IF($C19="","",VLOOKUP($E19,'📊 SECCIONES'!$B$4:$S$9,18,FALSE())) -> 0 | O19: =IF($C19="","",ROUND('⚙️ SUPUESTOS'!$C$21*K19+'⚙️ SUPUESTOS'!$C$22*L19+'⚙️ SUPUESTOS'!$C$23*M19+'⚙️ SUPUESTOS'!$C$24*N19,4)) -> 0.6307 | P19: =IF($C19="","",VLOOKUP($E19,'📊 SECCIONES'!$B$4:$S$9,7,FALSE())) -> 66.51 | Q19: =IF($C19="","",VLOOKUP($E19,'📊 SECCIONES'!$B$4:$S$9,8,FALSE())) -> 17450 | R19: =IF($C19="","",VLOOKUP($E19,'📊 SECCIONES'!$B$4:$S$9,10,FALSE())) -> 10.6 | S19: =IF('📇 INVENTARIO'!K19="","",'📇 INVENTARIO'!K19) -> 3 | T19: =IF($C19="","","Objetivo: alcanzar calificación C. Actual: Cal."&F19&". "&IF(OR(F19="G",F19="F"),"SATE integral + cubierta + carpinterías triple + aerotermia + instalación fotovoltaica",IF(F19="E","SATE fachada + carpinterías doble + instalación fotovoltaica",IF(F19="D","Mantenimiento de envolvente + instalación fotovoltaica en cubierta","Optimización energética + instalación fotovoltaica")))) -> Objetivo: alcanzar calificación C. Actual: Cal.G. SATE integral + cubierta + carpinterías triple + aerotermia + instalación fotovoltaica | U19: =IF($C19="","",IF(S19=0,"s/d",IF(S19>=4,"Valorar ascensor (verificar)","—"))) -> — | V19: =IF('📇 INVENTARIO'!L19="","",'📇 INVENTARIO'!L19) -> 102.9 | W19: =IF($C19="","",V19*'⚙️ SUPUESTOS'!$C$8*'⚙️ SUPUESTOS'!$C$9) -> 21.609 | X19: =IF('📇 INVENTARIO'!N19="","",'📇 INVENTARIO'!N19) -> 1525 | Y19: =IF($C19="","",W19*X19*'⚙️ SUPUESTOS'!$C$7) -> 29658.353 | Z19: =IF($C19="","",W19*'⚙️ SUPUESTOS'!$C$10) -> 28848.015 | AA19: =IF($C19="","",Y19*('⚙️ SUPUESTOS'!$C$12*'⚙️ SUPUESTOS'!$C$11+(1-'⚙️ SUPUESTOS'!$C$12)*'⚙️ SUPUESTOS'!$C$13)) -> 2022.6996 | AB19: =IF($C19="","",IF(Y19>0,ROUND(Y19*'⚙️ SUPUESTOS'!$C$12*'⚙️ SUPUESTOS'!$C$11,0),"")) -> 741 | AC19: =IF($C19="","",IF(Y19>0,ROUND(Y19*(1-'⚙️ SUPUESTOS'!$C$12)*'⚙️ SUPUESTOS'!$C$13,0),"")) -> 1281 | AD19: =IF($C19="","",IF(AND(ISNUMBER(AA19),ISNUMBER(AE19),AA19>0,AE19>0),ROUND(AA19*MAX(0,25-AE19),0),"")) -> 21719 | AE19: =IF($C19="","",IF(AA19>0,Z19/AA19,"")) -> 14.262135 | AF19: =IF($C19="","",IF(AE19="","—",IF(AE19<='⚙️ SUPUESTOS'!$C$32,"✔ Muy recomendable",IF(AE19<='⚙️ SUPUESTOS'!$C$33,"✔ Recomendable","Valorar")))) -> ✔ Muy recomendable | AG19: =IF('📇 INVENTARIO'!O20="","",'📇 INVENTARIO'!O20) -> 41.6496 | AH19: =IF('📇 INVENTARIO'!P20="","",'📇 INVENTARIO'!P20) -> -4.70846
A20: =IF($C20="","",RANK(O20,$O$3:$O$265,0)+COUNTIF($O$3:O20,O20)-1) -> 18 | B20: =IF($C20="","",IF(A20<='⚙️ SUPUESTOS'!$C$29,"Fase 1",IF(A20<='⚙️ SUPUESTOS'!$C$30,"Fase 2","Fase 3"))) -> Fase 1 | C20: =IF('📇 INVENTARIO'!B21="","",'📇 INVENTARIO'!B21) -> C/ Zorzal, 16 | D20: =IF('📇 INVENTARIO'!C21="","",'📇 INVENTARIO'!C21) -> 7724205UM5172D | E20: =IF('📇 INVENTARIO'!D21="","",'📇 INVENTARIO'!D21) -> 4718606026 | F20: =IF('📇 INVENTARIO'!F21="","",'📇 INVENTARIO'!F21) -> G | G20: =IF('📇 INVENTARIO'!G21="","",'📇 INVENTARIO'!G21) -> 419 | H20: =IF('📇 INVENTARIO'!H21="","",'📇 INVENTARIO'!H21) -> 88.5 | I20: =IF('📇 INVENTARIO'!I21="","",'📇 INVENTARIO'!I21) -> 232.2 | J20: =IF('📇 INVENTARIO'!J21="","",'📇 INVENTARIO'!J21) -> 1965 | K20: =IF($C20="","",(G20-'⚙️ SUPUESTOS'!$C$20)/('⚙️ SUPUESTOS'!$C$25-'⚙️ SUPUESTOS'!$C$20)) -> 0.47504303 | L20: =IF($C20="","",VLOOKUP($E20,'📊 SECCIONES'!$B$4:$S$9,16,FALSE())) -> 1 | M20: =IF($C20="","",VLOOKUP($E20,'📊 SECCIONES'!$B$4:$S$9,17,FALSE())) -> 1 | N20: =IF($C20="","",VLOOKUP($E20,'📊 SECCIONES'!$B$4:$S$9,18,FALSE())) -> 0 | O20: =IF($C20="","",ROUND('⚙️ SUPUESTOS'!$C$21*K20+'⚙️ SUPUESTOS'!$C$22*L20+'⚙️ SUPUESTOS'!$C$23*M20+'⚙️ SUPUESTOS'!$C$24*N20,4)) -> 0.6213 | P20: =IF($C20="","",VLOOKUP($E20,'📊 SECCIONES'!$B$4:$S$9,7,FALSE())) -> 66.51 | Q20: =IF($C20="","",VLOOKUP($E20,'📊 SECCIONES'!$B$4:$S$9,8,FALSE())) -> 17450 | R20: =IF($C20="","",VLOOKUP($E20,'📊 SECCIONES'!$B$4:$S$9,10,FALSE())) -> 10.6 | S20: =IF('📇 INVENTARIO'!K21="","",'📇 INVENTARIO'!K21) -> 3 | T20: =IF($C20="","","Objetivo: alcanzar calificación C. Actual: Cal."&F20&". "&IF(OR(F20="G",F20="F"),"SATE integral + cubierta + carpinterías triple + aerotermia + instalación fotovoltaica",IF(F20="E","SATE fachada + carpinterías doble + instalación fotovoltaica",IF(F20="D","Mantenimiento de envolvente + instalación fotovoltaica en cubierta","Optimización energética + instalación fotovoltaica")))) -> Objetivo: alcanzar calificación C. Actual: Cal.G. SATE integral + cubierta + carpinterías triple + aerotermia + instalación fotovoltaica | U20: =IF($C20="","",IF(S20=0,"s/d",IF(S20>=4,"Valorar ascensor (verificar)","—"))) -> — | V20: =IF('📇 INVENTARIO'!L21="","",'📇 INVENTARIO'!L21) -> 100.2 | W20: =IF($C20="","",V20*'⚙️ SUPUESTOS'!$C$8*'⚙️ SUPUESTOS'!$C$9) -> 21.042 | X20: =IF('📇 INVENTARIO'!N21="","",'📇 INVENTARIO'!N21) -> 1440 | Y20: =IF($C20="","",W20*X20*'⚙️ SUPUESTOS'!$C$7) -> 27270.432 | Z20: =IF($C20="","",W20*'⚙️ SUPUESTOS'!$C$10) -> 28091.07 | AA20: =IF($C20="","",Y20*('⚙️ SUPUESTOS'!$C$12*'⚙️ SUPUESTOS'!$C$11+(1-'⚙️ SUPUESTOS'!$C$12)*'⚙️ SUPUESTOS'!$C$13)) -> 1859.8435 | AB20: =IF($C20="","",IF(Y20>0,ROUND(Y20*'⚙️ SUPUESTOS'!$C$12*'⚙️ SUPUESTOS'!$C$11,0),"")) -> 682 | AC20: =IF($C20="","",IF(Y20>0,ROUND(Y20*(1-'⚙️ SUPUESTOS'!$C$12)*'⚙️ SUPUESTOS'!$C$13,0),"")) -> 1178 | AD20: =IF($C20="","",IF(AND(ISNUMBER(AA20),ISNUMBER(AE20),AA20>0,AE20>0),ROUND(AA20*MAX(0,25-AE20),0),"")) -> 18405 | AE20: =IF($C20="","",IF(AA20>0,Z20/AA20,"")) -> 15.103997 | AF20: =IF($C20="","",IF(AE20="","—",IF(AE20<='⚙️ SUPUESTOS'!$C$32,"✔ Muy recomendable",IF(AE20<='⚙️ SUPUESTOS'!$C$33,"✔ Recomendable","Valorar")))) -> ✔ Recomendable | AG20: =IF('📇 INVENTARIO'!O21="","",'📇 INVENTARIO'!O21) -> 41.6492 | AH20: =IF('📇 INVENTARIO'!P21="","",'📇 INVENTARIO'!P21) -> -4.70978
A21: =IF($C21="","",RANK(O21,$O$3:$O$265,0)+COUNTIF($O$3:O21,O21)-1) -> 19 | B21: =IF($C21="","",IF(A21<='⚙️ SUPUESTOS'!$C$29,"Fase 1",IF(A21<='⚙️ SUPUESTOS'!$C$30,"Fase 2","Fase 3"))) -> Fase 1 | C21: =IF('📇 INVENTARIO'!B22="","",'📇 INVENTARIO'!B22) -> C/ Periquito, 4 | D21: =IF('📇 INVENTARIO'!C22="","",'📇 INVENTARIO'!C22) -> 7724204UM5172D | E21: =IF('📇 INVENTARIO'!D22="","",'📇 INVENTARIO'!D22) -> 4718606026 | F21: =IF('📇 INVENTARIO'!F22="","",'📇 INVENTARIO'!F22) -> G | G21: =IF('📇 INVENTARIO'!G22="","",'📇 INVENTARIO'!G22) -> 416 | H21: =IF('📇 INVENTARIO'!H22="","",'📇 INVENTARIO'!H22) -> 70 | I21: =IF('📇 INVENTARIO'!I22="","",'📇 INVENTARIO'!I22) -> 168.5 | J21: =IF('📇 INVENTARIO'!J22="","",'📇 INVENTARIO'!J22) -> 1965 | K21: =IF($C21="","",(G21-'⚙️ SUPUESTOS'!$C$20)/('⚙️ SUPUESTOS'!$C$25-'⚙️ SUPUESTOS'!$C$20)) -> 0.46987952 | L21: =IF($C21="","",VLOOKUP($E21,'📊 SECCIONES'!$B$4:$S$9,16,FALSE())) -> 1 | M21: =IF($C21="","",VLOOKUP($E21,'📊 SECCIONES'!$B$4:$S$9,17,FALSE())) -> 1 | N21: =IF($C21="","",VLOOKUP($E21,'📊 SECCIONES'!$B$4:$S$9,18,FALSE())) -> 0 | O21: =IF($C21="","",ROUND('⚙️ SUPUESTOS'!$C$21*K21+'⚙️ SUPUESTOS'!$C$22*L21+'⚙️ SUPUESTOS'!$C$23*M21+'⚙️ SUPUESTOS'!$C$24*N21,4)) -> 0.6184 | P21: =IF($C21="","",VLOOKUP($E21,'📊 SECCIONES'!$B$4:$S$9,7,FALSE())) -> 66.51 | Q21: =IF($C21="","",VLOOKUP($E21,'📊 SECCIONES'!$B$4:$S$9,8,FALSE())) -> 17450 | R21: =IF($C21="","",VLOOKUP($E21,'📊 SECCIONES'!$B$4:$S$9,10,FALSE())) -> 10.6 | S21: =IF('📇 INVENTARIO'!K22="","",'📇 INVENTARIO'!K22) -> 3 | T21: =IF($C21="","","Objetivo: alcanzar calificación C. Actual: Cal."&F21&". "&IF(OR(F21="G",F21="F"),"SATE integral + cubierta + carpinterías triple + aerotermia + instalación fotovoltaica",IF(F21="E","SATE fachada + carpinterías doble + instalación fotovoltaica",IF(F21="D","Mantenimiento de envolvente + instalación fotovoltaica en cubierta","Optimización energética + instalación fotovoltaica")))) -> Objetivo: alcanzar calificación C. Actual: Cal.G. SATE integral + cubierta + carpinterías triple + aerotermia + instalación fotovoltaica | U21: =IF($C21="","",IF(S21=0,"s/d",IF(S21>=4,"Valorar ascensor (verificar)","—"))) -> — | V21: =IF('📇 INVENTARIO'!L22="","",'📇 INVENTARIO'!L22) -> 112.4 | W21: =IF($C21="","",V21*'⚙️ SUPUESTOS'!$C$8*'⚙️ SUPUESTOS'!$C$9) -> 23.604 | X21: =IF('📇 INVENTARIO'!N22="","",'📇 INVENTARIO'!N22) -> 1414 | Y21: =IF($C21="","",W21*X21*'⚙️ SUPUESTOS'!$C$7) -> 30038.45 | Z21: =IF($C21="","",W21*'⚙️ SUPUESTOS'!$C$10) -> 31511.34 | AA21: =IF($C21="","",Y21*('⚙️ SUPUESTOS'!$C$12*'⚙️ SUPUESTOS'!$C$11+(1-'⚙️ SUPUESTOS'!$C$12)*'⚙️ SUPUESTOS'!$C$13)) -> 2048.6223 | AB21: =IF($C21="","",IF(Y21>0,ROUND(Y21*'⚙️ SUPUESTOS'!$C$12*'⚙️ SUPUESTOS'!$C$11,0),"")) -> 751 | AC21: =IF($C21="","",IF(Y21>0,ROUND(Y21*(1-'⚙️ SUPUESTOS'!$C$12)*'⚙️ SUPUESTOS'!$C$13,0),"")) -> 1298 | AD21: =IF($C21="","",IF(AND(ISNUMBER(AA21),ISNUMBER(AE21),AA21>0,AE21>0),ROUND(AA21*MAX(0,25-AE21),0),"")) -> 19704 | AE21: =IF($C21="","",IF(AA21>0,Z21/AA21,"")) -> 15.381723 | AF21: =IF($C21="","",IF(AE21="","—",IF(AE21<='⚙️ SUPUESTOS'!$C$32,"✔ Muy recomendable",IF(AE21<='⚙️ SUPUESTOS'!$C$33,"✔ Recomendable","Valorar")))) -> ✔ Recomendable | AG21: =IF('📇 INVENTARIO'!O22="","",'📇 INVENTARIO'!O22) -> 41.64935 | AH21: =IF('📇 INVENTARIO'!P22="","",'📇 INVENTARIO'!P22) -> -4.70989
A22: =IF($C22="","",RANK(O22,$O$3:$O$265,0)+COUNTIF($O$3:O22,O22)-1) -> 20 | B22: =IF($C22="","",IF(A22<='⚙️ SUPUESTOS'!$C$29,"Fase 1",IF(A22<='⚙️ SUPUESTOS'!$C$30,"Fase 2","Fase 3"))) -> Fase 1 | C22: =IF('📇 INVENTARIO'!B23="","",'📇 INVENTARIO'!B23) -> C/ Águila, 25 | D22: =IF('📇 INVENTARIO'!C23="","",'📇 INVENTARIO'!C23) -> 7724209UM5172D | E22: =IF('📇 INVENTARIO'!D23="","",'📇 INVENTARIO'!D23) -> 4718606026 | F22: =IF('📇 INVENTARIO'!F23="","",'📇 INVENTARIO'!F23) -> G | G22: =IF('📇 INVENTARIO'!G23="","",'📇 INVENTARIO'!G23) -> 402 | H22: =IF('📇 INVENTARIO'!H23="","",'📇 INVENTARIO'!H23) -> 83 | I22: =IF('📇 INVENTARIO'!I23="","",'📇 INVENTARIO'!I23) -> 277.9 | J22: =IF('📇 INVENTARIO'!J23="","",'📇 INVENTARIO'!J23) -> 1965 | K22: =IF($C22="","",(G22-'⚙️ SUPUESTOS'!$C$20)/('⚙️ SUPUESTOS'!$C$25-'⚙️ SUPUESTOS'!$C$20)) -> 0.44578313 | L22: =IF($C22="","",VLOOKUP($E22,'📊 SECCIONES'!$B$4:$S$9,16,FALSE())) -> 1 | M22: =IF($C22="","",VLOOKUP($E22,'📊 SECCIONES'!$B$4:$S$9,17,FALSE())) -> 1 | N22: =IF($C22="","",VLOOKUP($E22,'📊 SECCIONES'!$B$4:$S$9,18,FALSE())) -> 0 | O22: =IF($C22="","",ROUND('⚙️ SUPUESTOS'!$C$21*K22+'⚙️ SUPUESTOS'!$C$22*L22+'⚙️ SUPUESTOS'!$C$23*M22+'⚙️ SUPUESTOS'!$C$24*N22,4)) -> 0.6052 | P22: =IF($C22="","",VLOOKUP($E22,'📊 SECCIONES'!$B$4:$S$9,7,FALSE())) -> 66.51 | Q22: =IF($C22="","",VLOOKUP($E22,'📊 SECCIONES'!$B$4:$S$9,8,FALSE())) -> 17450 | R22: =IF($C22="","",VLOOKUP($E22,'📊 SECCIONES'!$B$4:$S$9,10,FALSE())) -> 10.6 | S22: =IF('📇 INVENTARIO'!K23="","",'📇 INVENTARIO'!K23) -> 3 | T22: =IF($C22="","","Objetivo: alcanzar calificación C. Actual: Cal."&F22&". "&IF(OR(F22="G",F22="F"),"SATE integral + cubierta + carpinterías triple + aerotermia + instalación fotovoltaica",IF(F22="E","SATE fachada + carpinterías doble + instalación fotovoltaica",IF(F22="D","Mantenimiento de envolvente + instalación fotovoltaica en cubierta","Optimización energética + instalación fotovoltaica")))) -> Objetivo: alcanzar calificación C. Actual: Cal.G. SATE integral + cubierta + carpinterías triple + aerotermia + instalación fotovoltaica | U22: =IF($C22="","",IF(S22=0,"s/d",IF(S22>=4,"Valorar ascensor (verificar)","—"))) -> — | V22: =IF('📇 INVENTARIO'!L23="","",'📇 INVENTARIO'!L23) -> 100.6 | W22: =IF($C22="","",V22*'⚙️ SUPUESTOS'!$C$8*'⚙️ SUPUESTOS'!$C$9) -> 21.126 | X22: =IF('📇 INVENTARIO'!N23="","",'📇 INVENTARIO'!N23) -> 1458 | Y22: =IF($C22="","",W22*X22*'⚙️ SUPUESTOS'!$C$7) -> 27721.537 | Z22: =IF($C22="","",W22*'⚙️ SUPUESTOS'!$C$10) -> 28203.21 | AA22: =IF($C22="","",Y22*('⚙️ SUPUESTOS'!$C$12*'⚙️ SUPUESTOS'!$C$11+(1-'⚙️ SUPUESTOS'!$C$12)*'⚙️ SUPUESTOS'!$C$13)) -> 1890.6088 | AB22: =IF($C22="","",IF(Y22>0,ROUND(Y22*'⚙️ SUPUESTOS'!$C$12*'⚙️ SUPUESTOS'!$C$11,0),"")) -> 693 | AC22: =IF($C22="","",IF(Y22>0,ROUND(Y22*(1-'⚙️ SUPUESTOS'!$C$12)*'⚙️ SUPUESTOS'!$C$13,0),"")) -> 1198 | AD22: =IF($C22="","",IF(AND(ISNUMBER(AA22),ISNUMBER(AE22),AA22>0,AE22>0),ROUND(AA22*MAX(0,25-AE22),0),"")) -> 19062 | AE22: =IF($C22="","",IF(AA22>0,Z22/AA22,"")) -> 14.917528 | AF22: =IF($C22="","",IF(AE22="","—",IF(AE22<='⚙️ SUPUESTOS'!$C$32,"✔ Muy recomendable",IF(AE22<='⚙️ SUPUESTOS'!$C$33,"✔ Recomendable","Valorar")))) -> ✔ Muy recomendable | AG22: =IF('📇 INVENTARIO'!O23="","",'📇 INVENTARIO'!O23) -> 41.64904 | AH22: =IF('📇 INVENTARIO'!P23="","",'📇 INVENTARIO'!P23) -> -4.70917
A23: =IF($C23="","",RANK(O23,$O$3:$O$265,0)+COUNTIF($O$3:O23,O23)-1) -> 21 | B23: =IF($C23="","",IF(A23<='⚙️ SUPUESTOS'!$C$29,"Fase 1",IF(A23<='⚙️ SUPUESTOS'!$C$30,"Fase 2","Fase 3"))) -> Fase 1 | C23: =IF('📇 INVENTARIO'!B24="","",'📇 INVENTARIO'!B24) -> C/ Paloma, 7 | D23: =IF('📇 INVENTARIO'!C24="","",'📇 INVENTARIO'!C24) -> 7724215UM5172D | E23: =IF('📇 INVENTARIO'!D24="","",'📇 INVENTARIO'!D24) -> 4718606026 | F23: =IF('📇 INVENTARIO'!F24="","",'📇 INVENTARIO'!F24) -> G | G23: =IF('📇 INVENTARIO'!G24="","",'📇 INVENTARIO'!G24) -> 399 | H23: =IF('📇 INVENTARIO'!H24="","",'📇 INVENTARIO'!H24) -> 84 | I23: =IF('📇 INVENTARIO'!I24="","",'📇 INVENTARIO'!I24) -> 237.4 | J23: =IF('📇 INVENTARIO'!J24="","",'📇 INVENTARIO'!J24) -> 1965 | K23: =IF($C23="","",(G23-'⚙️ SUPUESTOS'!$C$20)/('⚙️ SUPUESTOS'!$C$25-'⚙️ SUPUESTOS'!$C$20)) -> 0.44061962 | L23: =IF($C23="","",VLOOKUP($E23,'📊 SECCIONES'!$B$4:$S$9,16,FALSE())) -> 1 | M23: =IF($C23="","",VLOOKUP($E23,'📊 SECCIONES'!$B$4:$S$9,17,FALSE())) -> 1 | N23: =IF($C23="","",VLOOKUP($E23,'📊 SECCIONES'!$B$4:$S$9,18,FALSE())) -> 0 | O23: =IF($C23="","",ROUND('⚙️ SUPUESTOS'!$C$21*K23+'⚙️ SUPUESTOS'!$C$22*L23+'⚙️ SUPUESTOS'!$C$23*M23+'⚙️ SUPUESTOS'!$C$24*N23,4)) -> 0.6023 | P23: =IF($C23="","",VLOOKUP($E23,'📊 SECCIONES'!$B$4:$S$9,7,FALSE())) -> 66.51 | Q23: =IF($C23="","",VLOOKUP($E23,'📊 SECCIONES'!$B$4:$S$9,8,FALSE())) -> 17450 | R23: =IF($C23="","",VLOOKUP($E23,'📊 SECCIONES'!$B$4:$S$9,10,FALSE())) -> 10.6 | S23: =IF('📇 INVENTARIO'!K24="","",'📇 INVENTARIO'!K24) -> 3 | T23: =IF($C23="","","Objetivo: alcanzar calificación C. Actual: Cal."&F23&". "&IF(OR(F23="G",F23="F"),"SATE integral + cubierta + carpinterías triple + aerotermia + instalación fotovoltaica",IF(F23="E","SATE fachada + carpinterías doble + instalación fotovoltaica",IF(F23="D","Mantenimiento de envolvente + instalación fotovoltaica en cubierta","Optimización energética + instalación fotovoltaica")))) -> Objetivo: alcanzar calificación C. Actual: Cal.G. SATE integral + cubierta + carpinterías triple + aerotermia + instalación fotovoltaica | U23: =IF($C23="","",IF(S23=0,"s/d",IF(S23>=4,"Valorar ascensor (verificar)","—"))) -> — | V23: =IF('📇 INVENTARIO'!L24="","",'📇 INVENTARIO'!L24) -> 100.1 | W23: =IF($C23="","",V23*'⚙️ SUPUESTOS'!$C$8*'⚙️ SUPUESTOS'!$C$9) -> 21.021 | X23: =IF('📇 INVENTARIO'!N24="","",'📇 INVENTARIO'!N24) -> 1381 | Y23: =IF($C23="","",W23*X23*'⚙️ SUPUESTOS'!$C$7) -> 26127.001 | Z23: =IF($C23="","",W23*'⚙️ SUPUESTOS'!$C$10) -> 28063.035 | AA23: =IF($C23="","",Y23*('⚙️ SUPUESTOS'!$C$12*'⚙️ SUPUESTOS'!$C$11+(1-'⚙️ SUPUESTOS'!$C$12)*'⚙️ SUPUESTOS'!$C$13)) -> 1781.8615 | AB23: =IF($C23="","",IF(Y23>0,ROUND(Y23*'⚙️ SUPUESTOS'!$C$12*'⚙️ SUPUESTOS'!$C$11,0),"")) -> 653 | AC23: =IF($C23="","",IF(Y23>0,ROUND(Y23*(1-'⚙️ SUPUESTOS'!$C$12)*'⚙️ SUPUESTOS'!$C$13,0),"")) -> 1129 | AD23: =IF($C23="","",IF(AND(ISNUMBER(AA23),ISNUMBER(AE23),AA23>0,AE23>0),ROUND(AA23*MAX(0,25-AE23),0),"")) -> 16484 | AE23: =IF($C23="","",IF(AA23>0,Z23/AA23,"")) -> 15.74928 | AF23: =IF($C23="","",IF(AE23="","—",IF(AE23<='⚙️ SUPUESTOS'!$C$32,"✔ Muy recomendable",IF(AE23<='⚙️ SUPUESTOS'!$C$33,"✔ Recomendable","Valorar")))) -> ✔ Recomendable | AG23: =IF('📇 INVENTARIO'!O24="","",'📇 INVENTARIO'!O24) -> 41.64871 | AH23: =IF('📇 INVENTARIO'!P24="","",'📇 INVENTARIO'!P24) -> -4.70996
A24: =IF($C24="","",RANK(O24,$O$3:$O$265,0)+COUNTIF($O$3:O24,O24)-1) -> 22 | B24: =IF($C24="","",IF(A24<='⚙️ SUPUESTOS'!$C$29,"Fase 1",IF(A24<='⚙️ SUPUESTOS'!$C$30,"Fase 2","Fase 3"))) -> Fase 1 | C24: =IF('📇 INVENTARIO'!B25="","",'📇 INVENTARIO'!B25) -> C/ Grulla, 2 | D24: =IF('📇 INVENTARIO'!C25="","",'📇 INVENTARIO'!C25) -> 7925708UM5172F | E24: =IF('📇 INVENTARIO'!D25="","",'📇 INVENTARIO'!D25) -> 4718606023 | F24: =IF('📇 INVENTARIO'!F25="","",'📇 INVENTARIO'!F25) -> G | G24: =IF('📇 INVENTARIO'!G25="","",'📇 INVENTARIO'!G25) -> 532 | H24: =IF('📇 INVENTARIO'!H25="","",'📇 INVENTARIO'!H25) -> 138 | I24: =IF('📇 INVENTARIO'!I25="","",'📇 INVENTARIO'!I25) -> 252.8 | J24: =IF('📇 INVENTARIO'!J25="","",'📇 INVENTARIO'!J25) -> 1965 | K24: =IF($C24="","",(G24-'⚙️ SUPUESTOS'!$C$20)/('⚙️ SUPUESTOS'!$C$25-'⚙️ SUPUESTOS'!$C$20)) -> 0.66953528 | L24: =IF($C24="","",VLOOKUP($E24,'📊 SECCIONES'!$B$4:$S$9,16,FALSE())) -> 0.54128061 | M24: =IF($C24="","",VLOOKUP($E24,'📊 SECCIONES'!$B$4:$S$9,17,FALSE())) -> 0.59585492 | N24: =IF($C24="","",VLOOKUP($E24,'📊 SECCIONES'!$B$4:$S$9,18,FALSE())) -> 0.28636364 | O24: =IF($C24="","",ROUND('⚙️ SUPUESTOS'!$C$21*K24+'⚙️ SUPUESTOS'!$C$22*L24+'⚙️ SUPUESTOS'!$C$23*M24+'⚙️ SUPUESTOS'!$C$24*N24,4)) -> 0.5965 | P24: =IF($C24="","",VLOOKUP($E24,'📊 SECCIONES'!$B$4:$S$9,7,FALSE())) -> 39.41 | Q24: =IF($C24="","",VLOOKUP($E24,'📊 SECCIONES'!$B$4:$S$9,8,FALSE())) -> 22486 | R24: =IF($C24="","",VLOOKUP($E24,'📊 SECCIONES'!$B$4:$S$9,10,FALSE())) -> 16.9 | S24: =IF('📇 INVENTARIO'!K25="","",'📇 INVENTARIO'!K25) -> 3 | T24: =IF($C24="","","Objetivo: alcanzar calificación C. Actual: Cal."&F24&". "&IF(OR(F24="G",F24="F"),"SATE integral + cubierta + carpinterías triple + aerotermia + instalación fotovoltaica",IF(F24="E","SATE fachada + carpinterías doble + instalación fotovoltaica",IF(F24="D","Mantenimiento de envolvente + instalación fotovoltaica en cubierta","Optimización energética + instalación fotovoltaica")))) -> Objetivo: alcanzar calificación C. Actual: Cal.G. SATE integral + cubierta + carpinterías triple + aerotermia + instalación fotovoltaica | U24: =IF($C24="","",IF(S24=0,"s/d",IF(S24>=4,"Valorar ascensor (verificar)","—"))) -> — | V24: =IF('📇 INVENTARIO'!L25="","",'📇 INVENTARIO'!L25) -> 97.5 | W24: =IF($C24="","",V24*'⚙️ SUPUESTOS'!$C$8*'⚙️ SUPUESTOS'!$C$9) -> 20.475 | X24: =IF('📇 INVENTARIO'!N25="","",'📇 INVENTARIO'!N25) -> 1379 | Y24: =IF($C24="","",W24*X24*'⚙️ SUPUESTOS'!$C$7) -> 25411.522 | Z24: =IF($C24="","",W24*'⚙️ SUPUESTOS'!$C$10) -> 27334.125 | AA24: =IF($C24="","",Y24*('⚙️ SUPUESTOS'!$C$12*'⚙️ SUPUESTOS'!$C$11+(1-'⚙️ SUPUESTOS'!$C$12)*'⚙️ SUPUESTOS'!$C$13)) -> 1733.0658 | AB24: =IF($C24="","",IF(Y24>0,ROUND(Y24*'⚙️ SUPUESTOS'!$C$12*'⚙️ SUPUESTOS'!$C$11,0),"")) -> 635 | AC24: =IF($C24="","",IF(Y24>0,ROUND(Y24*(1-'⚙️ SUPUESTOS'!$C$12)*'⚙️ SUPUESTOS'!$C$13,0),"")) -> 1098 | AD24: =IF($C24="","",IF(AND(ISNUMBER(AA24),ISNUMBER(AE24),AA24>0,AE24>0),ROUND(AA24*MAX(0,25-AE24),0),"")) -> 15993 | AE24: =IF($C24="","",IF(AA24>0,Z24/AA24,"")) -> 15.772122 | AF24: =IF($C24="","",IF(AE24="","—",IF(AE24<='⚙️ SUPUESTOS'!$C$32,"✔ Muy recomendable",IF(AE24<='⚙️ SUPUESTOS'!$C$33,"✔ Recomendable","Valorar")))) -> ✔ Recomendable | AG24: =IF('📇 INVENTARIO'!O25="","",'📇 INVENTARIO'!O25) -> 41.64981 | AH24: =IF('📇 INVENTARIO'!P25="","",'📇 INVENTARIO'!P25) -> -4.70826
A25: =IF($C25="","",RANK(O25,$O$3:$O$265,0)+COUNTIF($O$3:O25,O25)-1) -> 23 | B25: =IF($C25="","",IF(A25<='⚙️ SUPUESTOS'!$C$29,"Fase 1",IF(A25<='⚙️ SUPUESTOS'!$C$30,"Fase 2","Fase 3"))) -> Fase 1 | C25: =IF('📇 INVENTARIO'!B26="","",'📇 INVENTARIO'!B26) -> C/ Paloma, 1 | D25: =IF('📇 INVENTARIO'!C26="","",'📇 INVENTARIO'!C26) -> 7724212UM5172D | E25: =IF('📇 INVENTARIO'!D26="","",'📇 INVENTARIO'!D26) -> 4718606026 | F25: =IF('📇 INVENTARIO'!F26="","",'📇 INVENTARIO'!F26) -> G | G25: =IF('📇 INVENTARIO'!G26="","",'📇 INVENTARIO'!G26) -> 375 | H25: =IF('📇 INVENTARIO'!H26="","",'📇 INVENTARIO'!H26) -> 67 | I25: =IF('📇 INVENTARIO'!I26="","",'📇 INVENTARIO'!I26) -> 185.6 | J25: =IF('📇 INVENTARIO'!J26="","",'📇 INVENTARIO'!J26) -> 1965 | K25: =IF($C25="","",(G25-'⚙️ SUPUESTOS'!$C$20)/('⚙️ SUPUESTOS'!$C$25-'⚙️ SUPUESTOS'!$C$20)) -> 0.39931153 | L25: =IF($C25="","",VLOOKUP($E25,'📊 SECCIONES'!$B$4:$S$9,16,FALSE())) -> 1 | M25: =IF($C25="","",VLOOKUP($E25,'📊 SECCIONES'!$B$4:$S$9,17,FALSE())) -> 1 | N25: =IF($C25="","",VLOOKUP($E25,'📊 SECCIONES'!$B$4:$S$9,18,FALSE())) -> 0 | O25: =IF($C25="","",ROUND('⚙️ SUPUESTOS'!$C$21*K25+'⚙️ SUPUESTOS'!$C$22*L25+'⚙️ SUPUESTOS'!$C$23*M25+'⚙️ SUPUESTOS'!$C$24*N25,4)) -> 0.5796 | P25: =IF($C25="","",VLOOKUP($E25,'📊 SECCIONES'!$B$4:$S$9,7,FALSE())) -> 66.51 | Q25: =IF($C25="","",VLOOKUP($E25,'📊 SECCIONES'!$B$4:$S$9,8,FALSE())) -> 17450 | R25: =IF($C25="","",VLOOKUP($E25,'📊 SECCIONES'!$B$4:$S$9,10,FALSE())) -> 10.6 | S25: =IF('📇 INVENTARIO'!K26="","",'📇 INVENTARIO'!K26) -> 3 | T25: =IF($C25="","","Objetivo: alcanzar calificación C. Actual: Cal."&F25&". "&IF(OR(F25="G",F25="F"),"SATE integral + cubierta + carpinterías triple + aerotermia + instalación fotovoltaica",IF(F25="E","SATE fachada + carpinterías doble + instalación fotovoltaica",IF(F25="D","Mantenimiento de envolvente + instalación fotovoltaica en cubierta","Optimización energética + instalación fotovoltaica")))) -> Objetivo: alcanzar calificación C. Actual: Cal.G. SATE integral + cubierta + carpinterías triple + aerotermia + instalación fotovoltaica | U25: =IF($C25="","",IF(S25=0,"s/d",IF(S25>=4,"Valorar ascensor (verificar)","—"))) -> — | V25: =IF('📇 INVENTARIO'!L26="","",'📇 INVENTARIO'!L26) -> 100.2 | W25: =IF($C25="","",V25*'⚙️ SUPUESTOS'!$C$8*'⚙️ SUPUESTOS'!$C$9) -> 21.042 | X25: =IF('📇 INVENTARIO'!N26="","",'📇 INVENTARIO'!N26) -> 1315 | Y25: =IF($C25="","",W25*X25*'⚙️ SUPUESTOS'!$C$7) -> 24903.207 | Z25: =IF($C25="","",W25*'⚙️ SUPUESTOS'!$C$10) -> 28091.07 | AA25: =IF($C25="","",Y25*('⚙️ SUPUESTOS'!$C$12*'⚙️ SUPUESTOS'!$C$11+(1-'⚙️ SUPUESTOS'!$C$12)*'⚙️ SUPUESTOS'!$C$13)) -> 1698.3987 | AB25: =IF($C25="","",IF(Y25>0,ROUND(Y25*'⚙️ SUPUESTOS'!$C$12*'⚙️ SUPUESTOS'!$C$11,0),"")) -> 623 | AC25: =IF($C25="","",IF(Y25>0,ROUND(Y25*(1-'⚙️ SUPUESTOS'!$C$12)*'⚙️ SUPUESTOS'!$C$13,0),"")) -> 1076 | AD25: =IF($C25="","",IF(AND(ISNUMBER(AA25),ISNUMBER(AE25),AA25>0,AE25>0),ROUND(AA25*MAX(0,25-AE25),0),"")) -> 14369 | AE25: =IF($C25="","",IF(AA25>0,Z25/AA25,"")) -> 16.539738 | AF25: =IF($C25="","",IF(AE25="","—",IF(AE25<='⚙️ SUPUESTOS'!$C$32,"✔ Muy recomendable",IF(AE25<='⚙️ SUPUESTOS'!$C$33,"✔ Recomendable","Valorar")))) -> Valorar | AG25: =IF('📇 INVENTARIO'!O26="","",'📇 INVENTARIO'!O26) -> 41.64914 | AH25: =IF('📇 INVENTARIO'!P26="","",'📇 INVENTARIO'!P26) -> -4.70956
A26: =IF($C26="","",RANK(O26,$O$3:$O$265,0)+COUNTIF($O$3:O26,O26)-1) -> 24 | B26: =IF($C26="","",IF(A26<='⚙️ SUPUESTOS'!$C$29,"Fase 1",IF(A26<='⚙️ SUPUESTOS'!$C$30,"Fase 2","Fase 3"))) -> Fase 1 | C26: =IF('📇 INVENTARIO'!B27="","",'📇 INVENTARIO'!B27) -> C/ Zorzal, 18 | D26: =IF('📇 INVENTARIO'!C27="","",'📇 INVENTARIO'!C27) -> 7724206UM5172D | E26: =IF('📇 INVENTARIO'!D27="","",'📇 INVENTARIO'!D27) -> 4718606026 | F26: =IF('📇 INVENTARIO'!F27="","",'📇 INVENTARIO'!F27) -> G | G26: =IF('📇 INVENTARIO'!G27="","",'📇 INVENTARIO'!G27) -> 368 | H26: =IF('📇 INVENTARIO'!H27="","",'📇 INVENTARIO'!H27) -> 73 | I26: =IF('📇 INVENTARIO'!I27="","",'📇 INVENTARIO'!I27) -> 201.2 | J26: =IF('📇 INVENTARIO'!J27="","",'📇 INVENTARIO'!J27) -> 1965 | K26: =IF($C26="","",(G26-'⚙️ SUPUESTOS'!$C$20)/('⚙️ SUPUESTOS'!$C$25-'⚙️ SUPUESTOS'!$C$20)) -> 0.38726334 | L26: =IF($C26="","",VLOOKUP($E26,'📊 SECCIONES'!$B$4:$S$9,16,FALSE())) -> 1 | M26: =IF($C26="","",VLOOKUP($E26,'📊 SECCIONES'!$B$4:$S$9,17,FALSE())) -> 1 | N26: =IF($C26="","",VLOOKUP($E26,'📊 SECCIONES'!$B$4:$S$9,18,FALSE())) -> 0 | O26: =IF($C26="","",ROUND('⚙️ SUPUESTOS'!$C$21*K26+'⚙️ SUPUESTOS'!$C$22*L26+'⚙️ SUPUESTOS'!$C$23*M26+'⚙️ SUPUESTOS'!$C$24*N26,4)) -> 0.573 | P26: =IF($C26="","",VLOOKUP($E26,'📊 SECCIONES'!$B$4:$S$9,7,FALSE())) -> 66.51 | Q26: =IF($C26="","",VLOOKUP($E26,'📊 SECCIONES'!$B$4:$S$9,8,FALSE())) -> 17450 | R26: =IF($C26="","",VLOOKUP($E26,'📊 SECCIONES'!$B$4:$S$9,10,FALSE())) -> 10.6 | S26: =IF('📇 INVENTARIO'!K27="","",'📇 INVENTARIO'!K27) -> 3 | T26: =IF($C26="","","Objetivo: alcanzar calificación C. Actual: Cal."&F26&". "&IF(OR(F26="G",F26="F"),"SATE integral + cubierta + carpinterías triple + aerotermia + instalación fotovoltaica",IF(F26="E","SATE fachada + carpinterías doble + instalación fotovoltaica",IF(F26="D","Mantenimiento de envolvente + instalación fotovoltaica en cubierta","Optimización energética + instalación fotovoltaica")))) -> Objetivo: alcanzar calificación C. Actual: Cal.G. SATE integral + cubierta + carpinterías triple + aerotermia + instalación fotovoltaica | U26: =IF($C26="","",IF(S26=0,"s/d",IF(S26>=4,"Valorar ascensor (verificar)","—"))) -> — | V26: =IF('📇 INVENTARIO'!L27="","",'📇 INVENTARIO'!L27) -> 102.6 | W26: =IF($C26="","",V26*'⚙️ SUPUESTOS'!$C$8*'⚙️ SUPUESTOS'!$C$9) -> 21.546 | X26: =IF('📇 INVENTARIO'!N27="","",'📇 INVENTARIO'!N27) -> 1312 | Y26: =IF($C26="","",W26*X26*'⚙️ SUPUESTOS'!$C$7) -> 25441.517 | Z26: =IF($C26="","",W26*'⚙️ SUPUESTOS'!$C$10) -> 28763.91 | AA26: =IF($C26="","",Y26*('⚙️ SUPUESTOS'!$C$12*'⚙️ SUPUESTOS'!$C$11+(1-'⚙️ SUPUESTOS'!$C$12)*'⚙️ SUPUESTOS'!$C$13)) -> 1735.1114 | AB26: =IF($C26="","",IF(Y26>0,ROUND(Y26*'⚙️ SUPUESTOS'!$C$12*'⚙️ SUPUESTOS'!$C$11,0),"")) -> 636 | AC26: =IF($C26="","",IF(Y26>0,ROUND(Y26*(1-'⚙️ SUPUESTOS'!$C$12)*'⚙️ SUPUESTOS'!$C$13,0),"")) -> 1099 | AD26: =IF($C26="","",IF(AND(ISNUMBER(AA26),ISNUMBER(AE26),AA26>0,AE26>0),ROUND(AA26*MAX(0,25-AE26),0),"")) -> 14614 | AE26: =IF($C26="","",IF(AA26>0,Z26/AA26,"")) -> 16.577558 | AF26: =IF($C26="","",IF(AE26="","—",IF(AE26<='⚙️ SUPUESTOS'!$C$32,"✔ Muy recomendable",IF(AE26<='⚙️ SUPUESTOS'!$C$33,"✔ Recomendable","Valorar")))) -> Valorar | AG26: =IF('📇 INVENTARIO'!O27="","",'📇 INVENTARIO'!O27) -> 41.64932 | AH26: =IF('📇 INVENTARIO'!P27="","",'📇 INVENTARIO'!P27) -> -4.70969
A27: =IF($C27="","",RANK(O27,$O$3:$O$265,0)+COUNTIF($O$3:O27,O27)-1) -> 25 | B27: =IF($C27="","",IF(A27<='⚙️ SUPUESTOS'!$C$29,"Fase 1",IF(A27<='⚙️ SUPUESTOS'!$C$30,"Fase 2","Fase 3"))) -> Fase 1 | C27: =IF('📇 INVENTARIO'!B28="","",'📇 INVENTARIO'!B28) -> C/ Pavo Real, 15 | D27: =IF('📇 INVENTARIO'!C28="","",'📇 INVENTARIO'!C28) -> 7625407UM5172F | E27: =IF('📇 INVENTARIO'!D28="","",'📇 INVENTARIO'!D28) -> 4718606026 | F27: =IF('📇 INVENTARIO'!F28="","",'📇 INVENTARIO'!F28) -> F | G27: =IF('📇 INVENTARIO'!G28="","",'📇 INVENTARIO'!G28) -> 368 | H27: =IF('📇 INVENTARIO'!H28="","",'📇 INVENTARIO'!H28) -> 97 | I27: =IF('📇 INVENTARIO'!I28="","",'📇 INVENTARIO'!I28) -> 218 | J27: =IF('📇 INVENTARIO'!J28="","",'📇 INVENTARIO'!J28) -> 1965 | K27: =IF($C27="","",(G27-'⚙️ SUPUESTOS'!$C$20)/('⚙️ SUPUESTOS'!$C$25-'⚙️ SUPUESTOS'!$C$20)) -> 0.38726334 | L27: =IF($C27="","",VLOOKUP($E27,'📊 SECCIONES'!$B$4:$S$9,16,FALSE())) -> 1 | M27: =IF($C27="","",VLOOKUP($E27,'📊 SECCIONES'!$B$4:$S$9,17,FALSE())) -> 1 | N27: =IF($C27="","",VLOOKUP($E27,'📊 SECCIONES'!$B$4:$S$9,18,FALSE())) -> 0 | O27: =IF($C27="","",ROUND('⚙️ SUPUESTOS'!$C$21*K27+'⚙️ SUPUESTOS'!$C$22*L27+'⚙️ SUPUESTOS'!$C$23*M27+'⚙️ SUPUESTOS'!$C$24*N27,4)) -> 0.573 | P27: =IF($C27="","",VLOOKUP($E27,'📊 SECCIONES'!$B$4:$S$9,7,FALSE())) -> 66.51 | Q27: =IF($C27="","",VLOOKUP($E27,'📊 SECCIONES'!$B$4:$S$9,8,FALSE())) -> 17450 | R27: =IF($C27="","",VLOOKUP($E27,'📊 SECCIONES'!$B$4:$S$9,10,FALSE())) -> 10.6 | S27: =IF('📇 INVENTARIO'!K28="","",'📇 INVENTARIO'!K28) -> 3 | T27: =IF($C27="","","Objetivo: alcanzar calificación C. Actual: Cal."&F27&". "&IF(OR(F27="G",F27="F"),"SATE integral + cubierta + carpinterías triple + aerotermia + instalación fotovoltaica",IF(F27="E","SATE fachada + carpinterías doble + instalación fotovoltaica",IF(F27="D","Mantenimiento de envolvente + instalación fotovoltaica en cubierta","Optimización energética + instalación fotovoltaica")))) -> Objetivo: alcanzar calificación C. Actual: Cal.F. SATE integral + cubierta + carpinterías triple + aerotermia + instalación fotovoltaica | U27: =IF($C27="","",IF(S27=0,"s/d",IF(S27>=4,"Valorar ascensor (verificar)","—"))) -> — | V27: =IF('📇 INVENTARIO'!L28="","",'📇 INVENTARIO'!L28) -> 94.7 | W27: =IF($C27="","",V27*'⚙️ SUPUESTOS'!$C$8*'⚙️ SUPUESTOS'!$C$9) -> 19.887 | X27: =IF('📇 INVENTARIO'!N28="","",'📇 INVENTARIO'!N28) -> 1484 | Y27: =IF($C27="","",W27*X27*'⚙️ SUPUESTOS'!$C$7) -> 26561.077 | Z27: =IF($C27="","",W27*'⚙️ SUPUESTOS'!$C$10) -> 26549.145 | AA27: =IF($C27="","",Y27*('⚙️ SUPUESTOS'!$C$12*'⚙️ SUPUESTOS'!$C$11+(1-'⚙️ SUPUESTOS'!$C$12)*'⚙️ SUPUESTOS'!$C$13)) -> 1811.4655 | AB27: =IF($C27="","",IF(Y27>0,ROUND(Y27*'⚙️ SUPUESTOS'!$C$12*'⚙️ SUPUESTOS'!$C$11,0),"")) -> 664 | AC27: =IF($C27="","",IF(Y27>0,ROUND(Y27*(1-'⚙️ SUPUESTOS'!$C$12)*'⚙️ SUPUESTOS'!$C$13,0),"")) -> 1147 | AD27: =IF($C27="","",IF(AND(ISNUMBER(AA27),ISNUMBER(AE27),AA27>0,AE27>0),ROUND(AA27*MAX(0,25-AE27),0),"")) -> 18737 | AE27: =IF($C27="","",IF(AA27>0,Z27/AA27,"")) -> 14.65617 | AF27: =IF($C27="","",IF(AE27="","—",IF(AE27<='⚙️ SUPUESTOS'!$C$32,"✔ Muy recomendable",IF(AE27<='⚙️ SUPUESTOS'!$C$33,"✔ Recomendable","Valorar")))) -> ✔ Muy recomendable | AG27: =IF('📇 INVENTARIO'!O28="","",'📇 INVENTARIO'!O28) -> 41.64912 | AH27: =IF('📇 INVENTARIO'!P28="","",'📇 INVENTARIO'!P28) -> -4.71082
A28: =IF($C28="","",RANK(O28,$O$3:$O$265,0)+COUNTIF($O$3:O28,O28)-1) -> 26 | B28: =IF($C28="","",IF(A28<='⚙️ SUPUESTOS'!$C$29,"Fase 1",IF(A28<='⚙️ SUPUESTOS'!$C$30,"Fase 2","Fase 3"))) -> Fase 1 | C28: =IF('📇 INVENTARIO'!B29="","",'📇 INVENTARIO'!B29) -> C/ Villabáñez, 12 | D28: =IF('📇 INVENTARIO'!C29="","",'📇 INVENTARIO'!C29) -> 7724207UM5172D | E28: =IF('📇 INVENTARIO'!D29="","",'📇 INVENTARIO'!D29) -> 4718606026 | F28: =IF('📇 INVENTARIO'!F29="","",'📇 INVENTARIO'!F29) -> G | G28: =IF('📇 INVENTARIO'!G29="","",'📇 INVENTARIO'!G29) -> 367 | H28: =IF('📇 INVENTARIO'!H29="","",'📇 INVENTARIO'!H29) -> 72 | I28: =IF('📇 INVENTARIO'!I29="","",'📇 INVENTARIO'!I29) -> 188.1 | J28: =IF('📇 INVENTARIO'!J29="","",'📇 INVENTARIO'!J29) -> 1965 | K28: =IF($C28="","",(G28-'⚙️ SUPUESTOS'!$C$20)/('⚙️ SUPUESTOS'!$C$25-'⚙️ SUPUESTOS'!$C$20)) -> 0.38554217 | L28: =IF($C28="","",VLOOKUP($E28,'📊 SECCIONES'!$B$4:$S$9,16,FALSE())) -> 1 | M28: =IF($C28="","",VLOOKUP($E28,'📊 SECCIONES'!$B$4:$S$9,17,FALSE())) -> 1 | N28: =IF($C28="","",VLOOKUP($E28,'📊 SECCIONES'!$B$4:$S$9,18,FALSE())) -> 0 | O28: =IF($C28="","",ROUND('⚙️ SUPUESTOS'!$C$21*K28+'⚙️ SUPUESTOS'!$C$22*L28+'⚙️ SUPUESTOS'!$C$23*M28+'⚙️ SUPUESTOS'!$C$24*N28,4)) -> 0.572 | P28: =IF($C28="","",VLOOKUP($E28,'📊 SECCIONES'!$B$4:$S$9,7,FALSE())) -> 66.51 | Q28: =IF($C28="","",VLOOKUP($E28,'📊 SECCIONES'!$B$4:$S$9,8,FALSE())) -> 17450 | R28: =IF($C28="","",VLOOKUP($E28,'📊 SECCIONES'!$B$4:$S$9,10,FALSE())) -> 10.6 | S28: =IF('📇 INVENTARIO'!K29="","",'📇 INVENTARIO'!K29) -> 3 | T28: =IF($C28="","","Objetivo: alcanzar calificación C. Actual: Cal."&F28&". "&IF(OR(F28="G",F28="F"),"SATE integral + cubierta + carpinterías triple + aerotermia + instalación fotovoltaica",IF(F28="E","SATE fachada + carpinterías doble + instalación fotovoltaica",IF(F28="D","Mantenimiento de envolvente + instalación fotovoltaica en cubierta","Optimización energética + instalación fotovoltaica")))) -> Objetivo: alcanzar calificación C. Actual: Cal.G. SATE integral + cubierta + carpinterías triple + aerotermia + instalación fotovoltaica | U28: =IF($C28="","",IF(S28=0,"s/d",IF(S28>=4,"Valorar ascensor (verificar)","—"))) -> — | V28: =IF('📇 INVENTARIO'!L29="","",'📇 INVENTARIO'!L29) -> 114.7 | W28: =IF($C28="","",V28*'⚙️ SUPUESTOS'!$C$8*'⚙️ SUPUESTOS'!$C$9) -> 24.087 | X28: =IF('📇 INVENTARIO'!N29="","",'📇 INVENTARIO'!N29) -> 1383 | Y28: =IF($C28="","",W28*X28*'⚙️ SUPUESTOS'!$C$7) -> 29981.089 | Z28: =IF($C28="","",W28*'⚙️ SUPUESTOS'!$C$10) -> 32156.145 | AA28: =IF($C28="","",Y28*('⚙️ SUPUESTOS'!$C$12*'⚙️ SUPUESTOS'!$C$11+(1-'⚙️ SUPUESTOS'!$C$12)*'⚙️ SUPUESTOS'!$C$13)) -> 2044.7103 | AB28: =IF($C28="","",IF(Y28>0,ROUND(Y28*'⚙️ SUPUESTOS'!$C$12*'⚙️ SUPUESTOS'!$C$11,0),"")) -> 750 | AC28: =IF($C28="","",IF(Y28>0,ROUND(Y28*(1-'⚙️ SUPUESTOS'!$C$12)*'⚙️ SUPUESTOS'!$C$13,0),"")) -> 1295 | AD28: =IF($C28="","",IF(AND(ISNUMBER(AA28),ISNUMBER(AE28),AA28>0,AE28>0),ROUND(AA28*MAX(0,25-AE28),0),"")) -> 18962 | AE28: =IF($C28="","",IF(AA28>0,Z28/AA28,"")) -> 15.726504 | AF28: =IF($C28="","",IF(AE28="","—",IF(AE28<='⚙️ SUPUESTOS'!$C$32,"✔ Muy recomendable",IF(AE28<='⚙️ SUPUESTOS'!$C$33,"✔ Recomendable","Valorar")))) -> ✔ Recomendable | AG28: =IF('📇 INVENTARIO'!O29="","",'📇 INVENTARIO'!O29) -> 41.64927 | AH28: =IF('📇 INVENTARIO'!P29="","",'📇 INVENTARIO'!P29) -> -4.70942
A29: =IF($C29="","",RANK(O29,$O$3:$O$265,0)+COUNTIF($O$3:O29,O29)-1) -> 27 | B29: =IF($C29="","",IF(A29<='⚙️ SUPUESTOS'!$C$29,"Fase 1",IF(A29<='⚙️ SUPUESTOS'!$C$30,"Fase 2","Fase 3"))) -> Fase 1 | C29: =IF('📇 INVENTARIO'!B30="","",'📇 INVENTARIO'!B30) -> C/ Villabáñez, 2 | D29: =IF('📇 INVENTARIO'!C30="","",'📇 INVENTARIO'!C30) -> 7625401UM5172F | E29: =IF('📇 INVENTARIO'!D30="","",'📇 INVENTARIO'!D30) -> 4718606026 | F29: =IF('📇 INVENTARIO'!F30="","",'📇 INVENTARIO'!F30) -> G | G29: =IF('📇 INVENTARIO'!G30="","",'📇 INVENTARIO'!G30) -> 346 | H29: =IF('📇 INVENTARIO'!H30="","",'📇 INVENTARIO'!H30) -> 58.5 | I29: =IF('📇 INVENTARIO'!I30="","",'📇 INVENTARIO'!I30) -> 140.2 | J29: =IF('📇 INVENTARIO'!J30="","",'📇 INVENTARIO'!J30) -> 1958 | K29: =IF($C29="","",(G29-'⚙️ SUPUESTOS'!$C$20)/('⚙️ SUPUESTOS'!$C$25-'⚙️ SUPUESTOS'!$C$20)) -> 0.34939759 | L29: =IF($C29="","",VLOOKUP($E29,'📊 SECCIONES'!$B$4:$S$9,16,FALSE())) -> 1 | M29: =IF($C29="","",VLOOKUP($E29,'📊 SECCIONES'!$B$4:$S$9,17,FALSE())) -> 1 | N29: =IF($C29="","",VLOOKUP($E29,'📊 SECCIONES'!$B$4:$S$9,18,FALSE())) -> 0 | O29: =IF($C29="","",ROUND('⚙️ SUPUESTOS'!$C$21*K29+'⚙️ SUPUESTOS'!$C$22*L29+'⚙️ SUPUESTOS'!$C$23*M29+'⚙️ SUPUESTOS'!$C$24*N29,4)) -> 0.5522 | P29: =IF($C29="","",VLOOKUP($E29,'📊 SECCIONES'!$B$4:$S$9,7,FALSE())) -> 66.51 | Q29: =IF($C29="","",VLOOKUP($E29,'📊 SECCIONES'!$B$4:$S$9,8,FALSE())) -> 17450 | R29: =IF($C29="","",VLOOKUP($E29,'📊 SECCIONES'!$B$4:$S$9,10,FALSE())) -> 10.6 | S29: =IF('📇 INVENTARIO'!K30="","",'📇 INVENTARIO'!K30) -> 5 | T29: =IF($C29="","","Objetivo: alcanzar calificación C. Actual: Cal."&F29&". "&IF(OR(F29="G",F29="F"),"SATE integral + cubierta + carpinterías triple + aerotermia + instalación fotovoltaica",IF(F29="E","SATE fachada + carpinterías doble + instalación fotovoltaica",IF(F29="D","Mantenimiento de envolvente + instalación fotovoltaica en cubierta","Optimización energética + instalación fotovoltaica")))) -> Objetivo: alcanzar calificación C. Actual: Cal.G. SATE integral + cubierta + carpinterías triple + aerotermia + instalación fotovoltaica | U29: =IF($C29="","",IF(S29=0,"s/d",IF(S29>=4,"Valorar ascensor (verificar)","—"))) -> Valorar ascensor (verificar) | V29: =IF('📇 INVENTARIO'!L30="","",'📇 INVENTARIO'!L30) -> 330.5 | W29: =IF($C29="","",V29*'⚙️ SUPUESTOS'!$C$8*'⚙️ SUPUESTOS'!$C$9) -> 69.405 | X29: =IF('📇 INVENTARIO'!N30="","",'📇 INVENTARIO'!N30) -> 1373 | Y29: =IF($C29="","",W29*X29*'⚙️ SUPUESTOS'!$C$7) -> 85763.759 | Z29: =IF($C29="","",W29*'⚙️ SUPUESTOS'!$C$10) -> 92655.675 | AA29: =IF($C29="","",Y29*('⚙️ SUPUESTOS'!$C$12*'⚙️ SUPUESTOS'!$C$11+(1-'⚙️ SUPUESTOS'!$C$12)*'⚙️ SUPUESTOS'!$C$13)) -> 5849.0883 | AB29: =IF($C29="","",IF(Y29>0,ROUND(Y29*'⚙️ SUPUESTOS'!$C$12*'⚙️ SUPUESTOS'!$C$11,0),"")) -> 2144 | AC29: =IF($C29="","",IF(Y29>0,ROUND(Y29*(1-'⚙️ SUPUESTOS'!$C$12)*'⚙️ SUPUESTOS'!$C$13,0),"")) -> 3705 | AD29: =IF($C29="","",IF(AND(ISNUMBER(AA29),ISNUMBER(AE29),AA29>0,AE29>0),ROUND(AA29*MAX(0,25-AE29),0),"")) -> 53572 | AE29: =IF($C29="","",IF(AA29>0,Z29/AA29,"")) -> 15.841046 | AF29: =IF($C29="","",IF(AE29="","—",IF(AE29<='⚙️ SUPUESTOS'!$C$32,"✔ Muy recomendable",IF(AE29<='⚙️ SUPUESTOS'!$C$33,"✔ Recomendable","Valorar")))) -> ✔ Recomendable | AG29: =IF('📇 INVENTARIO'!O30="","",'📇 INVENTARIO'!O30) -> 41.64988 | AH29: =IF('📇 INVENTARIO'!P30="","",'📇 INVENTARIO'!P30) -> -4.71069
A30: =IF($C30="","",RANK(O30,$O$3:$O$265,0)+COUNTIF($O$3:O30,O30)-1) -> 28 | B30: =IF($C30="","",IF(A30<='⚙️ SUPUESTOS'!$C$29,"Fase 1",IF(A30<='⚙️ SUPUESTOS'!$C$30,"Fase 2","Fase 3"))) -> Fase 1 | C30: =IF('📇 INVENTARIO'!B31="","",'📇 INVENTARIO'!B31) -> C/ Cigüeña, 39 | D30: =IF('📇 INVENTARIO'!C31="","",'📇 INVENTARIO'!C31) -> 7824513UM5172D | E30: =IF('📇 INVENTARIO'!D31="","",'📇 INVENTARIO'!D31) -> 4718606026 | F30: =IF('📇 INVENTARIO'!F31="","",'📇 INVENTARIO'!F31) -> G | G30: =IF('📇 INVENTARIO'!G31="","",'📇 INVENTARIO'!G31) -> 344 | H30: =IF('📇 INVENTARIO'!H31="","",'📇 INVENTARIO'!H31) -> 66 | I30: =IF('📇 INVENTARIO'!I31="","",'📇 INVENTARIO'!I31) -> 138.2 | J30: =IF('📇 INVENTARIO'!J31="","",'📇 INVENTARIO'!J31) -> 1965 | K30: =IF($C30="","",(G30-'⚙️ SUPUESTOS'!$C$20)/('⚙️ SUPUESTOS'!$C$25-'⚙️ SUPUESTOS'!$C$20)) -> 0.34595525 | L30: =IF($C30="","",VLOOKUP($E30,'📊 SECCIONES'!$B$4:$S$9,16,FALSE())) -> 1 | M30: =IF($C30="","",VLOOKUP($E30,'📊 SECCIONES'!$B$4:$S$9,17,FALSE())) -> 1 | N30: =IF($C30="","",VLOOKUP($E30,'📊 SECCIONES'!$B$4:$S$9,18,FALSE())) -> 0 | O30: =IF($C30="","",ROUND('⚙️ SUPUESTOS'!$C$21*K30+'⚙️ SUPUESTOS'!$C$22*L30+'⚙️ SUPUESTOS'!$C$23*M30+'⚙️ SUPUESTOS'!$C$24*N30,4)) -> 0.5503 | P30: =IF($C30="","",VLOOKUP($E30,'📊 SECCIONES'!$B$4:$S$9,7,FALSE())) -> 66.51 | Q30: =IF($C30="","",VLOOKUP($E30,'📊 SECCIONES'!$B$4:$S$9,8,FALSE())) -> 17450 | R30: =IF($C30="","",VLOOKUP($E30,'📊 SECCIONES'!$B$4:$S$9,10,FALSE())) -> 10.6 | S30: =IF('📇 INVENTARIO'!K31="","",'📇 INVENTARIO'!K31) -> 3 | T30: =IF($C30="","","Objetivo: alcanzar calificación C. Actual: Cal."&F30&". "&IF(OR(F30="G",F30="F"),"SATE integral + cubierta + carpinterías triple + aerotermia + instalación fotovoltaica",IF(F30="E","SATE fachada + carpinterías doble + instalación fotovoltaica",IF(F30="D","Mantenimiento de envolvente + instalación fotovoltaica en cubierta","Optimización energética + instalación fotovoltaica")))) -> Objetivo: alcanzar calificación C. Actual: Cal.G. SATE integral + cubierta + carpinterías triple + aerotermia + instalación fotovoltaica | U30: =IF($C30="","",IF(S30=0,"s/d",IF(S30>=4,"Valorar ascensor (verificar)","—"))) -> — | V30: =IF('📇 INVENTARIO'!L31="","",'📇 INVENTARIO'!L31) -> 96.7 | W30: =IF($C30="","",V30*'⚙️ SUPUESTOS'!$C$8*'⚙️ SUPUESTOS'!$C$9) -> 20.307 | X30: =IF('📇 INVENTARIO'!N31="","",'📇 INVENTARIO'!N31) -> 1532 | Y30: =IF($C30="","",W30*X30*'⚙️ SUPUESTOS'!$C$7) -> 27999.292 | Z30: =IF($C30="","",W30*'⚙️ SUPUESTOS'!$C$10) -> 27109.845 | AA30: =IF($C30="","",Y30*('⚙️ SUPUESTOS'!$C$12*'⚙️ SUPUESTOS'!$C$11+(1-'⚙️ SUPUESTOS'!$C$12)*'⚙️ SUPUESTOS'!$C$13)) -> 1909.5517 | AB30: =IF($C30="","",IF(Y30>0,ROUND(Y30*'⚙️ SUPUESTOS'!$C$12*'⚙️ SUPUESTOS'!$C$11,0),"")) -> 700 | AC30: =IF($C30="","",IF(Y30>0,ROUND(Y30*(1-'⚙️ SUPUESTOS'!$C$12)*'⚙️ SUPUESTOS'!$C$13,0),"")) -> 1210 | AD30: =IF($C30="","",IF(AND(ISNUMBER(AA30),ISNUMBER(AE30),AA30>0,AE30>0),ROUND(AA30*MAX(0,25-AE30),0),"")) -> 20629 | AE30: =IF($C30="","",IF(AA30>0,Z30/AA30,"")) -> 14.196968 | AF30: =IF($C30="","",IF(AE30="","—",IF(AE30<='⚙️ SUPUESTOS'!$C$32,"✔ Muy recomendable",IF(AE30<='⚙️ SUPUESTOS'!$C$33,"✔ Recomendable","Valorar")))) -> ✔ Muy recomendable | AG30: =IF('📇 INVENTARIO'!O31="","",'📇 INVENTARIO'!O31) -> 41.6482 | AH30: =IF('📇 INVENTARIO'!P31="","",'📇 INVENTARIO'!P31) -> -4.709
A31: =IF($C31="","",RANK(O31,$O$3:$O$265,0)+COUNTIF($O$3:O31,O31)-1) -> 29 | B31: =IF($C31="","",IF(A31<='⚙️ SUPUESTOS'!$C$29,"Fase 1",IF(A31<='⚙️ SUPUESTOS'!$C$30,"Fase 2","Fase 3"))) -> Fase 1 | C31: =IF('📇 INVENTARIO'!B32="","",'📇 INVENTARIO'!B32) -> C/ Faisán, 7 | D31: =IF('📇 INVENTARIO'!C32="","",'📇 INVENTARIO'!C32) -> 7724220UM5172D | E31: =IF('📇 INVENTARIO'!D32="","",'📇 INVENTARIO'!D32) -> 4718606026 | F31: =IF('📇 INVENTARIO'!F32="","",'📇 INVENTARIO'!F32) -> G | G31: =IF('📇 INVENTARIO'!G32="","",'📇 INVENTARIO'!G32) -> 338 | H31: =IF('📇 INVENTARIO'!H32="","",'📇 INVENTARIO'!H32) -> 71.5 | I31: =IF('📇 INVENTARIO'!I32="","",'📇 INVENTARIO'!I32) -> 176 | J31: =IF('📇 INVENTARIO'!J32="","",'📇 INVENTARIO'!J32) -> 1965 | K31: =IF($C31="","",(G31-'⚙️ SUPUESTOS'!$C$20)/('⚙️ SUPUESTOS'!$C$25-'⚙️ SUPUESTOS'!$C$20)) -> 0.33562823 | L31: =IF($C31="","",VLOOKUP($E31,'📊 SECCIONES'!$B$4:$S$9,16,FALSE())) -> 1 | M31: =IF($C31="","",VLOOKUP($E31,'📊 SECCIONES'!$B$4:$S$9,17,FALSE())) -> 1 | N31: =IF($C31="","",VLOOKUP($E31,'📊 SECCIONES'!$B$4:$S$9,18,FALSE())) -> 0 | O31: =IF($C31="","",ROUND('⚙️ SUPUESTOS'!$C$21*K31+'⚙️ SUPUESTOS'!$C$22*L31+'⚙️ SUPUESTOS'!$C$23*M31+'⚙️ SUPUESTOS'!$C$24*N31,4)) -> 0.5446 | P31: =IF($C31="","",VLOOKUP($E31,'📊 SECCIONES'!$B$4:$S$9,7,FALSE())) -> 66.51 | Q31: =IF($C31="","",VLOOKUP($E31,'📊 SECCIONES'!$B$4:$S$9,8,FALSE())) -> 17450 | R31: =IF($C31="","",VLOOKUP($E31,'📊 SECCIONES'!$B$4:$S$9,10,FALSE())) -> 10.6 | S31: =IF('📇 INVENTARIO'!K32="","",'📇 INVENTARIO'!K32) -> 3 | T31: =IF($C31="","","Objetivo: alcanzar calificación C. Actual: Cal."&F31&". "&IF(OR(F31="G",F31="F"),"SATE integral + cubierta + carpinterías triple + aerotermia + instalación fotovoltaica",IF(F31="E","SATE fachada + carpinterías doble + instalación fotovoltaica",IF(F31="D","Mantenimiento de envolvente + instalación fotovoltaica en cubierta","Optimización energética + instalación fotovoltaica")))) -> Objetivo: alcanzar calificación C. Actual: Cal.G. SATE integral + cubierta + carpinterías triple + aerotermia + instalación fotovoltaica | U31: =IF($C31="","",IF(S31=0,"s/d",IF(S31>=4,"Valorar ascensor (verificar)","—"))) -> — | V31: =IF('📇 INVENTARIO'!L32="","",'📇 INVENTARIO'!L32) -> 97.6 | W31: =IF($C31="","",V31*'⚙️ SUPUESTOS'!$C$8*'⚙️ SUPUESTOS'!$C$9) -> 20.496 | X31: =IF('📇 INVENTARIO'!N32="","",'📇 INVENTARIO'!N32) -> 1532 | Y31: =IF($C31="","",W31*X31*'⚙️ SUPUESTOS'!$C$7) -> 28259.885 | Z31: =IF($C31="","",W31*'⚙️ SUPUESTOS'!$C$10) -> 27362.16 | AA31: =IF($C31="","",Y31*('⚙️ SUPUESTOS'!$C$12*'⚙️ SUPUESTOS'!$C$11+(1-'⚙️ SUPUESTOS'!$C$12)*'⚙️ SUPUESTOS'!$C$13)) -> 1927.3241 | AB31: =IF($C31="","",IF(Y31>0,ROUND(Y31*'⚙️ SUPUESTOS'!$C$12*'⚙️ SUPUESTOS'!$C$11,0),"")) -> 706 | AC31: =IF($C31="","",IF(Y31>0,ROUND(Y31*(1-'⚙️ SUPUESTOS'!$C$12)*'⚙️ SUPUESTOS'!$C$13,0),"")) -> 1221 | AD31: =IF($C31="","",IF(AND(ISNUMBER(AA31),ISNUMBER(AE31),AA31>0,AE31>0),ROUND(AA31*MAX(0,25-AE31),0),"")) -> 20821 | AE31: =IF($C31="","",IF(AA31>0,Z31/AA31,"")) -> 14.196968 | AF31: =IF($C31="","",IF(AE31="","—",IF(AE31<='⚙️ SUPUESTOS'!$C$32,"✔ Muy recomendable",IF(AE31<='⚙️ SUPUESTOS'!$C$33,"✔ Recomendable","Valorar")))) -> ✔ Muy recomendable | AG31: =IF('📇 INVENTARIO'!O32="","",'📇 INVENTARIO'!O32) -> 41.64852 | AH31: =IF('📇 INVENTARIO'!P32="","",'📇 INVENTARIO'!P32) -> -4.71003
... A35: =IF($C35="","",RANK(O35,$O$3:$O$265,0)+COUNTIF($O$3:O35,O35)-1) -> 33 | B35: =IF($C35="","",IF(A35<='⚙️ SUPUESTOS'!$C$29,"Fase 1",IF(A35<='⚙️ SUPUESTOS'!$C$30,"Fase 2","Fase 3"))) -> Fase 1 | C35: =IF('📇 INVENTARIO'!B36="","",'📇 INVENTARIO'!B36) -> C/ Faisán, 5 | D35: =IF('📇 INVENTARIO'!C36="","",'📇 INVENTARIO'!C36) -> 7724223UM5172D | E35: =IF('📇 INVENTARIO'!D36="","",'📇 INVENTARIO'!D36) -> 4718606026 | F35: =IF('📇 INVENTARIO'!F36="","",'📇 INVENTARIO'!F36) -> E | G35: =IF('📇 INVENTARIO'!G36="","",'📇 INVENTARIO'!G36) -> 328 | H35: =IF('📇 INVENTARIO'!H36="","",'📇 INVENTARIO'!H36) -> 66.5 | I35: =IF('📇 INVENTARIO'!I36="","",'📇 INVENTARIO'!I36) -> 186.2 | J35: =IF('📇 INVENTARIO'!J36="","",'📇 INVENTARIO'!J36) -> 1965 | K35: =IF($C35="","",(G35-'⚙️ SUPUESTOS'!$C$20)/('⚙️ SUPUESTOS'!$C$25-'⚙️ SUPUESTOS'!$C$20)) -> 0.31841652 | L35: =IF($C35="","",VLOOKUP($E35,'📊 SECCIONES'!$B$4:$S$9,16,FALSE())) -> 1 | M35: =IF($C35="","",VLOOKUP($E35,'📊 SECCIONES'!$B$4:$S$9,17,FALSE())) -> 1 | N35: =IF($C35="","",VLOOKUP($E35,'📊 SECCIONES'!$B$4:$S$9,18,FALSE())) -> 0 | O35: =IF($C35="","",ROUND('⚙️ SUPUESTOS'!$C$21*K35+'⚙️ SUPUESTOS'!$C$22*L35+'⚙️ SUPUESTOS'!$C$23*M35+'⚙️ SUPUESTOS'!$C$24*N35,4)) -> 0.5351 | P35: =IF($C35="","",VLOOKUP($E35,'📊 SECCIONES'!$B$4:$S$9,7,FALSE())) -> 66.51 | Q35: =IF($C35="","",VLOOKUP($E35,'📊 SECCIONES'!$B$4:$S$9,8,FALSE())) -> 17450 | R35: =IF($C35="","",VLOOKUP($E35,'📊 SECCIONES'!$B$4:$S$9,10,FALSE())) -> 10.6 | S35: =IF('📇 INVENTARIO'!K36="","",'📇 INVENTARIO'!K36) -> 3 | T35: =IF($C35="","","Objetivo: alcanzar calificación C. Actual: Cal."&F35&". "&IF(OR(F35="G",F35="F"),"SATE integral + cubierta + carpinterías triple + aerotermia + instalación fotovoltaica",IF(F35="E","SATE fachada + carpinterías doble + instalación fotovoltaica",IF(F35="D","Mantenimiento de envolvente + instalación fotovoltaica en cubierta","Optimización energética + instalación fotovoltaica")))) -> Objetivo: alcanzar calificación C. Actual: Cal.E. SATE fachada + carpinterías doble + instalación fotovoltaica | U35: =IF($C35="","",IF(S35=0,"s/d",IF(S35>=4,"Valorar ascensor (verificar)","—"))) -> — | V35: =IF('📇 INVENTARIO'!L36="","",'📇 INVENTARIO'!L36) -> 97.8 | W35: =IF($C35="","",V35*'⚙️ SUPUESTOS'!$C$8*'⚙️ SUPUESTOS'!$C$9) -> 20.538 | X35: =IF('📇 INVENTARIO'!N36="","",'📇 INVENTARIO'!N36) -> 1446 | Y35: =IF($C35="","",W35*X35*'⚙️ SUPUESTOS'!$C$7) -> 26728.153 | Z35: =IF($C35="","",W35*'⚙️ SUPUESTOS'!$C$10) -> 27418.23 | AA35: =IF($C35="","",Y35*('⚙️ SUPUESTOS'!$C$12*'⚙️ SUPUESTOS'!$C$11+(1-'⚙️ SUPUESTOS'!$C$12)*'⚙️ SUPUESTOS'!$C$13)) -> 1822.86 | AB35: =IF($C35="","",IF(Y35>0,ROUND(Y35*'⚙️ SUPUESTOS'!$C$12*'⚙️ SUPUESTOS'!$C$11,0),"")) -> 668 | AC35: =IF($C35="","",IF(Y35>0,ROUND(Y35*(1-'⚙️ SUPUESTOS'!$C$12)*'⚙️ SUPUESTOS'!$C$13,0),"")) -> 1155 | AD35: =IF($C35="","",IF(AND(ISNUMBER(AA35),ISNUMBER(AE35),AA35>0,AE35>0),ROUND(AA35*MAX(0,25-AE35),0),"")) -> 18153 | AE35: =IF($C35="","",IF(AA35>0,Z35/AA35,"")) -> 15.041325 | AF35: =IF($C35="","",IF(AE35="","—",IF(AE35<='⚙️ SUPUESTOS'!$C$32,"✔ Muy recomendable",IF(AE35<='⚙️ SUPUESTOS'!$C$33,"✔ Recomendable","Valorar")))) -> ✔ Recomendable | AG35: =IF('📇 INVENTARIO'!O36="","",'📇 INVENTARIO'!O36) -> 41.64869 | AH35: =IF('📇 INVENTARIO'!P36="","",'📇 INVENTARIO'!P36) -> -4.71042
A36: =IF($C36="","",RANK(O36,$O$3:$O$265,0)+COUNTIF($O$3:O36,O36)-1) -> 34 | B36: =IF($C36="","",IF(A36<='⚙️ SUPUESTOS'!$C$29,"Fase 1",IF(A36<='⚙️ SUPUESTOS'!$C$30,"Fase 2","Fase 3"))) -> Fase 1 | C36: =IF('📇 INVENTARIO'!B41="","",'📇 INVENTARIO'!B41) -> C/ Martín Pescador, 4 | D36: =IF('📇 INVENTARIO'!C41="","",'📇 INVENTARIO'!C41) -> 7623001UM5172D | E36: =IF('📇 INVENTARIO'!D41="","",'📇 INVENTARIO'!D41) -> 4718606027 | F36: =IF('📇 INVENTARIO'!F41="","",'📇 INVENTARIO'!F41) -> G | G36: =IF('📇 INVENTARIO'!G41="","",'📇 INVENTARIO'!G41) -> 525 | H36: =IF('📇 INVENTARIO'!H41="","",'📇 INVENTARIO'!H41) -> 89 | I36: =IF('📇 INVENTARIO'!I41="","",'📇 INVENTARIO'!I41) -> 210.2 | J36: =IF('📇 INVENTARIO'!J41="","",'📇 INVENTARIO'!J41) -> 1969 | K36: =IF($C36="","",(G36-'⚙️ SUPUESTOS'!$C$20)/('⚙️ SUPUESTOS'!$C$25-'⚙️ SUPUESTOS'!$C$20)) -> 0.65748709 | L36: =IF($C36="","",VLOOKUP($E36,'📊 SECCIONES'!$B$4:$S$9,16,FALSE())) -> 0.1948196 | M36: =IF($C36="","",VLOOKUP($E36,'📊 SECCIONES'!$B$4:$S$9,17,FALSE())) -> 0.26632124 | N36: =IF($C36="","",VLOOKUP($E36,'📊 SECCIONES'!$B$4:$S$9,18,FALSE())) -> 1 | O36: =IF($C36="","",ROUND('⚙️ SUPUESTOS'!$C$21*K36+'⚙️ SUPUESTOS'!$C$22*L36+'⚙️ SUPUESTOS'!$C$23*M36+'⚙️ SUPUESTOS'!$C$24*N36,4)) -> 0.5318 | P36: =IF($C36="","",VLOOKUP($E36,'📊 SECCIONES'!$B$4:$S$9,7,FALSE())) -> 24.5 | Q36: =IF($C36="","",VLOOKUP($E36,'📊 SECCIONES'!$B$4:$S$9,8,FALSE())) -> 25206 | R36: =IF($C36="","",VLOOKUP($E36,'📊 SECCIONES'!$B$4:$S$9,10,FALSE())) -> 32.6 | S36: =IF('📇 INVENTARIO'!K41="","",'📇 INVENTARIO'!K41) -> 6 | T36: =IF($C36="","","Objetivo: alcanzar calificación C. Actual: Cal."&F36&". "&IF(OR(F36="G",F36="F"),"SATE integral + cubierta + carpinterías triple + aerotermia + instalación fotovoltaica",IF(F36="E","SATE fachada + carpinterías doble + instalación fotovoltaica",IF(F36="D","Mantenimiento de envolvente + instalación fotovoltaica en cubierta","Optimización energética + instalación fotovoltaica")))) -> Objetivo: alcanzar calificación C. Actual: Cal.G. SATE integral + cubierta + carpinterías triple + aerotermia + instalación fotovoltaica | U36: =IF($C36="","",IF(S36=0,"s/d",IF(S36>=4,"Valorar ascensor (verificar)","—"))) -> Valorar ascensor (verificar) | V36: =IF('📇 INVENTARIO'!L41="","",'📇 INVENTARIO'!L41) -> 193.8 | W36: =IF($C36="","",V36*'⚙️ SUPUESTOS'!$C$8*'⚙️ SUPUESTOS'!$C$9) -> 40.698 | X36: =IF('📇 INVENTARIO'!N41="","",'📇 INVENTARIO'!N41) -> 1454 | Y36: =IF($C36="","",W36*X36*'⚙️ SUPUESTOS'!$C$7) -> 53257.403 | Z36: =IF($C36="","",W36*'⚙️ SUPUESTOS'!$C$10) -> 54331.83 | AA36: =IF($C36="","",Y36*('⚙️ SUPUESTOS'!$C$12*'⚙️ SUPUESTOS'!$C$11+(1-'⚙️ SUPUESTOS'!$C$12)*'⚙️ SUPUESTOS'!$C$13)) -> 3632.1549 | AB36: =IF($C36="","",IF(Y36>0,ROUND(Y36*'⚙️ SUPUESTOS'!$C$12*'⚙️ SUPUESTOS'!$C$11,0),"")) -> 1331 | AC36: =IF($C36="","",IF(Y36>0,ROUND(Y36*(1-'⚙️ SUPUESTOS'!$C$12)*'⚙️ SUPUESTOS'!$C$13,0),"")) -> 2301 | AD36: =IF($C36="","",IF(AND(ISNUMBER(AA36),ISNUMBER(AE36),AA36>0,AE36>0),ROUND(AA36*MAX(0,25-AE36),0),"")) -> 36472 | AE36: =IF($C36="","",IF(AA36>0,Z36/AA36,"")) -> 14.958566 | AF36: =IF($C36="","",IF(AE36="","—",IF(AE36<='⚙️ SUPUESTOS'!$C$32,"✔ Muy recomendable",IF(AE36<='⚙️ SUPUESTOS'!$C$33,"✔ Recomendable","Valorar")))) -> ✔ Muy recomendable | AG36: =IF('📇 INVENTARIO'!O37="","",'📇 INVENTARIO'!O37) -> 41.6485 | AH36: =IF('📇 INVENTARIO'!P37="","",'📇 INVENTARIO'!P37) -> -4.70937
A37: =IF($C37="","",RANK(O37,$O$3:$O$265,0)+COUNTIF($O$3:O37,O37)-1) -> 35 | B37: =IF($C37="","",IF(A37<='⚙️ SUPUESTOS'!$C$29,"Fase 1",IF(A37<='⚙️ SUPUESTOS'!$C$30,"Fase 2","Fase 3"))) -> Fase 1 | C37: =IF('📇 INVENTARIO'!B37="","",'📇 INVENTARIO'!B37) -> C/ Águila, 14 | D37: =IF('📇 INVENTARIO'!C37="","",'📇 INVENTARIO'!C37) -> 7824516UM5172D | E37: =IF('📇 INVENTARIO'!D37="","",'📇 INVENTARIO'!D37) -> 4718606026 | F37: =IF('📇 INVENTARIO'!F37="","",'📇 INVENTARIO'!F37) -> F | G37: =IF('📇 INVENTARIO'!G37="","",'📇 INVENTARIO'!G37) -> 324 | H37: =IF('📇 INVENTARIO'!H37="","",'📇 INVENTARIO'!H37) -> 59 | I37: =IF('📇 INVENTARIO'!I37="","",'📇 INVENTARIO'!I37) -> 140.5 | J37: =IF('📇 INVENTARIO'!J37="","",'📇 INVENTARIO'!J37) -> 1965 | K37: =IF($C37="","",(G37-'⚙️ SUPUESTOS'!$C$20)/('⚙️ SUPUESTOS'!$C$25-'⚙️ SUPUESTOS'!$C$20)) -> 0.31153184 | L37: =IF($C37="","",VLOOKUP($E37,'📊 SECCIONES'!$B$4:$S$9,16,FALSE())) -> 1 | M37: =IF($C37="","",VLOOKUP($E37,'📊 SECCIONES'!$B$4:$S$9,17,FALSE())) -> 1 | N37: =IF($C37="","",VLOOKUP($E37,'📊 SECCIONES'!$B$4:$S$9,18,FALSE())) -> 0 | O37: =IF($C37="","",ROUND('⚙️ SUPUESTOS'!$C$21*K37+'⚙️ SUPUESTOS'!$C$22*L37+'⚙️ SUPUESTOS'!$C$23*M37+'⚙️ SUPUESTOS'!$C$24*N37,4)) -> 0.5313 | P37: =IF($C37="","",VLOOKUP($E37,'📊 SECCIONES'!$B$4:$S$9,7,FALSE())) -> 66.51 | Q37: =IF($C37="","",VLOOKUP($E37,'📊 SECCIONES'!$B$4:$S$9,8,FALSE())) -> 17450 | R37: =IF($C37="","",VLOOKUP($E37,'📊 SECCIONES'!$B$4:$S$9,10,FALSE())) -> 10.6 | S37: =IF('📇 INVENTARIO'!K37="","",'📇 INVENTARIO'!K37) -> 3 | T37: =IF($C37="","","Objetivo: alcanzar calificación C. Actual: Cal."&F37&". "&IF(OR(F37="G",F37="F"),"SATE integral + cubierta + carpinterías triple + aerotermia + instalación fotovoltaica",IF(F37="E","SATE fachada + carpinterías doble + instalación fotovoltaica",IF(F37="D","Mantenimiento de envolvente + instalación fotovoltaica en cubierta","Optimización energética + instalación fotovoltaica")))) -> Objetivo: alcanzar calificación C. Actual: Cal.F. SATE integral + cubierta + carpinterías triple + aerotermia + instalación fotovoltaica | U37: =IF($C37="","",IF(S37=0,"s/d",IF(S37>=4,"Valorar ascensor (verificar)","—"))) -> — | V37: =IF('📇 INVENTARIO'!L37="","",'📇 INVENTARIO'!L37) -> 110.4 | W37: =IF($C37="","",V37*'⚙️ SUPUESTOS'!$C$8*'⚙️ SUPUESTOS'!$C$9) -> 23.184 | X37: =IF('📇 INVENTARIO'!N37="","",'📇 INVENTARIO'!N37) -> 1530 | Y37: =IF($C37="","",W37*X37*'⚙️ SUPUESTOS'!$C$7) -> 31924.368 | Z37: =IF($C37="","",W37*'⚙️ SUPUESTOS'!$C$10) -> 30950.64 | AA37: =IF($C37="","",Y37*('⚙️ SUPUESTOS'!$C$12*'⚙️ SUPUESTOS'!$C$11+(1-'⚙️ SUPUESTOS'!$C$12)*'⚙️ SUPUESTOS'!$C$13)) -> 2177.2419 | AB37: =IF($C37="","",IF(Y37>0,ROUND(Y37*'⚙️ SUPUESTOS'!$C$12*'⚙️ SUPUESTOS'!$C$11,0),"")) -> 798 | AC37: =IF($C37="","",IF(Y37>0,ROUND(Y37*(1-'⚙️ SUPUESTOS'!$C$12)*'⚙️ SUPUESTOS'!$C$13,0),"")) -> 1379 | AD37: =IF($C37="","",IF(AND(ISNUMBER(AA37),ISNUMBER(AE37),AA37>0,AE37>0),ROUND(AA37*MAX(0,25-AE37),0),"")) -> 23480 | AE37: =IF($C37="","",IF(AA37>0,Z37/AA37,"")) -> 14.215527 | AF37: =IF($C37="","",IF(AE37="","—",IF(AE37<='⚙️ SUPUESTOS'!$C$32,"✔ Muy recomendable",IF(AE37<='⚙️ SUPUESTOS'!$C$33,"✔ Recomendable","Valorar")))) -> ✔ Muy recomendable | AG37: =IF('📇 INVENTARIO'!O38="","",'📇 INVENTARIO'!O38) -> 41.64922 | AH37: =IF('📇 INVENTARIO'!P38="","",'📇 INVENTARIO'!P38) -> -4.71128
A38: =IF($C38="","",RANK(O38,$O$3:$O$265,0)+COUNTIF($O$3:O38,O38)-1) -> 36 | B38: =IF($C38="","",IF(A38<='⚙️ SUPUESTOS'!$C$29,"Fase 1",IF(A38<='⚙️ SUPUESTOS'!$C$30,"Fase 2","Fase 3"))) -> Fase 1 | C38: =IF('📇 INVENTARIO'!B38="","",'📇 INVENTARIO'!B38) -> C/ Salud, 15 | D38: =IF('📇 INVENTARIO'!C38="","",'📇 INVENTARIO'!C38) -> 7625401UM5172F | E38: =IF('📇 INVENTARIO'!D38="","",'📇 INVENTARIO'!D38) -> 4718606026 | F38: =IF('📇 INVENTARIO'!F38="","",'📇 INVENTARIO'!F38) -> F | G38: =IF('📇 INVENTARIO'!G38="","",'📇 INVENTARIO'!G38) -> 322 | H38: =IF('📇 INVENTARIO'!H38="","",'📇 INVENTARIO'!H38) -> 65 | I38: =IF('📇 INVENTARIO'!I38="","",'📇 INVENTARIO'!I38) -> 183.9 | J38: =IF('📇 INVENTARIO'!J38="","",'📇 INVENTARIO'!J38) -> 1958 | K38: =IF($C38="","",(G38-'⚙️ SUPUESTOS'!$C$20)/('⚙️ SUPUESTOS'!$C$25-'⚙️ SUPUESTOS'!$C$20)) -> 0.3080895 | L38: =IF($C38="","",VLOOKUP($E38,'📊 SECCIONES'!$B$4:$S$9,16,FALSE())) -> 1 | M38: =IF($C38="","",VLOOKUP($E38,'📊 SECCIONES'!$B$4:$S$9,17,FALSE())) -> 1 | N38: =IF($C38="","",VLOOKUP($E38,'📊 SECCIONES'!$B$4:$S$9,18,FALSE())) -> 0 | O38: =IF($C38="","",ROUND('⚙️ SUPUESTOS'!$C$21*K38+'⚙️ SUPUESTOS'!$C$22*L38+'⚙️ SUPUESTOS'!$C$23*M38+'⚙️ SUPUESTOS'!$C$24*N38,4)) -> 0.5294 | P38: =IF($C38="","",VLOOKUP($E38,'📊 SECCIONES'!$B$4:$S$9,7,FALSE())) -> 66.51 | Q38: =IF($C38="","",VLOOKUP($E38,'📊 SECCIONES'!$B$4:$S$9,8,FALSE())) -> 17450 | R38: =IF($C38="","",VLOOKUP($E38,'📊 SECCIONES'!$B$4:$S$9,10,FALSE())) -> 10.6 | S38: =IF('📇 INVENTARIO'!K38="","",'📇 INVENTARIO'!K38) -> 5 | T38: =IF($C38="","","Objetivo: alcanzar calificación C. Actual: Cal."&F38&". "&IF(OR(F38="G",F38="F"),"SATE integral + cubierta + carpinterías triple + aerotermia + instalación fotovoltaica",IF(F38="E","SATE fachada + carpinterías doble + instalación fotovoltaica",IF(F38="D","Mantenimiento de envolvente + instalación fotovoltaica en cubierta","Optimización energética + instalación fotovoltaica")))) -> Objetivo: alcanzar calificación C. Actual: Cal.F. SATE integral + cubierta + carpinterías triple + aerotermia + instalación fotovoltaica | U38: =IF($C38="","",IF(S38=0,"s/d",IF(S38>=4,"Valorar ascensor (verificar)","—"))) -> Valorar ascensor (verificar) | V38: =IF('📇 INVENTARIO'!L38="","",'📇 INVENTARIO'!L38) -> 330.5 | W38: =IF($C38="","",V38*'⚙️ SUPUESTOS'!$C$8*'⚙️ SUPUESTOS'!$C$9) -> 69.405 | X38: =IF('📇 INVENTARIO'!N38="","",'📇 INVENTARIO'!N38) -> 1373 | Y38: =IF($C38="","",W38*X38*'⚙️ SUPUESTOS'!$C$7) -> 85763.759 | Z38: =IF($C38="","",W38*'⚙️ SUPUESTOS'!$C$10) -> 92655.675 | AA38: =IF($C38="","",Y38*('⚙️ SUPUESTOS'!$C$12*'⚙️ SUPUESTOS'!$C$11+(1-'⚙️ SUPUESTOS'!$C$12)*'⚙️ SUPUESTOS'!$C$13)) -> 5849.0883 | AB38: =IF($C38="","",IF(Y38>0,ROUND(Y38*'⚙️ SUPUESTOS'!$C$12*'⚙️ SUPUESTOS'!$C$11,0),"")) -> 2144 | AC38: =IF($C38="","",IF(Y38>0,ROUND(Y38*(1-'⚙️ SUPUESTOS'!$C$12)*'⚙️ SUPUESTOS'!$C$13,0),"")) -> 3705 | AD38: =IF($C38="","",IF(AND(ISNUMBER(AA38),ISNUMBER(AE38),AA38>0,AE38>0),ROUND(AA38*MAX(0,25-AE38),0),"")) -> 53572 | AE38: =IF($C38="","",IF(AA38>0,Z38/AA38,"")) -> 15.841046 | AF38: =IF($C38="","",IF(AE38="","—",IF(AE38<='⚙️ SUPUESTOS'!$C$32,"✔ Muy recomendable",IF(AE38<='⚙️ SUPUESTOS'!$C$33,"✔ Recomendable","Valorar")))) -> ✔ Recomendable | AG38: =IF('📇 INVENTARIO'!O39="","",'📇 INVENTARIO'!O39) -> 41.64892 | AH38: =IF('📇 INVENTARIO'!P39="","",'📇 INVENTARIO'!P39) -> -4.70922
A39: =IF($C39="","",RANK(O39,$O$3:$O$265,0)+COUNTIF($O$3:O39,O39)-1) -> 37 | B39: =IF($C39="","",IF(A39<='⚙️ SUPUESTOS'!$C$29,"Fase 1",IF(A39<='⚙️ SUPUESTOS'!$C$30,"Fase 2","Fase 3"))) -> Fase 1 | C39: =IF('📇 INVENTARIO'!B39="","",'📇 INVENTARIO'!B39) -> C/ Águila, 23 | D39: =IF('📇 INVENTARIO'!C39="","",'📇 INVENTARIO'!C39) -> 7724210UM5172D | E39: =IF('📇 INVENTARIO'!D39="","",'📇 INVENTARIO'!D39) -> 4718606026 | F39: =IF('📇 INVENTARIO'!F39="","",'📇 INVENTARIO'!F39) -> G | G39: =IF('📇 INVENTARIO'!G39="","",'📇 INVENTARIO'!G39) -> 318 | H39: =IF('📇 INVENTARIO'!H39="","",'📇 INVENTARIO'!H39) -> 59.5 | I39: =IF('📇 INVENTARIO'!I39="","",'📇 INVENTARIO'!I39) -> 117.8 | J39: =IF('📇 INVENTARIO'!J39="","",'📇 INVENTARIO'!J39) -> 1965 | K39: =IF($C39="","",(G39-'⚙️ SUPUESTOS'!$C$20)/('⚙️ SUPUESTOS'!$C$25-'⚙️ SUPUESTOS'!$C$20)) -> 0.30120482 | L39: =IF($C39="","",VLOOKUP($E39,'📊 SECCIONES'!$B$4:$S$9,16,FALSE())) -> 1 | M39: =IF($C39="","",VLOOKUP($E39,'📊 SECCIONES'!$B$4:$S$9,17,FALSE())) -> 1 | N39: =IF($C39="","",VLOOKUP($E39,'📊 SECCIONES'!$B$4:$S$9,18,FALSE())) -> 0 | O39: =IF($C39="","",ROUND('⚙️ SUPUESTOS'!$C$21*K39+'⚙️ SUPUESTOS'!$C$22*L39+'⚙️ SUPUESTOS'!$C$23*M39+'⚙️ SUPUESTOS'!$C$24*N39,4)) -> 0.5257 | P39: =IF($C39="","",VLOOKUP($E39,'📊 SECCIONES'!$B$4:$S$9,7,FALSE())) -> 66.51 | Q39: =IF($C39="","",VLOOKUP($E39,'📊 SECCIONES'!$B$4:$S$9,8,FALSE())) -> 17450 | R39: =IF($C39="","",VLOOKUP($E39,'📊 SECCIONES'!$B$4:$S$9,10,FALSE())) -> 10.6 | S39: =IF('📇 INVENTARIO'!K39="","",'📇 INVENTARIO'!K39) -> 3 | T39: =IF($C39="","","Objetivo: alcanzar calificación C. Actual: Cal."&F39&". "&IF(OR(F39="G",F39="F"),"SATE integral + cubierta + carpinterías triple + aerotermia + instalación fotovoltaica",IF(F39="E","SATE fachada + carpinterías doble + instalación fotovoltaica",IF(F39="D","Mantenimiento de envolvente + instalación fotovoltaica en cubierta","Optimización energética + instalación fotovoltaica")))) -> Objetivo: alcanzar calificación C. Actual: Cal.G. SATE integral + cubierta + carpinterías triple + aerotermia + instalación fotovoltaica | U39: =IF($C39="","",IF(S39=0,"s/d",IF(S39>=4,"Valorar ascensor (verificar)","—"))) -> — | V39: =IF('📇 INVENTARIO'!L39="","",'📇 INVENTARIO'!L39) -> 97.1 | W39: =IF($C39="","",V39*'⚙️ SUPUESTOS'!$C$8*'⚙️ SUPUESTOS'!$C$9) -> 20.391 | X39: =IF('📇 INVENTARIO'!N39="","",'📇 INVENTARIO'!N39) -> 1556 | Y39: =IF($C39="","",W39*X39*'⚙️ SUPUESTOS'!$C$7) -> 28555.556 | Z39: =IF($C39="","",W39*'⚙️ SUPUESTOS'!$C$10) -> 27221.985 | AA39: =IF($C39="","",Y39*('⚙️ SUPUESTOS'!$C$12*'⚙️ SUPUESTOS'!$C$11+(1-'⚙️ SUPUESTOS'!$C$12)*'⚙️ SUPUESTOS'!$C$13)) -> 1947.4889 | AB39: =IF($C39="","",IF(Y39>0,ROUND(Y39*'⚙️ SUPUESTOS'!$C$12*'⚙️ SUPUESTOS'!$C$11,0),"")) -> 714 | AC39: =IF($C39="","",IF(Y39>0,ROUND(Y39*(1-'⚙️ SUPUESTOS'!$C$12)*'⚙️ SUPUESTOS'!$C$13,0),"")) -> 1234 | AD39: =IF($C39="","",IF(AND(ISNUMBER(AA39),ISNUMBER(AE39),AA39>0,AE39>0),ROUND(AA39*MAX(0,25-AE39),0),"")) -> 21465 | AE39: =IF($C39="","",IF(AA39>0,Z39/AA39,"")) -> 13.977992 | AF39: =IF($C39="","",IF(AE39="","—",IF(AE39<='⚙️ SUPUESTOS'!$C$32,"✔ Muy recomendable",IF(AE39<='⚙️ SUPUESTOS'!$C$33,"✔ Recomendable","Valorar")))) -> ✔ Muy recomendable | AG39: =IF('📇 INVENTARIO'!O40="","",'📇 INVENTARIO'!O40) -> 41.64876 | AH39: =IF('📇 INVENTARIO'!P40="","",'📇 INVENTARIO'!P40) -> -4.71056
A40: =IF($C40="","",RANK(O40,$O$3:$O$265,0)+COUNTIF($O$3:O40,O40)-1) -> 38 | B40: =IF($C40="","",IF(A40<='⚙️ SUPUESTOS'!$C$29,"Fase 1",IF(A40<='⚙️ SUPUESTOS'!$C$30,"Fase 2","Fase 3"))) -> Fase 1 | C40: =IF('📇 INVENTARIO'!B40="","",'📇 INVENTARIO'!B40) -> C/ Faisán, 3 | D40: =IF('📇 INVENTARIO'!C40="","",'📇 INVENTARIO'!C40) -> 7724224UM5172D | E40: =IF('📇 INVENTARIO'!D40="","",'📇 INVENTARIO'!D40) -> 4718606026 | F40: =IF('📇 INVENTARIO'!F40="","",'📇 INVENTARIO'!F40) -> E | G40: =IF('📇 INVENTARIO'!G40="","",'📇 INVENTARIO'!G40) -> 315 | H40: =IF('📇 INVENTARIO'!H40="","",'📇 INVENTARIO'!H40) -> 66.5 | I40: =IF('📇 INVENTARIO'!I40="","",'📇 INVENTARIO'!I40) -> 134.7 | J40: =IF('📇 INVENTARIO'!J40="","",'📇 INVENTARIO'!J40) -> 1965 | K40: =IF($C40="","",(G40-'⚙️ SUPUESTOS'!$C$20)/('⚙️ SUPUESTOS'!$C$25-'⚙️ SUPUESTOS'!$C$20)) -> 0.29604131 | L40: =IF($C40="","",VLOOKUP($E40,'📊 SECCIONES'!$B$4:$S$9,16,FALSE())) -> 1 | M40: =IF($C40="","",VLOOKUP($E40,'📊 SECCIONES'!$B$4:$S$9,17,FALSE())) -> 1 | N40: =IF($C40="","",VLOOKUP($E40,'📊 SECCIONES'!$B$4:$S$9,18,FALSE())) -> 0 | O40: =IF($C40="","",ROUND('⚙️ SUPUESTOS'!$C$21*K40+'⚙️ SUPUESTOS'!$C$22*L40+'⚙️ SUPUESTOS'!$C$23*M40+'⚙️ SUPUESTOS'!$C$24*N40,4)) -> 0.5228 | P40: =IF($C40="","",VLOOKUP($E40,'📊 SECCIONES'!$B$4:$S$9,7,FALSE())) -> 66.51 | Q40: =IF($C40="","",VLOOKUP($E40,'📊 SECCIONES'!$B$4:$S$9,8,FALSE())) -> 17450 | R40: =IF($C40="","",VLOOKUP($E40,'📊 SECCIONES'!$B$4:$S$9,10,FALSE())) -> 10.6 | S40: =IF('📇 INVENTARIO'!K40="","",'📇 INVENTARIO'!K40) -> 3 | T40: =IF($C40="","","Objetivo: alcanzar calificación C. Actual: Cal."&F40&". "&IF(OR(F40="G",F40="F"),"SATE integral + cubierta + carpinterías triple + aerotermia + instalación fotovoltaica",IF(F40="E","SATE fachada + carpinterías doble + instalación fotovoltaica",IF(F40="D","Mantenimiento de envolvente + instalación fotovoltaica en cubierta","Optimización energética + instalación fotovoltaica")))) -> Objetivo: alcanzar calificación C. Actual: Cal.E. SATE fachada + carpinterías doble + instalación fotovoltaica | U40: =IF($C40="","",IF(S40=0,"s/d",IF(S40>=4,"Valorar ascensor (verificar)","—"))) -> — | V40: =IF('📇 INVENTARIO'!L40="","",'📇 INVENTARIO'!L40) -> 100.2 | W40: =IF($C40="","",V40*'⚙️ SUPUESTOS'!$C$8*'⚙️ SUPUESTOS'!$C$9) -> 21.042 | X40: =IF('📇 INVENTARIO'!N40="","",'📇 INVENTARIO'!N40) -> 1380 | Y40: =IF($C40="","",W40*X40*'⚙️ SUPUESTOS'!$C$7) -> 26134.164 | Z40: =IF($C40="","",W40*'⚙️ SUPUESTOS'!$C$10) -> 28091.07 | AA40: =IF($C40="","",Y40*('⚙️ SUPUESTOS'!$C$12*'⚙️ SUPUESTOS'!$C$11+(1-'⚙️ SUPUESTOS'!$C$12)*'⚙️ SUPUESTOS'!$C$13)) -> 1782.35 | AB40: =IF($C40="","",IF(Y40>0,ROUND(Y40*'⚙️ SUPUESTOS'!$C$12*'⚙️ SUPUESTOS'!$C$11,0),"")) -> 653 | AC40: =IF($C40="","",IF(Y40>0,ROUND(Y40*(1-'⚙️ SUPUESTOS'!$C$12)*'⚙️ SUPUESTOS'!$C$13,0),"")) -> 1129 | AD40: =IF($C40="","",IF(AND(ISNUMBER(AA40),ISNUMBER(AE40),AA40>0,AE40>0),ROUND(AA40*MAX(0,25-AE40),0),"")) -> 16468 | AE40: =IF($C40="","",IF(AA40>0,Z40/AA40,"")) -> 15.760692 | AF40: =IF($C40="","",IF(AE40="","—",IF(AE40<='⚙️ SUPUESTOS'!$C$32,"✔ Muy recomendable",IF(AE40<='⚙️ SUPUESTOS'!$C$33,"✔ Recomendable","Valorar")))) -> ✔ Recomendable | AG40: =IF('📇 INVENTARIO'!O41="","",'📇 INVENTARIO'!O41) -> 41.648107 | AH40: =IF('📇 INVENTARIO'!P41="","",'📇 INVENTARIO'!P41) -> -4.710901
A41: =IF($C41="","",RANK(O41,$O$3:$O$265,0)+COUNTIF($O$3:O41,O41)-1) -> 39 | B41: =IF($C41="","",IF(A41<='⚙️ SUPUESTOS'!$C$29,"Fase 1",IF(A41<='⚙️ SUPUESTOS'!$C$30,"Fase 2","Fase 3"))) -> Fase 1 | C41: =IF('📇 INVENTARIO'!B42="","",'📇 INVENTARIO'!B42) -> C/ Pavo Real, 20 | D41: =IF('📇 INVENTARIO'!C42="","",'📇 INVENTARIO'!C42) -> 7724229UM5172D | E41: =IF('📇 INVENTARIO'!D42="","",'📇 INVENTARIO'!D42) -> 4718606026 | F41: =IF('📇 INVENTARIO'!F42="","",'📇 INVENTARIO'!F42) -> F | G41: =IF('📇 INVENTARIO'!G42="","",'📇 INVENTARIO'!G42) -> 313 | H41: =IF('📇 INVENTARIO'!H42="","",'📇 INVENTARIO'!H42) -> 66 | I41: =IF('📇 INVENTARIO'!I42="","",'📇 INVENTARIO'!I42) -> 126.2 | J41: =IF('📇 INVENTARIO'!J42="","",'📇 INVENTARIO'!J42) -> 1965 | K41: =IF($C41="","",(G41-'⚙️ SUPUESTOS'!$C$20)/('⚙️ SUPUESTOS'!$C$25-'⚙️ SUPUESTOS'!$C$20)) -> 0.29259897 | L41: =IF($C41="","",VLOOKUP($E41,'📊 SECCIONES'!$B$4:$S$9,16,FALSE())) -> 1 | M41: =IF($C41="","",VLOOKUP($E41,'📊 SECCIONES'!$B$4:$S$9,17,FALSE())) -> 1 | N41: =IF($C41="","",VLOOKUP($E41,'📊 SECCIONES'!$B$4:$S$9,18,FALSE())) -> 0 | O41: =IF($C41="","",ROUND('⚙️ SUPUESTOS'!$C$21*K41+'⚙️ SUPUESTOS'!$C$22*L41+'⚙️ SUPUESTOS'!$C$23*M41+'⚙️ SUPUESTOS'!$C$24*N41,4)) -> 0.5209 | P41: =IF($C41="","",VLOOKUP($E41,'📊 SECCIONES'!$B$4:$S$9,7,FALSE())) -> 66.51 | Q41: =IF($C41="","",VLOOKUP($E41,'📊 SECCIONES'!$B$4:$S$9,8,FALSE())) -> 17450 | R41: =IF($C41="","",VLOOKUP($E41,'📊 SECCIONES'!$B$4:$S$9,10,FALSE())) -> 10.6 | S41: =IF('📇 INVENTARIO'!K42="","",'📇 INVENTARIO'!K42) -> 3 | T41: =IF($C41="","","Objetivo: alcanzar calificación C. Actual: Cal."&F41&". "&IF(OR(F41="G",F41="F"),"SATE integral + cubierta + carpinterías triple + aerotermia + instalación fotovoltaica",IF(F41="E","SATE fachada + carpinterías doble + instalación fotovoltaica",IF(F41="D","Mantenimiento de envolvente + instalación fotovoltaica en cubierta","Optimización energética + instalación fotovoltaica")))) -> Objetivo: alcanzar calificación C. Actual: Cal.F. SATE integral + cubierta + carpinterías triple + aerotermia + instalación fotovoltaica | U41: =IF($C41="","",IF(S41=0,"s/d",IF(S41>=4,"Valorar ascensor (verificar)","—"))) -> — | V41: =IF('📇 INVENTARIO'!L42="","",'📇 INVENTARIO'!L42) -> 103.4 | W41: =IF($C41="","",V41*'⚙️ SUPUESTOS'!$C$8*'⚙️ SUPUESTOS'!$C$9) -> 21.714 | X41: =IF('📇 INVENTARIO'!N42="","",'📇 INVENTARIO'!N42) -> 1337 | Y41: =IF($C41="","",W41*X41*'⚙️ SUPUESTOS'!$C$7) -> 26128.456 | Z41: =IF($C41="","",W41*'⚙️ SUPUESTOS'!$C$10) -> 28988.19 | AA41: =IF($C41="","",Y41*('⚙️ SUPUESTOS'!$C$12*'⚙️ SUPUESTOS'!$C$11+(1-'⚙️ SUPUESTOS'!$C$12)*'⚙️ SUPUESTOS'!$C$13)) -> 1781.9607 | AB41: =IF($C41="","",IF(Y41>0,ROUND(Y41*'⚙️ SUPUESTOS'!$C$12*'⚙️ SUPUESTOS'!$C$11,0),"")) -> 653 | AC41: =IF($C41="","",IF(Y41>0,ROUND(Y41*(1-'⚙️ SUPUESTOS'!$C$12)*'⚙️ SUPUESTOS'!$C$13,0),"")) -> 1129 | AD41: =IF($C41="","",IF(AND(ISNUMBER(AA41),ISNUMBER(AE41),AA41>0,AE41>0),ROUND(AA41*MAX(0,25-AE41),0),"")) -> 15561 | AE41: =IF($C41="","",IF(AA41>0,Z41/AA41,"")) -> 16.267581 | AF41: =IF($C41="","",IF(AE41="","—",IF(AE41<='⚙️ SUPUESTOS'!$C$32,"✔ Muy recomendable",IF(AE41<='⚙️ SUPUESTOS'!$C$33,"✔ Recomendable","Valorar")))) -> Valorar | AG41: =IF('📇 INVENTARIO'!O42="","",'📇 INVENTARIO'!O42) -> 41.64958 | AH41: =IF('📇 INVENTARIO'!P42="","",'📇 INVENTARIO'!P42) -> -4.71024
A42: =IF($C42="","",RANK(O42,$O$3:$O$265,0)+COUNTIF($O$3:O42,O42)-1) -> 40 | B42: =IF($C42="","",IF(A42<='⚙️ SUPUESTOS'!$C$29,"Fase 1",IF(A42<='⚙️ SUPUESTOS'!$C$30,"Fase 2","Fase 3"))) -> Fase 1 | C42: =IF('📇 INVENTARIO'!B43="","",'📇 INVENTARIO'!B43) -> C/ Villabáñez, 6 | D42: =IF('📇 INVENTARIO'!C43="","",'📇 INVENTARIO'!C43) -> 7625402UM5172F | E42: =IF('📇 INVENTARIO'!D43="","",'📇 INVENTARIO'!D43) -> 4718606026 | F42: =IF('📇 INVENTARIO'!F43="","",'📇 INVENTARIO'!F43) -> F | G42: =IF('📇 INVENTARIO'!G43="","",'📇 INVENTARIO'!G43) -> 312 | H42: =IF('📇 INVENTARIO'!H43="","",'📇 INVENTARIO'!H43) -> 65 | I42: =IF('📇 INVENTARIO'!I43="","",'📇 INVENTARIO'!I43) -> 146.1 | J42: =IF('📇 INVENTARIO'!J43="","",'📇 INVENTARIO'!J43) -> 1965 | K42: =IF($C42="","",(G42-'⚙️ SUPUESTOS'!$C$20)/('⚙️ SUPUESTOS'!$C$25-'⚙️ SUPUESTOS'!$C$20)) -> 0.2908778 | L42: =IF($C42="","",VLOOKUP($E42,'📊 SECCIONES'!$B$4:$S$9,16,FALSE())) -> 1 | M42: =IF($C42="","",VLOOKUP($E42,'📊 SECCIONES'!$B$4:$S$9,17,FALSE())) -> 1 | N42: =IF($C42="","",VLOOKUP($E42,'📊 SECCIONES'!$B$4:$S$9,18,FALSE())) -> 0 | O42: =IF($C42="","",ROUND('⚙️ SUPUESTOS'!$C$21*K42+'⚙️ SUPUESTOS'!$C$22*L42+'⚙️ SUPUESTOS'!$C$23*M42+'⚙️ SUPUESTOS'!$C$24*N42,4)) -> 0.52 | P42: =IF($C42="","",VLOOKUP($E42,'📊 SECCIONES'!$B$4:$S$9,7,FALSE())) -> 66.51 | Q42: =IF($C42="","",VLOOKUP($E42,'📊 SECCIONES'!$B$4:$S$9,8,FALSE())) -> 17450 | R42: =IF($C42="","",VLOOKUP($E42,'📊 SECCIONES'!$B$4:$S$9,10,FALSE())) -> 10.6 | S42: =IF('📇 INVENTARIO'!K43="","",'📇 INVENTARIO'!K43) -> 3 | T42: =IF($C42="","","Objetivo: alcanzar calificación C. Actual: Cal."&F42&". "&IF(OR(F42="G",F42="F"),"SATE integral + cubierta + carpinterías triple + aerotermia + instalación fotovoltaica",IF(F42="E","SATE fachada + carpinterías doble + instalación fotovoltaica",IF(F42="D","Mantenimiento de envolvente + instalación fotovoltaica en cubierta","Optimización energética + instalación fotovoltaica")))) -> Objetivo: alcanzar calificación C. Actual: Cal.F. SATE integral + cubierta + carpinterías triple + aerotermia + instalación fotovoltaica | U42: =IF($C42="","",IF(S42=0,"s/d",IF(S42>=4,"Valorar ascensor (verificar)","—"))) -> — | V42: =IF('📇 INVENTARIO'!L43="","",'📇 INVENTARIO'!L43) -> 115.9 | W42: =IF($C42="","",V42*'⚙️ SUPUESTOS'!$C$8*'⚙️ SUPUESTOS'!$C$9) -> 24.339 | X42: =IF('📇 INVENTARIO'!N43="","",'📇 INVENTARIO'!N43) -> 1378 | Y42: =IF($C42="","",W42*X42*'⚙️ SUPUESTOS'!$C$7) -> 30185.228 | Z42: =IF($C42="","",W42*'⚙️ SUPUESTOS'!$C$10) -> 32492.565 | AA42: =IF($C42="","",Y42*('⚙️ SUPUESTOS'!$C$12*'⚙️ SUPUESTOS'!$C$11+(1-'⚙️ SUPUESTOS'!$C$12)*'⚙️ SUPUESTOS'!$C$13)) -> 2058.6325 | AB42: =IF($C42="","",IF(Y42>0,ROUND(Y42*'⚙️ SUPUESTOS'!$C$12*'⚙️ SUPUESTOS'!$C$11,0),"")) -> 755 | AC42: =IF($C42="","",IF(Y42>0,ROUND(Y42*(1-'⚙️ SUPUESTOS'!$C$12)*'⚙️ SUPUESTOS'!$C$13,0),"")) -> 1304 | AD42: =IF($C42="","",IF(AND(ISNUMBER(AA42),ISNUMBER(AE42),AA42>0,AE42>0),ROUND(AA42*MAX(0,25-AE42),0),"")) -> 18973 | AE42: =IF($C42="","",IF(AA42>0,Z42/AA42,"")) -> 15.783567 | AF42: =IF($C42="","",IF(AE42="","—",IF(AE42<='⚙️ SUPUESTOS'!$C$32,"✔ Muy recomendable",IF(AE42<='⚙️ SUPUESTOS'!$C$33,"✔ Recomendable","Valorar")))) -> ✔ Recomendable | AG42: =IF('📇 INVENTARIO'!O43="","",'📇 INVENTARIO'!O43) -> 41.64974 | AH42: =IF('📇 INVENTARIO'!P43="","",'📇 INVENTARIO'!P43) -> -4.71036
A43: =IF($C43="","",RANK(O43,$O$3:$O$265,0)+COUNTIF($O$3:O43,O43)-1) -> 41 | B43: =IF($C43="","",IF(A43<='⚙️ SUPUESTOS'!$C$29,"Fase 1",IF(A43<='⚙️ SUPUESTOS'!$C$30,"Fase 2","Fase 3"))) -> Fase 1 | C43: =IF('📇 INVENTARIO'!B44="","",'📇 INVENTARIO'!B44) -> C/ Pavo Real, 23 | D43: =IF('📇 INVENTARIO'!C44="","",'📇 INVENTARIO'!C44) -> 7625403UM5172F | E43: =IF('📇 INVENTARIO'!D44="","",'📇 INVENTARIO'!D44) -> 4718606026 | F43: =IF('📇 INVENTARIO'!F44="","",'📇 INVENTARIO'!F44) -> F | G43: =IF('📇 INVENTARIO'!G44="","",'📇 INVENTARIO'!G44) -> 306 | H43: =IF('📇 INVENTARIO'!H44="","",'📇 INVENTARIO'!H44) -> 65 | I43: =IF('📇 INVENTARIO'!I44="","",'📇 INVENTARIO'!I44) -> 143 | J43: =IF('📇 INVENTARIO'!J44="","",'📇 INVENTARIO'!J44) -> 1965 | K43: =IF($C43="","",(G43-'⚙️ SUPUESTOS'!$C$20)/('⚙️ SUPUESTOS'!$C$25-'⚙️ SUPUESTOS'!$C$20)) -> 0.28055077 | L43: =IF($C43="","",VLOOKUP($E43,'📊 SECCIONES'!$B$4:$S$9,16,FALSE())) -> 1 | M43: =IF($C43="","",VLOOKUP($E43,'📊 SECCIONES'!$B$4:$S$9,17,FALSE())) -> 1 | N43: =IF($C43="","",VLOOKUP($E43,'📊 SECCIONES'!$B$4:$S$9,18,FALSE())) -> 0 | O43: =IF($C43="","",ROUND('⚙️ SUPUESTOS'!$C$21*K43+'⚙️ SUPUESTOS'!$C$22*L43+'⚙️ SUPUESTOS'!$C$23*M43+'⚙️ SUPUESTOS'!$C$24*N43,4)) -> 0.5143 | P43: =IF($C43="","",VLOOKUP($E43,'📊 SECCIONES'!$B$4:$S$9,7,FALSE())) -> 66.51 | Q43: =IF($C43="","",VLOOKUP($E43,'📊 SECCIONES'!$B$4:$S$9,8,FALSE())) -> 17450 | R43: =IF($C43="","",VLOOKUP($E43,'📊 SECCIONES'!$B$4:$S$9,10,FALSE())) -> 10.6 | S43: =IF('📇 INVENTARIO'!K44="","",'📇 INVENTARIO'!K44) -> 3 | T43: =IF($C43="","","Objetivo: alcanzar calificación C. Actual: Cal."&F43&". "&IF(OR(F43="G",F43="F"),"SATE integral + cubierta + carpinterías triple + aerotermia + instalación fotovoltaica",IF(F43="E","SATE fachada + carpinterías doble + instalación fotovoltaica",IF(F43="D","Mantenimiento de envolvente + instalación fotovoltaica en cubierta","Optimización energética + instalación fotovoltaica")))) -> Objetivo: alcanzar calificación C. Actual: Cal.F. SATE integral + cubierta + carpinterías triple + aerotermia + instalación fotovoltaica | U43: =IF($C43="","",IF(S43=0,"s/d",IF(S43>=4,"Valorar ascensor (verificar)","—"))) -> — | V43: =IF('📇 INVENTARIO'!L44="","",'📇 INVENTARIO'!L44) -> 99.5 | W43: =IF($C43="","",V43*'⚙️ SUPUESTOS'!$C$8*'⚙️ SUPUESTOS'!$C$9) -> 20.895 | X43: =IF('📇 INVENTARIO'!N44="","",'📇 INVENTARIO'!N44) -> 1398 | Y43: =IF($C43="","",W43*X43*'⚙️ SUPUESTOS'!$C$7) -> 26290.089 | Z43: =IF($C43="","",W43*'⚙️ SUPUESTOS'!$C$10) -> 27894.825 | AA43: =IF($C43="","",Y43*('⚙️ SUPUESTOS'!$C$12*'⚙️ SUPUESTOS'!$C$11+(1-'⚙️ SUPUESTOS'!$C$12)*'⚙️ SUPUESTOS'!$C$13)) -> 1792.9841 | AB43: =IF($C43="","",IF(Y43>0,ROUND(Y43*'⚙️ SUPUESTOS'!$C$12*'⚙️ SUPUESTOS'!$C$11,0),"")) -> 657 | AC43: =IF($C43="","",IF(Y43>0,ROUND(Y43*(1-'⚙️ SUPUESTOS'!$C$12)*'⚙️ SUPUESTOS'!$C$13,0),"")) -> 1136 | AD43: =IF($C43="","",IF(AND(ISNUMBER(AA43),ISNUMBER(AE43),AA43>0,AE43>0),ROUND(AA43*MAX(0,25-AE43),0),"")) -> 16930 | AE43: =IF($C43="","",IF(AA43>0,Z43/AA43,"")) -> 15.557765 | AF43: =IF($C43="","",IF(AE43="","—",IF(AE43<='⚙️ SUPUESTOS'!$C$32,"✔ Muy recomendable",IF(AE43<='⚙️ SUPUESTOS'!$C$33,"✔ Recomendable","Valorar")))) -> ✔ Recomendable | AG43: =IF('📇 INVENTARIO'!O44="","",'📇 INVENTARIO'!O44) -> 41.64955 | AH43: =IF('📇 INVENTARIO'!P44="","",'📇 INVENTARIO'!P44) -> -4.71047
A44: =IF($C44="","",RANK(O44,$O$3:$O$265,0)+COUNTIF($O$3:O44,O44)-1) -> 42 | B44: =IF($C44="","",IF(A44<='⚙️ SUPUESTOS'!$C$29,"Fase 1",IF(A44<='⚙️ SUPUESTOS'!$C$30,"Fase 2","Fase 3"))) -> Fase 1 | C44: =IF('📇 INVENTARIO'!B45="","",'📇 INVENTARIO'!B45) -> C/ Gaviota, 2 | D44: =IF('📇 INVENTARIO'!C45="","",'📇 INVENTARIO'!C45) -> 7824505UM5172D | E44: =IF('📇 INVENTARIO'!D45="","",'📇 INVENTARIO'!D45) -> 4718606026 | F44: =IF('📇 INVENTARIO'!F45="","",'📇 INVENTARIO'!F45) -> F | G44: =IF('📇 INVENTARIO'!G45="","",'📇 INVENTARIO'!G45) -> 302 | H44: =IF('📇 INVENTARIO'!H45="","",'📇 INVENTARIO'!H45) -> 64 | I44: =IF('📇 INVENTARIO'!I45="","",'📇 INVENTARIO'!I45) -> 155.2 | J44: =IF('📇 INVENTARIO'!J45="","",'📇 INVENTARIO'!J45) -> 1965 | K44: =IF($C44="","",(G44-'⚙️ SUPUESTOS'!$C$20)/('⚙️ SUPUESTOS'!$C$25-'⚙️ SUPUESTOS'!$C$20)) -> 0.27366609 | L44: =IF($C44="","",VLOOKUP($E44,'📊 SECCIONES'!$B$4:$S$9,16,FALSE())) -> 1 | M44: =IF($C44="","",VLOOKUP($E44,'📊 SECCIONES'!$B$4:$S$9,17,FALSE())) -> 1 | N44: =IF($C44="","",VLOOKUP($E44,'📊 SECCIONES'!$B$4:$S$9,18,FALSE())) -> 0 | O44: =IF($C44="","",ROUND('⚙️ SUPUESTOS'!$C$21*K44+'⚙️ SUPUESTOS'!$C$22*L44+'⚙️ SUPUESTOS'!$C$23*M44+'⚙️ SUPUESTOS'!$C$24*N44,4)) -> 0.5105 | P44: =IF($C44="","",VLOOKUP($E44,'📊 SECCIONES'!$B$4:$S$9,7,FALSE())) -> 66.51 | Q44: =IF($C44="","",VLOOKUP($E44,'📊 SECCIONES'!$B$4:$S$9,8,FALSE())) -> 17450 | R44: =IF($C44="","",VLOOKUP($E44,'📊 SECCIONES'!$B$4:$S$9,10,FALSE())) -> 10.6 | S44: =IF('📇 INVENTARIO'!K45="","",'📇 INVENTARIO'!K45) -> 3 | T44: =IF($C44="","","Objetivo: alcanzar calificación C. Actual: Cal."&F44&". "&IF(OR(F44="G",F44="F"),"SATE integral + cubierta + carpinterías triple + aerotermia + instalación fotovoltaica",IF(F44="E","SATE fachada + carpinterías doble + instalación fotovoltaica",IF(F44="D","Mantenimiento de envolvente + instalación fotovoltaica en cubierta","Optimización energética + instalación fotovoltaica")))) -> Objetivo: alcanzar calificación C. Actual: Cal.F. SATE integral + cubierta + carpinterías triple + aerotermia + instalación fotovoltaica | U44: =IF($C44="","",IF(S44=0,"s/d",IF(S44>=4,"Valorar ascensor (verificar)","—"))) -> — | V44: =IF('📇 INVENTARIO'!L45="","",'📇 INVENTARIO'!L45) -> 99.1 | W44: =IF($C44="","",V44*'⚙️ SUPUESTOS'!$C$8*'⚙️ SUPUESTOS'!$C$9) -> 20.811 | X44: =IF('📇 INVENTARIO'!N45="","",'📇 INVENTARIO'!N45) -> 1451 | Y44: =IF($C44="","",W44*X44*'⚙️ SUPUESTOS'!$C$7) -> 27177.085 | Z44: =IF($C44="","",W44*'⚙️ SUPUESTOS'!$C$10) -> 27782.685 | AA44: =IF($C44="","",Y44*('⚙️ SUPUESTOS'!$C$12*'⚙️ SUPUESTOS'!$C$11+(1-'⚙️ SUPUESTOS'!$C$12)*'⚙️ SUPUESTOS'!$C$13)) -> 1853.4772 | AB44: =IF($C44="","",IF(Y44>0,ROUND(Y44*'⚙️ SUPUESTOS'!$C$12*'⚙️ SUPUESTOS'!$C$11,0),"")) -> 679 | AC44: =IF($C44="","",IF(Y44>0,ROUND(Y44*(1-'⚙️ SUPUESTOS'!$C$12)*'⚙️ SUPUESTOS'!$C$13,0),"")) -> 1174 | AD44: =IF($C44="","",IF(AND(ISNUMBER(AA44),ISNUMBER(AE44),AA44>0,AE44>0),ROUND(AA44*MAX(0,25-AE44),0),"")) -> 18554 | AE44: =IF($C44="","",IF(AA44>0,Z44/AA44,"")) -> 14.989494 | AF44: =IF($C44="","",IF(AE44="","—",IF(AE44<='⚙️ SUPUESTOS'!$C$32,"✔ Muy recomendable",IF(AE44<='⚙️ SUPUESTOS'!$C$33,"✔ Recomendable","Valorar")))) -> ✔ Muy recomendable | AG44: =IF('📇 INVENTARIO'!O45="","",'📇 INVENTARIO'!O45) -> 41.64878 | AH44: =IF('📇 INVENTARIO'!P45="","",'📇 INVENTARIO'!P45) -> -4.70875
A45: =IF($C45="","",RANK(O45,$O$3:$O$265,0)+COUNTIF($O$3:O45,O45)-1) -> 43 | B45: =IF($C45="","",IF(A45<='⚙️ SUPUESTOS'!$C$29,"Fase 1",IF(A45<='⚙️ SUPUESTOS'!$C$30,"Fase 2","Fase 3"))) -> Fase 1 | C45: =IF('📇 INVENTARIO'!B46="","",'📇 INVENTARIO'!B46) -> C/ Paloma, 5 | D45: =IF('📇 INVENTARIO'!C46="","",'📇 INVENTARIO'!C46) -> 7724214UM5172D | E45: =IF('📇 INVENTARIO'!D46="","",'📇 INVENTARIO'!D46) -> 4718606026 | F45: =IF('📇 INVENTARIO'!F46="","",'📇 INVENTARIO'!F46) -> F | G45: =IF('📇 INVENTARIO'!G46="","",'📇 INVENTARIO'!G46) -> 297 | H45: =IF('📇 INVENTARIO'!H46="","",'📇 INVENTARIO'!H46) -> 63 | I45: =IF('📇 INVENTARIO'!I46="","",'📇 INVENTARIO'!I46) -> 195.6 | J45: =IF('📇 INVENTARIO'!J46="","",'📇 INVENTARIO'!J46) -> 1965 | K45: =IF($C45="","",(G45-'⚙️ SUPUESTOS'!$C$20)/('⚙️ SUPUESTOS'!$C$25-'⚙️ SUPUESTOS'!$C$20)) -> 0.26506024 | L45: =IF($C45="","",VLOOKUP($E45,'📊 SECCIONES'!$B$4:$S$9,16,FALSE())) -> 1 | M45: =IF($C45="","",VLOOKUP($E45,'📊 SECCIONES'!$B$4:$S$9,17,FALSE())) -> 1 | N45: =IF($C45="","",VLOOKUP($E45,'📊 SECCIONES'!$B$4:$S$9,18,FALSE())) -> 0 | O45: =IF($C45="","",ROUND('⚙️ SUPUESTOS'!$C$21*K45+'⚙️ SUPUESTOS'!$C$22*L45+'⚙️ SUPUESTOS'!$C$23*M45+'⚙️ SUPUESTOS'!$C$24*N45,4)) -> 0.5058 | P45: =IF($C45="","",VLOOKUP($E45,'📊 SECCIONES'!$B$4:$S$9,7,FALSE())) -> 66.51 | Q45: =IF($C45="","",VLOOKUP($E45,'📊 SECCIONES'!$B$4:$S$9,8,FALSE())) -> 17450 | R45: =IF($C45="","",VLOOKUP($E45,'📊 SECCIONES'!$B$4:$S$9,10,FALSE())) -> 10.6 | S45: =IF('📇 INVENTARIO'!K46="","",'📇 INVENTARIO'!K46) -> 3 | T45: =IF($C45="","","Objetivo: alcanzar calificación C. Actual: Cal."&F45&". "&IF(OR(F45="G",F45="F"),"SATE integral + cubierta + carpinterías triple + aerotermia + instalación fotovoltaica",IF(F45="E","SATE fachada + carpinterías doble + instalación fotovoltaica",IF(F45="D","Mantenimiento de envolvente + instalación fotovoltaica en cubierta","Optimización energética + instalación fotovoltaica")))) -> Objetivo: alcanzar calificación C. Actual: Cal.F. SATE integral + cubierta + carpinterías triple + aerotermia + instalación fotovoltaica | U45: =IF($C45="","",IF(S45=0,"s/d",IF(S45>=4,"Valorar ascensor (verificar)","—"))) -> — | V45: =IF('📇 INVENTARIO'!L46="","",'📇 INVENTARIO'!L46) -> 100.9 | W45: =IF($C45="","",V45*'⚙️ SUPUESTOS'!$C$8*'⚙️ SUPUESTOS'!$C$9) -> 21.189 | X45: =IF('📇 INVENTARIO'!N46="","",'📇 INVENTARIO'!N46) -> 1346 | Y45: =IF($C45="","",W45*X45*'⚙️ SUPUESTOS'!$C$7) -> 25668.355 | Z45: =IF($C45="","",W45*'⚙️ SUPUESTOS'!$C$10) -> 28287.315 | AA45: =IF($C45="","",Y45*('⚙️ SUPUESTOS'!$C$12*'⚙️ SUPUESTOS'!$C$11+(1-'⚙️ SUPUESTOS'!$C$12)*'⚙️ SUPUESTOS'!$C$13)) -> 1750.5818 | AB45: =IF($C45="","",IF(Y45>0,ROUND(Y45*'⚙️ SUPUESTOS'!$C$12*'⚙️ SUPUESTOS'!$C$11,0),"")) -> 642 | AC45: =IF($C45="","",IF(Y45>0,ROUND(Y45*(1-'⚙️ SUPUESTOS'!$C$12)*'⚙️ SUPUESTOS'!$C$13,0),"")) -> 1109 | AD45: =IF($C45="","",IF(AND(ISNUMBER(AA45),ISNUMBER(AE45),AA45>0,AE45>0),ROUND(AA45*MAX(0,25-AE45),0),"")) -> 15477 | AE45: =IF($C45="","",IF(AA45>0,Z45/AA45,"")) -> 16.158808 | AF45: =IF($C45="","",IF(AE45="","—",IF(AE45<='⚙️ SUPUESTOS'!$C$32,"✔ Muy recomendable",IF(AE45<='⚙️ SUPUESTOS'!$C$33,"✔ Recomendable","Valorar")))) -> Valorar | AG45: =IF('📇 INVENTARIO'!O46="","",'📇 INVENTARIO'!O46) -> 41.64884 | AH45: =IF('📇 INVENTARIO'!P46="","",'📇 INVENTARIO'!P46) -> -4.70985
A46: =IF($C46="","",RANK(O46,$O$3:$O$265,0)+COUNTIF($O$3:O46,O46)-1) -> 44 | B46: =IF($C46="","",IF(A46<='⚙️ SUPUESTOS'!$C$29,"Fase 1",IF(A46<='⚙️ SUPUESTOS'!$C$30,"Fase 2","Fase 3"))) -> Fase 1 | C46: =IF('📇 INVENTARIO'!B47="","",'📇 INVENTARIO'!B47) -> C/ Salud, 18 | D46: =IF('📇 INVENTARIO'!C47="","",'📇 INVENTARIO'!C47) -> 7625401UM5172F | E46: =IF('📇 INVENTARIO'!D47="","",'📇 INVENTARIO'!D47) -> 4718606026 | F46: =IF('📇 INVENTARIO'!F47="","",'📇 INVENTARIO'!F47) -> F | G46: =IF('📇 INVENTARIO'!G47="","",'📇 INVENTARIO'!G47) -> 295 | H46: =IF('📇 INVENTARIO'!H47="","",'📇 INVENTARIO'!H47) -> 61 | I46: =IF('📇 INVENTARIO'!I47="","",'📇 INVENTARIO'!I47) -> 170.6 | J46: =IF('📇 INVENTARIO'!J47="","",'📇 INVENTARIO'!J47) -> 1958 | K46: =IF($C46="","",(G46-'⚙️ SUPUESTOS'!$C$20)/('⚙️ SUPUESTOS'!$C$25-'⚙️ SUPUESTOS'!$C$20)) -> 0.2616179 | L46: =IF($C46="","",VLOOKUP($E46,'📊 SECCIONES'!$B$4:$S$9,16,FALSE())) -> 1 | M46: =IF($C46="","",VLOOKUP($E46,'📊 SECCIONES'!$B$4:$S$9,17,FALSE())) -> 1 | N46: =IF($C46="","",VLOOKUP($E46,'📊 SECCIONES'!$B$4:$S$9,18,FALSE())) -> 0 | O46: =IF($C46="","",ROUND('⚙️ SUPUESTOS'!$C$21*K46+'⚙️ SUPUESTOS'!$C$22*L46+'⚙️ SUPUESTOS'!$C$23*M46+'⚙️ SUPUESTOS'!$C$24*N46,4)) -> 0.5039 | P46: =IF($C46="","",VLOOKUP($E46,'📊 SECCIONES'!$B$4:$S$9,7,FALSE())) -> 66.51 | Q46: =IF($C46="","",VLOOKUP($E46,'📊 SECCIONES'!$B$4:$S$9,8,FALSE())) -> 17450 | R46: =IF($C46="","",VLOOKUP($E46,'📊 SECCIONES'!$B$4:$S$9,10,FALSE())) -> 10.6 | S46: =IF('📇 INVENTARIO'!K47="","",'📇 INVENTARIO'!K47) -> 5 | T46: =IF($C46="","","Objetivo: alcanzar calificación C. Actual: Cal."&F46&". "&IF(OR(F46="G",F46="F"),"SATE integral + cubierta + carpinterías triple + aerotermia + instalación fotovoltaica",IF(F46="E","SATE fachada + carpinterías doble + instalación fotovoltaica",IF(F46="D","Mantenimiento de envolvente + instalación fotovoltaica en cubierta","Optimización energética + instalación fotovoltaica")))) -> Objetivo: alcanzar calificación C. Actual: Cal.F. SATE integral + cubierta + carpinterías triple + aerotermia + instalación fotovoltaica | U46: =IF($C46="","",IF(S46=0,"s/d",IF(S46>=4,"Valorar ascensor (verificar)","—"))) -> Valorar ascensor (verificar) | V46: =IF('📇 INVENTARIO'!L47="","",'📇 INVENTARIO'!L47) -> 330.5 | W46: =IF($C46="","",V46*'⚙️ SUPUESTOS'!$C$8*'⚙️ SUPUESTOS'!$C$9) -> 69.405 | X46: =IF('📇 INVENTARIO'!N47="","",'📇 INVENTARIO'!N47) -> 1373 | Y46: =IF($C46="","",W46*X46*'⚙️ SUPUESTOS'!$C$7) -> 85763.759 | Z46: =IF($C46="","",W46*'⚙️ SUPUESTOS'!$C$10) -> 92655.675 | AA46: =IF($C46="","",Y46*('⚙️ SUPUESTOS'!$C$12*'⚙️ SUPUESTOS'!$C$11+(1-'⚙️ SUPUESTOS'!$C$12)*'⚙️ SUPUESTOS'!$C$13)) -> 5849.0883 | AB46: =IF($C46="","",IF(Y46>0,ROUND(Y46*'⚙️ SUPUESTOS'!$C$12*'⚙️ SUPUESTOS'!$C$11,0),"")) -> 2144 | AC46: =IF($C46="","",IF(Y46>0,ROUND(Y46*(1-'⚙️ SUPUESTOS'!$C$12)*'⚙️ SUPUESTOS'!$C$13,0),"")) -> 3705 | AD46: =IF($C46="","",IF(AND(ISNUMBER(AA46),ISNUMBER(AE46),AA46>0,AE46>0),ROUND(AA46*MAX(0,25-AE46),0),"")) -> 53572 | AE46: =IF($C46="","",IF(AA46>0,Z46/AA46,"")) -> 15.841046 | AF46: =IF($C46="","",IF(AE46="","—",IF(AE46<='⚙️ SUPUESTOS'!$C$32,"✔ Muy recomendable",IF(AE46<='⚙️ SUPUESTOS'!$C$33,"✔ Recomendable","Valorar")))) -> ✔ Recomendable | AG46: =IF('📇 INVENTARIO'!O47="","",'📇 INVENTARIO'!O47) -> 41.64966 | AH46: =IF('📇 INVENTARIO'!P47="","",'📇 INVENTARIO'!P47) -> -4.71098
A47: =IF($C47="","",RANK(O47,$O$3:$O$265,0)+COUNTIF($O$3:O47,O47)-1) -> 45 | B47: =IF($C47="","",IF(A47<='⚙️ SUPUESTOS'!$C$29,"Fase 1",IF(A47<='⚙️ SUPUESTOS'!$C$30,"Fase 2","Fase 3"))) -> Fase 1 | C47: =IF('📇 INVENTARIO'!B49="","",'📇 INVENTARIO'!B49) -> C/ Papagayo, 2 | D47: =IF('📇 INVENTARIO'!C49="","",'📇 INVENTARIO'!C49) -> 7825401UM5172F | E47: =IF('📇 INVENTARIO'!D49="","",'📇 INVENTARIO'!D49) -> 4718606023 | F47: =IF('📇 INVENTARIO'!F49="","",'📇 INVENTARIO'!F49) -> G | G47: =IF('📇 INVENTARIO'!G49="","",'📇 INVENTARIO'!G49) -> 433 | H47: =IF('📇 INVENTARIO'!H49="","",'📇 INVENTARIO'!H49) -> 91 | I47: =IF('📇 INVENTARIO'!I49="","",'📇 INVENTARIO'!I49) -> 195.6 | J47: =IF('📇 INVENTARIO'!J49="","",'📇 INVENTARIO'!J49) -> 1965 | K47: =IF($C47="","",(G47-'⚙️ SUPUESTOS'!$C$20)/('⚙️ SUPUESTOS'!$C$25-'⚙️ SUPUESTOS'!$C$20)) -> 0.49913941 | L47: =IF($C47="","",VLOOKUP($E47,'📊 SECCIONES'!$B$4:$S$9,16,FALSE())) -> 0.54128061 | M47: =IF($C47="","",VLOOKUP($E47,'📊 SECCIONES'!$B$4:$S$9,17,FALSE())) -> 0.59585492 | N47: =IF($C47="","",VLOOKUP($E47,'📊 SECCIONES'!$B$4:$S$9,18,FALSE())) -> 0.28636364 | O47: =IF($C47="","",ROUND('⚙️ SUPUESTOS'!$C$21*K47+'⚙️ SUPUESTOS'!$C$22*L47+'⚙️ SUPUESTOS'!$C$23*M47+'⚙️ SUPUESTOS'!$C$24*N47,4)) -> 0.5028 | P47: =IF($C47="","",VLOOKUP($E47,'📊 SECCIONES'!$B$4:$S$9,7,FALSE())) -> 39.41 | Q47: =IF($C47="","",VLOOKUP($E47,'📊 SECCIONES'!$B$4:$S$9,8,FALSE())) -> 22486 | R47: =IF($C47="","",VLOOKUP($E47,'📊 SECCIONES'!$B$4:$S$9,10,FALSE())) -> 16.9 | S47: =IF('📇 INVENTARIO'!K49="","",'📇 INVENTARIO'!K49) -> 3 | T47: =IF($C47="","","Objetivo: alcanzar calificación C. Actual: Cal."&F47&". "&IF(OR(F47="G",F47="F"),"SATE integral + cubierta + carpinterías triple + aerotermia + instalación fotovoltaica",IF(F47="E","SATE fachada + carpinterías doble + instalación fotovoltaica",IF(F47="D","Mantenimiento de envolvente + instalación fotovoltaica en cubierta","Optimización energética + instalación fotovoltaica")))) -> Objetivo: alcanzar calificación C. Actual: Cal.G. SATE integral + cubierta + carpinterías triple + aerotermia + instalación fotovoltaica | U47: =IF($C47="","",IF(S47=0,"s/d",IF(S47>=4,"Valorar ascensor (verificar)","—"))) -> — | V47: =IF('📇 INVENTARIO'!L49="","",'📇 INVENTARIO'!L49) -> 102.5 | W47: =IF($C47="","",V47*'⚙️ SUPUESTOS'!$C$8*'⚙️ SUPUESTOS'!$C$9) -> 21.525 | X47: =IF('📇 INVENTARIO'!N49="","",'📇 INVENTARIO'!N49) -> 1409 | Y47: =IF($C47="","",W47*X47*'⚙️ SUPUESTOS'!$C$7) -> 27295.853 | Z47: =IF($C47="","",W47*'⚙️ SUPUESTOS'!$C$10) -> 28735.875 | AA47: =IF($C47="","",Y47*('⚙️ SUPUESTOS'!$C$12*'⚙️ SUPUESTOS'!$C$11+(1-'⚙️ SUPUESTOS'!$C$12)*'⚙️ SUPUESTOS'!$C$13)) -> 1861.5771 | AB47: =IF($C47="","",IF(Y47>0,ROUND(Y47*'⚙️ SUPUESTOS'!$C$12*'⚙️ SUPUESTOS'!$C$11,0),"")) -> 682 | AC47: =IF($C47="","",IF(Y47>0,ROUND(Y47*(1-'⚙️ SUPUESTOS'!$C$12)*'⚙️ SUPUESTOS'!$C$13,0),"")) -> 1179 | AD47: =IF($C47="","",IF(AND(ISNUMBER(AA47),ISNUMBER(AE47),AA47>0,AE47>0),ROUND(AA47*MAX(0,25-AE47),0),"")) -> 17804 | AE47: =IF($C47="","",IF(AA47>0,Z47/AA47,"")) -> 15.436306 | AF47: =IF($C47="","",IF(AE47="","—",IF(AE47<='⚙️ SUPUESTOS'!$C$32,"✔ Muy recomendable",IF(AE47<='⚙️ SUPUESTOS'!$C$33,"✔ Recomendable","Valorar")))) -> ✔ Recomendable | AG47: =IF('📇 INVENTARIO'!O48="","",'📇 INVENTARIO'!O48) -> 41.649033 | AH47: =IF('📇 INVENTARIO'!P48="","",'📇 INVENTARIO'!P48) -> -4.711155
A48: =IF($C48="","",RANK(O48,$O$3:$O$265,0)+COUNTIF($O$3:O48,O48)-1) -> 46 | B48: =IF($C48="","",IF(A48<='⚙️ SUPUESTOS'!$C$29,"Fase 1",IF(A48<='⚙️ SUPUESTOS'!$C$30,"Fase 2","Fase 3"))) -> Fase 1 | C48: =IF('📇 INVENTARIO'!B48="","",'📇 INVENTARIO'!B48) -> C/ Faisán, 1 | D48: =IF('📇 INVENTARIO'!C48="","",'📇 INVENTARIO'!C48) -> 7625401UM5172F | E48: =IF('📇 INVENTARIO'!D48="","",'📇 INVENTARIO'!D48) -> 4718606026 | F48: =IF('📇 INVENTARIO'!F48="","",'📇 INVENTARIO'!F48) -> E | G48: =IF('📇 INVENTARIO'!G48="","",'📇 INVENTARIO'!G48) -> 287 | H48: =IF('📇 INVENTARIO'!H48="","",'📇 INVENTARIO'!H48) -> 60.5 | I48: =IF('📇 INVENTARIO'!I48="","",'📇 INVENTARIO'!I48) -> 130.5 | J48: =IF('📇 INVENTARIO'!J48="","",'📇 INVENTARIO'!J48) -> 1958 | K48: =IF($C48="","",(G48-'⚙️ SUPUESTOS'!$C$20)/('⚙️ SUPUESTOS'!$C$25-'⚙️ SUPUESTOS'!$C$20)) -> 0.24784854 | L48: =IF($C48="","",VLOOKUP($E48,'📊 SECCIONES'!$B$4:$S$9,16,FALSE())) -> 1 | M48: =IF($C48="","",VLOOKUP($E48,'📊 SECCIONES'!$B$4:$S$9,17,FALSE())) -> 1 | N48: =IF($C48="","",VLOOKUP($E48,'📊 SECCIONES'!$B$4:$S$9,18,FALSE())) -> 0 | O48: =IF($C48="","",ROUND('⚙️ SUPUESTOS'!$C$21*K48+'⚙️ SUPUESTOS'!$C$22*L48+'⚙️ SUPUESTOS'!$C$23*M48+'⚙️ SUPUESTOS'!$C$24*N48,4)) -> 0.4963 | P48: =IF($C48="","",VLOOKUP($E48,'📊 SECCIONES'!$B$4:$S$9,7,FALSE())) -> 66.51 | Q48: =IF($C48="","",VLOOKUP($E48,'📊 SECCIONES'!$B$4:$S$9,8,FALSE())) -> 17450 | R48: =IF($C48="","",VLOOKUP($E48,'📊 SECCIONES'!$B$4:$S$9,10,FALSE())) -> 10.6 | S48: =IF('📇 INVENTARIO'!K48="","",'📇 INVENTARIO'!K48) -> 5 | T48: =IF($C48="","","Objetivo: alcanzar calificación C. Actual: Cal."&F48&". "&IF(OR(F48="G",F48="F"),"SATE integral + cubierta + carpinterías triple + aerotermia + instalación fotovoltaica",IF(F48="E","SATE fachada + carpinterías doble + instalación fotovoltaica",IF(F48="D","Mantenimiento de envolvente + instalación fotovoltaica en cubierta","Optimización energética + instalación fotovoltaica")))) -> Objetivo: alcanzar calificación C. Actual: Cal.E. SATE fachada + carpinterías doble + instalación fotovoltaica | U48: =IF($C48="","",IF(S48=0,"s/d",IF(S48>=4,"Valorar ascensor (verificar)","—"))) -> Valorar ascensor (verificar) | V48: =IF('📇 INVENTARIO'!L48="","",'📇 INVENTARIO'!L48) -> 330.5 | W48: =IF($C48="","",V48*'⚙️ SUPUESTOS'!$C$8*'⚙️ SUPUESTOS'!$C$9) -> 69.405 | X48: =IF('📇 INVENTARIO'!N48="","",'📇 INVENTARIO'!N48) -> 1373 | Y48: =IF($C48="","",W48*X48*'⚙️ SUPUESTOS'!$C$7) -> 85763.759 | Z48: =IF($C48="","",W48*'⚙️ SUPUESTOS'!$C$10) -> 92655.675 | AA48: =IF($C48="","",Y48*('⚙️ SUPUESTOS'!$C$12*'⚙️ SUPUESTOS'!$C$11+(1-'⚙️ SUPUESTOS'!$C$12)*'⚙️ SUPUESTOS'!$C$13)) -> 5849.0883 | AB48: =IF($C48="","",IF(Y48>0,ROUND(Y48*'⚙️ SUPUESTOS'!$C$12*'⚙️ SUPUESTOS'!$C$11,0),"")) -> 2144 | AC48: =IF($C48="","",IF(Y48>0,ROUND(Y48*(1-'⚙️ SUPUESTOS'!$C$12)*'⚙️ SUPUESTOS'!$C$13,0),"")) -> 3705 | AD48: =IF($C48="","",IF(AND(ISNUMBER(AA48),ISNUMBER(AE48),AA48>0,AE48>0),ROUND(AA48*MAX(0,25-AE48),0),"")) -> 53572 | AE48: =IF($C48="","",IF(AA48>0,Z48/AA48,"")) -> 15.841046 | AF48: =IF($C48="","",IF(AE48="","—",IF(AE48<='⚙️ SUPUESTOS'!$C$32,"✔ Muy recomendable",IF(AE48<='⚙️ SUPUESTOS'!$C$33,"✔ Recomendable","Valorar")))) -> ✔ Recomendable | AG48: =IF('📇 INVENTARIO'!O49="","",'📇 INVENTARIO'!O49) -> 41.6499 | AH48: =IF('📇 INVENTARIO'!P49="","",'📇 INVENTARIO'!P49) -> -4.70894
A49: =IF($C49="","",RANK(O49,$O$3:$O$265,0)+COUNTIF($O$3:O49,O49)-1) -> 47 | B49: =IF($C49="","",IF(A49<='⚙️ SUPUESTOS'!$C$29,"Fase 1",IF(A49<='⚙️ SUPUESTOS'!$C$30,"Fase 2","Fase 3"))) -> Fase 1 | C49: =IF('📇 INVENTARIO'!B50="","",'📇 INVENTARIO'!B50) -> C/ Cigüeña, 47 | D49: =IF('📇 INVENTARIO'!C50="","",'📇 INVENTARIO'!C50) -> 7825413UM5172F | E49: =IF('📇 INVENTARIO'!D50="","",'📇 INVENTARIO'!D50) -> 4718606023 | F49: =IF('📇 INVENTARIO'!F50="","",'📇 INVENTARIO'!F50) -> G | G49: =IF('📇 INVENTARIO'!G50="","",'📇 INVENTARIO'!G50) -> 425 | H49: =IF('📇 INVENTARIO'!H50="","",'📇 INVENTARIO'!H50) -> 96.5 | I49: =IF('📇 INVENTARIO'!I50="","",'📇 INVENTARIO'!I50) -> 242.6 | J49: =IF('📇 INVENTARIO'!J50="","",'📇 INVENTARIO'!J50) -> 1965 | K49: =IF($C49="","",(G49-'⚙️ SUPUESTOS'!$C$20)/('⚙️ SUPUESTOS'!$C$25-'⚙️ SUPUESTOS'!$C$20)) -> 0.48537005 | L49: =IF($C49="","",VLOOKUP($E49,'📊 SECCIONES'!$B$4:$S$9,16,FALSE())) -> 0.54128061 | M49: =IF($C49="","",VLOOKUP($E49,'📊 SECCIONES'!$B$4:$S$9,17,FALSE())) -> 0.59585492 | N49: =IF($C49="","",VLOOKUP($E49,'📊 SECCIONES'!$B$4:$S$9,18,FALSE())) -> 0.28636364 | O49: =IF($C49="","",ROUND('⚙️ SUPUESTOS'!$C$21*K49+'⚙️ SUPUESTOS'!$C$22*L49+'⚙️ SUPUESTOS'!$C$23*M49+'⚙️ SUPUESTOS'!$C$24*N49,4)) -> 0.4952 | P49: =IF($C49="","",VLOOKUP($E49,'📊 SECCIONES'!$B$4:$S$9,7,FALSE())) -> 39.41 | Q49: =IF($C49="","",VLOOKUP($E49,'📊 SECCIONES'!$B$4:$S$9,8,FALSE())) -> 22486 | R49: =IF($C49="","",VLOOKUP($E49,'📊 SECCIONES'!$B$4:$S$9,10,FALSE())) -> 16.9 | S49: =IF('📇 INVENTARIO'!K50="","",'📇 INVENTARIO'!K50) -> 3 | T49: =IF($C49="","","Objetivo: alcanzar calificación C. Actual: Cal."&F49&". "&IF(OR(F49="G",F49="F"),"SATE integral + cubierta + carpinterías triple + aerotermia + instalación fotovoltaica",IF(F49="E","SATE fachada + carpinterías doble + instalación fotovoltaica",IF(F49="D","Mantenimiento de envolvente + instalación fotovoltaica en cubierta","Optimización energética + instalación fotovoltaica")))) -> Objetivo: alcanzar calificación C. Actual: Cal.G. SATE integral + cubierta + carpinterías triple + aerotermia + instalación fotovoltaica | U49: =IF($C49="","",IF(S49=0,"s/d",IF(S49>=4,"Valorar ascensor (verificar)","—"))) -> — | V49: =IF('📇 INVENTARIO'!L50="","",'📇 INVENTARIO'!L50) -> 99 | W49: =IF($C49="","",V49*'⚙️ SUPUESTOS'!$C$8*'⚙️ SUPUESTOS'!$C$9) -> 20.79 | X49: =IF('📇 INVENTARIO'!N50="","",'📇 INVENTARIO'!N50) -> 1507 | Y49: =IF($C49="","",W49*X49*'⚙️ SUPUESTOS'!$C$7) -> 28197.477 | Z49: =IF($C49="","",W49*'⚙️ SUPUESTOS'!$C$10) -> 27754.65 | AA49: =IF($C49="","",Y49*('⚙️ SUPUESTOS'!$C$12*'⚙️ SUPUESTOS'!$C$11+(1-'⚙️ SUPUESTOS'!$C$12)*'⚙️ SUPUESTOS'!$C$13)) -> 1923.0679 | AB49: =IF($C49="","",IF(Y49>0,ROUND(Y49*'⚙️ SUPUESTOS'!$C$12*'⚙️ SUPUESTOS'!$C$11,0),"")) -> 705 | AC49: =IF($C49="","",IF(Y49>0,ROUND(Y49*(1-'⚙️ SUPUESTOS'!$C$12)*'⚙️ SUPUESTOS'!$C$13,0),"")) -> 1218 | AD49: =IF($C49="","",IF(AND(ISNUMBER(AA49),ISNUMBER(AE49),AA49>0,AE49>0),ROUND(AA49*MAX(0,25-AE49),0),"")) -> 20322 | AE49: =IF($C49="","",IF(AA49>0,Z49/AA49,"")) -> 14.432485 | AF49: =IF($C49="","",IF(AE49="","—",IF(AE49<='⚙️ SUPUESTOS'!$C$32,"✔ Muy recomendable",IF(AE49<='⚙️ SUPUESTOS'!$C$33,"✔ Recomendable","Valorar")))) -> ✔ Muy recomendable | AG49: =IF('📇 INVENTARIO'!O50="","",'📇 INVENTARIO'!O50) -> 41.64919 | AH49: =IF('📇 INVENTARIO'!P50="","",'📇 INVENTARIO'!P50) -> -4.7082
A50: =IF($C50="","",RANK(O50,$O$3:$O$265,0)+COUNTIF($O$3:O50,O50)-1) -> 48 | B50: =IF($C50="","",IF(A50<='⚙️ SUPUESTOS'!$C$29,"Fase 1",IF(A50<='⚙️ SUPUESTOS'!$C$30,"Fase 2","Fase 3"))) -> Fase 1 | C50: =IF('📇 INVENTARIO'!B51="","",'📇 INVENTARIO'!B51) -> C/ Papagayo, 4 | D50: =IF('📇 INVENTARIO'!C51="","",'📇 INVENTARIO'!C51) -> 7825406UM5172F | E50: =IF('📇 INVENTARIO'!D51="","",'📇 INVENTARIO'!D51) -> 4718606023 | F50: =IF('📇 INVENTARIO'!F51="","",'📇 INVENTARIO'!F51) -> G | G50: =IF('📇 INVENTARIO'!G51="","",'📇 INVENTARIO'!G51) -> 424 | H50: =IF('📇 INVENTARIO'!H51="","",'📇 INVENTARIO'!H51) -> 85.5 | I50: =IF('📇 INVENTARIO'!I51="","",'📇 INVENTARIO'!I51) -> 169.8 | J50: =IF('📇 INVENTARIO'!J51="","",'📇 INVENTARIO'!J51) -> 1965 | K50: =IF($C50="","",(G50-'⚙️ SUPUESTOS'!$C$20)/('⚙️ SUPUESTOS'!$C$25-'⚙️ SUPUESTOS'!$C$20)) -> 0.48364888 | L50: =IF($C50="","",VLOOKUP($E50,'📊 SECCIONES'!$B$4:$S$9,16,FALSE())) -> 0.54128061 | M50: =IF($C50="","",VLOOKUP($E50,'📊 SECCIONES'!$B$4:$S$9,17,FALSE())) -> 0.59585492 | N50: =IF($C50="","",VLOOKUP($E50,'📊 SECCIONES'!$B$4:$S$9,18,FALSE())) -> 0.28636364 | O50: =IF($C50="","",ROUND('⚙️ SUPUESTOS'!$C$21*K50+'⚙️ SUPUESTOS'!$C$22*L50+'⚙️ SUPUESTOS'!$C$23*M50+'⚙️ SUPUESTOS'!$C$24*N50,4)) -> 0.4943 | P50: =IF($C50="","",VLOOKUP($E50,'📊 SECCIONES'!$B$4:$S$9,7,FALSE())) -> 39.41 | Q50: =IF($C50="","",VLOOKUP($E50,'📊 SECCIONES'!$B$4:$S$9,8,FALSE())) -> 22486 | R50: =IF($C50="","",VLOOKUP($E50,'📊 SECCIONES'!$B$4:$S$9,10,FALSE())) -> 16.9 | S50: =IF('📇 INVENTARIO'!K51="","",'📇 INVENTARIO'!K51) -> 3 | T50: =IF($C50="","","Objetivo: alcanzar calificación C. Actual: Cal."&F50&". "&IF(OR(F50="G",F50="F"),"SATE integral + cubierta + carpinterías triple + aerotermia + instalación fotovoltaica",IF(F50="E","SATE fachada + carpinterías doble + instalación fotovoltaica",IF(F50="D","Mantenimiento de envolvente + instalación fotovoltaica en cubierta","Optimización energética + instalación fotovoltaica")))) -> Objetivo: alcanzar calificación C. Actual: Cal.G. SATE integral + cubierta + carpinterías triple + aerotermia + instalación fotovoltaica | U50: =IF($C50="","",IF(S50=0,"s/d",IF(S50>=4,"Valorar ascensor (verificar)","—"))) -> — | V50: =IF('📇 INVENTARIO'!L51="","",'📇 INVENTARIO'!L51) -> 100.9 | W50: =IF($C50="","",V50*'⚙️ SUPUESTOS'!$C$8*'⚙️ SUPUESTOS'!$C$9) -> 21.189 | X50: =IF('📇 INVENTARIO'!N51="","",'📇 INVENTARIO'!N51) -> 1381 | Y50: =IF($C50="","",W50*X50*'⚙️ SUPUESTOS'!$C$7) -> 26335.808 | Z50: =IF($C50="","",W50*'⚙️ SUPUESTOS'!$C$10) -> 28287.315 | AA50: =IF($C50="","",Y50*('⚙️ SUPUESTOS'!$C$12*'⚙️ SUPUESTOS'!$C$11+(1-'⚙️ SUPUESTOS'!$C$12)*'⚙️ SUPUESTOS'!$C$13)) -> 1796.1021 | AB50: =IF($C50="","",IF(Y50>0,ROUND(Y50*'⚙️ SUPUESTOS'!$C$12*'⚙️ SUPUESTOS'!$C$11,0),"")) -> 658 | AC50: =IF($C50="","",IF(Y50>0,ROUND(Y50*(1-'⚙️ SUPUESTOS'!$C$12)*'⚙️ SUPUESTOS'!$C$13,0),"")) -> 1138 | AD50: =IF($C50="","",IF(AND(ISNUMBER(AA50),ISNUMBER(AE50),AA50>0,AE50>0),ROUND(AA50*MAX(0,25-AE50),0),"")) -> 16615 | AE50: =IF($C50="","",IF(AA50>0,Z50/AA50,"")) -> 15.74928 | AF50: =IF($C50="","",IF(AE50="","—",IF(AE50<='⚙️ SUPUESTOS'!$C$32,"✔ Muy recomendable",IF(AE50<='⚙️ SUPUESTOS'!$C$33,"✔ Recomendable","Valorar")))) -> ✔ Recomendable | AG50: =IF('📇 INVENTARIO'!O51="","",'📇 INVENTARIO'!O51) -> 41.64973 | AH50: =IF('📇 INVENTARIO'!P51="","",'📇 INVENTARIO'!P51) -> -4.70855
A51: =IF($C51="","",RANK(O51,$O$3:$O$265,0)+COUNTIF($O$3:O51,O51)-1) -> 49 | B51: =IF($C51="","",IF(A51<='⚙️ SUPUESTOS'!$C$29,"Fase 1",IF(A51<='⚙️ SUPUESTOS'!$C$30,"Fase 2","Fase 3"))) -> Fase 1 | C51: =IF('📇 INVENTARIO'!B54="","",'📇 INVENTARIO'!B54) -> C/ Rincón del Esgueva, 15 | D51: =IF('📇 INVENTARIO'!C54="","",'📇 INVENTARIO'!C54) -> 7726408UM5172F | E51: =IF('📇 INVENTARIO'!D54="","",'📇 INVENTARIO'!D54) -> 4718606023 | F51: =IF('📇 INVENTARIO'!F54="","",'📇 INVENTARIO'!F54) -> F | G51: =IF('📇 INVENTARIO'!G54="","",'📇 INVENTARIO'!G54) -> 412 | H51: =IF('📇 INVENTARIO'!H54="","",'📇 INVENTARIO'!H54) -> 87 | I51: =IF('📇 INVENTARIO'!I54="","",'📇 INVENTARIO'!I54) -> 296.9 | J51: =IF('📇 INVENTARIO'!J54="","",'📇 INVENTARIO'!J54) -> 1936 | K51: =IF($C51="","",(G51-'⚙️ SUPUESTOS'!$C$20)/('⚙️ SUPUESTOS'!$C$25-'⚙️ SUPUESTOS'!$C$20)) -> 0.46299484 | L51: =IF($C51="","",VLOOKUP($E51,'📊 SECCIONES'!$B$4:$S$9,16,FALSE())) -> 0.54128061 | M51: =IF($C51="","",VLOOKUP($E51,'📊 SECCIONES'!$B$4:$S$9,17,FALSE())) -> 0.59585492 | N51: =IF($C51="","",VLOOKUP($E51,'📊 SECCIONES'!$B$4:$S$9,18,FALSE())) -> 0.28636364 | O51: =IF($C51="","",ROUND('⚙️ SUPUESTOS'!$C$21*K51+'⚙️ SUPUESTOS'!$C$22*L51+'⚙️ SUPUESTOS'!$C$23*M51+'⚙️ SUPUESTOS'!$C$24*N51,4)) -> 0.4829 | P51: =IF($C51="","",VLOOKUP($E51,'📊 SECCIONES'!$B$4:$S$9,7,FALSE())) -> 39.41 | Q51: =IF($C51="","",VLOOKUP($E51,'📊 SECCIONES'!$B$4:$S$9,8,FALSE())) -> 22486 | R51: =IF($C51="","",VLOOKUP($E51,'📊 SECCIONES'!$B$4:$S$9,10,FALSE())) -> 16.9 | S51: =IF('📇 INVENTARIO'!K54="","",'📇 INVENTARIO'!K54) -> 1 | T51: =IF($C51="","","Objetivo: alcanzar calificación C. Actual: Cal."&F51&". "&IF(OR(F51="G",F51="F"),"SATE integral + cubierta + carpinterías triple + aerotermia + instalación fotovoltaica",IF(F51="E","SATE fachada + carpinterías doble + instalación fotovoltaica",IF(F51="D","Mantenimiento de envolvente + instalación fotovoltaica en cubierta","Optimización energética + instalación fotovoltaica")))) -> Objetivo: alcanzar calificación C. Actual: Cal.F. SATE integral + cubierta + carpinterías triple + aerotermia + instalación fotovoltaica | U51: =IF($C51="","",IF(S51=0,"s/d",IF(S51>=4,"Valorar ascensor (verificar)","—"))) -> — | V51: =IF('📇 INVENTARIO'!L54="","",'📇 INVENTARIO'!L54) -> 80.7 | W51: =IF($C51="","",V51*'⚙️ SUPUESTOS'!$C$8*'⚙️ SUPUESTOS'!$C$9) -> 16.947 | X51: =IF('📇 INVENTARIO'!N54="","",'📇 INVENTARIO'!N54) -> 1528 | Y51: =IF($C51="","",W51*X51*'⚙️ SUPUESTOS'!$C$7) -> 23305.514 | Z51: =IF($C51="","",W51*'⚙️ SUPUESTOS'!$C$10) -> 22624.245 | AA51: =IF($C51="","",Y51*('⚙️ SUPUESTOS'!$C$12*'⚙️ SUPUESTOS'!$C$11+(1-'⚙️ SUPUESTOS'!$C$12)*'⚙️ SUPUESTOS'!$C$13)) -> 1589.4361 | AB51: =IF($C51="","",IF(Y51>0,ROUND(Y51*'⚙️ SUPUESTOS'!$C$12*'⚙️ SUPUESTOS'!$C$11,0),"")) -> 583 | AC51: =IF($C51="","",IF(Y51>0,ROUND(Y51*(1-'⚙️ SUPUESTOS'!$C$12)*'⚙️ SUPUESTOS'!$C$13,0),"")) -> 1007 | AD51: =IF($C51="","",IF(AND(ISNUMBER(AA51),ISNUMBER(AE51),AA51>0,AE51>0),ROUND(AA51*MAX(0,25-AE51),0),"")) -> 17112 | AE51: =IF($C51="","",IF(AA51>0,Z51/AA51,"")) -> 14.234133 | AF51: =IF($C51="","",IF(AE51="","—",IF(AE51<='⚙️ SUPUESTOS'!$C$32,"✔ Muy recomendable",IF(AE51<='⚙️ SUPUESTOS'!$C$33,"✔ Recomendable","Valorar")))) -> ✔ Muy recomendable | AG51: =IF('📇 INVENTARIO'!O52="","",'📇 INVENTARIO'!O52) -> 41.6483 | AH51: =IF('📇 INVENTARIO'!P52="","",'📇 INVENTARIO'!P52) -> -4.70944
A52: =IF($C52="","",RANK(O52,$O$3:$O$265,0)+COUNTIF($O$3:O52,O52)-1) -> 50 | B52: =IF($C52="","",IF(A52<='⚙️ SUPUESTOS'!$C$29,"Fase 1",IF(A52<='⚙️ SUPUESTOS'!$C$30,"Fase 2","Fase 3"))) -> Fase 1 | C52: =IF('📇 INVENTARIO'!B52="","",'📇 INVENTARIO'!B52) -> C/ Faisán, 11 | D52: =IF('📇 INVENTARIO'!C52="","",'📇 INVENTARIO'!C52) -> 7824515UM5172D | E52: =IF('📇 INVENTARIO'!D52="","",'📇 INVENTARIO'!D52) -> 4718606026 | F52: =IF('📇 INVENTARIO'!F52="","",'📇 INVENTARIO'!F52) -> E | G52: =IF('📇 INVENTARIO'!G52="","",'📇 INVENTARIO'!G52) -> 269 | H52: =IF('📇 INVENTARIO'!H52="","",'📇 INVENTARIO'!H52) -> 55 | I52: =IF('📇 INVENTARIO'!I52="","",'📇 INVENTARIO'!I52) -> 164.8 | J52: =IF('📇 INVENTARIO'!J52="","",'📇 INVENTARIO'!J52) -> 1965 | K52: =IF($C52="","",(G52-'⚙️ SUPUESTOS'!$C$20)/('⚙️ SUPUESTOS'!$C$25-'⚙️ SUPUESTOS'!$C$20)) -> 0.21686747 | L52: =IF($C52="","",VLOOKUP($E52,'📊 SECCIONES'!$B$4:$S$9,16,FALSE())) -> 1 | M52: =IF($C52="","",VLOOKUP($E52,'📊 SECCIONES'!$B$4:$S$9,17,FALSE())) -> 1 | N52: =IF($C52="","",VLOOKUP($E52,'📊 SECCIONES'!$B$4:$S$9,18,FALSE())) -> 0 | O52: =IF($C52="","",ROUND('⚙️ SUPUESTOS'!$C$21*K52+'⚙️ SUPUESTOS'!$C$22*L52+'⚙️ SUPUESTOS'!$C$23*M52+'⚙️ SUPUESTOS'!$C$24*N52,4)) -> 0.4793 | P52: =IF($C52="","",VLOOKUP($E52,'📊 SECCIONES'!$B$4:$S$9,7,FALSE())) -> 66.51 | Q52: =IF($C52="","",VLOOKUP($E52,'📊 SECCIONES'!$B$4:$S$9,8,FALSE())) -> 17450 | R52: =IF($C52="","",VLOOKUP($E52,'📊 SECCIONES'!$B$4:$S$9,10,FALSE())) -> 10.6 | S52: =IF('📇 INVENTARIO'!K52="","",'📇 INVENTARIO'!K52) -> 3 | T52: =IF($C52="","","Objetivo: alcanzar calificación C. Actual: Cal."&F52&". "&IF(OR(F52="G",F52="F"),"SATE integral + cubierta + carpinterías triple + aerotermia + instalación fotovoltaica",IF(F52="E","SATE fachada + carpinterías doble + instalación fotovoltaica",IF(F52="D","Mantenimiento de envolvente + instalación fotovoltaica en cubierta","Optimización energética + instalación fotovoltaica")))) -> Objetivo: alcanzar calificación C. Actual: Cal.E. SATE fachada + carpinterías doble + instalación fotovoltaica | U52: =IF($C52="","",IF(S52=0,"s/d",IF(S52>=4,"Valorar ascensor (verificar)","—"))) -> — | V52: =IF('📇 INVENTARIO'!L52="","",'📇 INVENTARIO'!L52) -> 101.1 | W52: =IF($C52="","",V52*'⚙️ SUPUESTOS'!$C$8*'⚙️ SUPUESTOS'!$C$9) -> 21.231 | X52: =IF('📇 INVENTARIO'!N52="","",'📇 INVENTARIO'!N52) -> 1390 | Y52: =IF($C52="","",W52*X52*'⚙️ SUPUESTOS'!$C$7) -> 26559.981 | Z52: =IF($C52="","",W52*'⚙️ SUPUESTOS'!$C$10) -> 28343.385 | AA52: =IF($C52="","",Y52*('⚙️ SUPUESTOS'!$C$12*'⚙️ SUPUESTOS'!$C$11+(1-'⚙️ SUPUESTOS'!$C$12)*'⚙️ SUPUESTOS'!$C$13)) -> 1811.3907 | AB52: =IF($C52="","",IF(Y52>0,ROUND(Y52*'⚙️ SUPUESTOS'!$C$12*'⚙️ SUPUESTOS'!$C$11,0),"")) -> 664 | AC52: =IF($C52="","",IF(Y52>0,ROUND(Y52*(1-'⚙️ SUPUESTOS'!$C$12)*'⚙️ SUPUESTOS'!$C$13,0),"")) -> 1147 | AD52: =IF($C52="","",IF(AND(ISNUMBER(AA52),ISNUMBER(AE52),AA52>0,AE52>0),ROUND(AA52*MAX(0,25-AE52),0),"")) -> 16941 | AE52: =IF($C52="","",IF(AA52>0,Z52/AA52,"")) -> 15.647306 | AF52: =IF($C52="","",IF(AE52="","—",IF(AE52<='⚙️ SUPUESTOS'!$C$32,"✔ Muy recomendable",IF(AE52<='⚙️ SUPUESTOS'!$C$33,"✔ Recomendable","Valorar")))) -> ✔ Recomendable | AG52: =IF('📇 INVENTARIO'!O53="","",'📇 INVENTARIO'!O53) -> 41.64845 | AH52: =IF('📇 INVENTARIO'!P53="","",'📇 INVENTARIO'!P53) -> -4.70988
A53: =IF($C53="","",RANK(O53,$O$3:$O$265,0)+COUNTIF($O$3:O53,O53)-1) -> 51 | B53: =IF($C53="","",IF(A53<='⚙️ SUPUESTOS'!$C$29,"Fase 1",IF(A53<='⚙️ SUPUESTOS'!$C$30,"Fase 2","Fase 3"))) -> Fase 1 | C53: =IF('📇 INVENTARIO'!B53="","",'📇 INVENTARIO'!B53) -> C/ Faisán, 9 | D53: =IF('📇 INVENTARIO'!C53="","",'📇 INVENTARIO'!C53) -> 7724219UM5172D | E53: =IF('📇 INVENTARIO'!D53="","",'📇 INVENTARIO'!D53) -> 4718606026 | F53: =IF('📇 INVENTARIO'!F53="","",'📇 INVENTARIO'!F53) -> E | G53: =IF('📇 INVENTARIO'!G53="","",'📇 INVENTARIO'!G53) -> 268 | H53: =IF('📇 INVENTARIO'!H53="","",'📇 INVENTARIO'!H53) -> 56.5 | I53: =IF('📇 INVENTARIO'!I53="","",'📇 INVENTARIO'!I53) -> 119.3 | J53: =IF('📇 INVENTARIO'!J53="","",'📇 INVENTARIO'!J53) -> 1965 | K53: =IF($C53="","",(G53-'⚙️ SUPUESTOS'!$C$20)/('⚙️ SUPUESTOS'!$C$25-'⚙️ SUPUESTOS'!$C$20)) -> 0.2151463 | L53: =IF($C53="","",VLOOKUP($E53,'📊 SECCIONES'!$B$4:$S$9,16,FALSE())) -> 1 | M53: =IF($C53="","",VLOOKUP($E53,'📊 SECCIONES'!$B$4:$S$9,17,FALSE())) -> 1 | N53: =IF($C53="","",VLOOKUP($E53,'📊 SECCIONES'!$B$4:$S$9,18,FALSE())) -> 0 | O53: =IF($C53="","",ROUND('⚙️ SUPUESTOS'!$C$21*K53+'⚙️ SUPUESTOS'!$C$22*L53+'⚙️ SUPUESTOS'!$C$23*M53+'⚙️ SUPUESTOS'!$C$24*N53,4)) -> 0.4783 | P53: =IF($C53="","",VLOOKUP($E53,'📊 SECCIONES'!$B$4:$S$9,7,FALSE())) -> 66.51 | Q53: =IF($C53="","",VLOOKUP($E53,'📊 SECCIONES'!$B$4:$S$9,8,FALSE())) -> 17450 | R53: =IF($C53="","",VLOOKUP($E53,'📊 SECCIONES'!$B$4:$S$9,10,FALSE())) -> 10.6 | S53: =IF('📇 INVENTARIO'!K53="","",'📇 INVENTARIO'!K53) -> 3 | T53: =IF($C53="","","Objetivo: alcanzar calificación C. Actual: Cal."&F53&". "&IF(OR(F53="G",F53="F"),"SATE integral + cubierta + carpinterías triple + aerotermia + instalación fotovoltaica",IF(F53="E","SATE fachada + carpinterías doble + instalación fotovoltaica",IF(F53="D","Mantenimiento de envolvente + instalación fotovoltaica en cubierta","Optimización energética + instalación fotovoltaica")))) -> Objetivo: alcanzar calificación C. Actual: Cal.E. SATE fachada + carpinterías doble + instalación fotovoltaica | U53: =IF($C53="","",IF(S53=0,"s/d",IF(S53>=4,"Valorar ascensor (verificar)","—"))) -> — | V53: =IF('📇 INVENTARIO'!L53="","",'📇 INVENTARIO'!L53) -> 96.9 | W53: =IF($C53="","",V53*'⚙️ SUPUESTOS'!$C$8*'⚙️ SUPUESTOS'!$C$9) -> 20.349 | X53: =IF('📇 INVENTARIO'!N53="","",'📇 INVENTARIO'!N53) -> 1536 | Y53: =IF($C53="","",W53*X53*'⚙️ SUPUESTOS'!$C$7) -> 28130.458 | Z53: =IF($C53="","",W53*'⚙️ SUPUESTOS'!$C$10) -> 27165.915 | AA53: =IF($C53="","",Y53*('⚙️ SUPUESTOS'!$C$12*'⚙️ SUPUESTOS'!$C$11+(1-'⚙️ SUPUESTOS'!$C$12)*'⚙️ SUPUESTOS'!$C$13)) -> 1918.4972 | AB53: =IF($C53="","",IF(Y53>0,ROUND(Y53*'⚙️ SUPUESTOS'!$C$12*'⚙️ SUPUESTOS'!$C$11,0),"")) -> 703 | AC53: =IF($C53="","",IF(Y53>0,ROUND(Y53*(1-'⚙️ SUPUESTOS'!$C$12)*'⚙️ SUPUESTOS'!$C$13,0),"")) -> 1215 | AD53: =IF($C53="","",IF(AND(ISNUMBER(AA53),ISNUMBER(AE53),AA53>0,AE53>0),ROUND(AA53*MAX(0,25-AE53),0),"")) -> 20797 | AE53: =IF($C53="","",IF(AA53>0,Z53/AA53,"")) -> 14.159997 | AF53: =IF($C53="","",IF(AE53="","—",IF(AE53<='⚙️ SUPUESTOS'!$C$32,"✔ Muy recomendable",IF(AE53<='⚙️ SUPUESTOS'!$C$33,"✔ Recomendable","Valorar")))) -> ✔ Muy recomendable | AG53: =IF('📇 INVENTARIO'!O54="","",'📇 INVENTARIO'!O54) -> 41.65016 | AH53: =IF('📇 INVENTARIO'!P54="","",'📇 INVENTARIO'!P54) -> -4.7096
A54: =IF($C54="","",RANK(O54,$O$3:$O$265,0)+COUNTIF($O$3:O54,O54)-1) -> 52 | B54: =IF($C54="","",IF(A54<='⚙️ SUPUESTOS'!$C$29,"Fase 1",IF(A54<='⚙️ SUPUESTOS'!$C$30,"Fase 2","Fase 3"))) -> Fase 1 | C54: =IF('📇 INVENTARIO'!B55="","",'📇 INVENTARIO'!B55) -> C/ Periquito, 2 | D54: =IF('📇 INVENTARIO'!C55="","",'📇 INVENTARIO'!C55) -> 7724203UM5172D | E54: =IF('📇 INVENTARIO'!D55="","",'📇 INVENTARIO'!D55) -> 4718606026 | F54: =IF('📇 INVENTARIO'!F55="","",'📇 INVENTARIO'!F55) -> E | G54: =IF('📇 INVENTARIO'!G55="","",'📇 INVENTARIO'!G55) -> 264 | H54: =IF('📇 INVENTARIO'!H55="","",'📇 INVENTARIO'!H55) -> 55.5 | I54: =IF('📇 INVENTARIO'!I55="","",'📇 INVENTARIO'!I55) -> 120.8 | J54: =IF('📇 INVENTARIO'!J55="","",'📇 INVENTARIO'!J55) -> 1965 | K54: =IF($C54="","",(G54-'⚙️ SUPUESTOS'!$C$20)/('⚙️ SUPUESTOS'!$C$25-'⚙️ SUPUESTOS'!$C$20)) -> 0.20826162 | L54: =IF($C54="","",VLOOKUP($E54,'📊 SECCIONES'!$B$4:$S$9,16,FALSE())) -> 1 | M54: =IF($C54="","",VLOOKUP($E54,'📊 SECCIONES'!$B$4:$S$9,17,FALSE())) -> 1 | N54: =IF($C54="","",VLOOKUP($E54,'📊 SECCIONES'!$B$4:$S$9,18,FALSE())) -> 0 | O54: =IF($C54="","",ROUND('⚙️ SUPUESTOS'!$C$21*K54+'⚙️ SUPUESTOS'!$C$22*L54+'⚙️ SUPUESTOS'!$C$23*M54+'⚙️ SUPUESTOS'!$C$24*N54,4)) -> 0.4745 | P54: =IF($C54="","",VLOOKUP($E54,'📊 SECCIONES'!$B$4:$S$9,7,FALSE())) -> 66.51 | Q54: =IF($C54="","",VLOOKUP($E54,'📊 SECCIONES'!$B$4:$S$9,8,FALSE())) -> 17450 | R54: =IF($C54="","",VLOOKUP($E54,'📊 SECCIONES'!$B$4:$S$9,10,FALSE())) -> 10.6 | S54: =IF('📇 INVENTARIO'!K55="","",'📇 INVENTARIO'!K55) -> 3 | T54: =IF($C54="","","Objetivo: alcanzar calificación C. Actual: Cal."&F54&". "&IF(OR(F54="G",F54="F"),"SATE integral + cubierta + carpinterías triple + aerotermia + instalación fotovoltaica",IF(F54="E","SATE fachada + carpinterías doble + instalación fotovoltaica",IF(F54="D","Mantenimiento de envolvente + instalación fotovoltaica en cubierta","Optimización energética + instalación fotovoltaica")))) -> Objetivo: alcanzar calificación C. Actual: Cal.E. SATE fachada + carpinterías doble + instalación fotovoltaica | U54: =IF($C54="","",IF(S54=0,"s/d",IF(S54>=4,"Valorar ascensor (verificar)","—"))) -> — | V54: =IF('📇 INVENTARIO'!L55="","",'📇 INVENTARIO'!L55) -> 112.5 | W54: =IF($C54="","",V54*'⚙️ SUPUESTOS'!$C$8*'⚙️ SUPUESTOS'!$C$9) -> 23.625 | X54: =IF('📇 INVENTARIO'!N55="","",'📇 INVENTARIO'!N55) -> 1405 | Y54: =IF($C54="","",W54*X54*'⚙️ SUPUESTOS'!$C$7) -> 29873.812 | Z54: =IF($C54="","",W54*'⚙️ SUPUESTOS'!$C$10) -> 31539.375 | AA54: =IF($C54="","",Y54*('⚙️ SUPUESTOS'!$C$12*'⚙️ SUPUESTOS'!$C$11+(1-'⚙️ SUPUESTOS'!$C$12)*'⚙️ SUPUESTOS'!$C$13)) -> 2037.394 | AB54: =IF($C54="","",IF(Y54>0,ROUND(Y54*'⚙️ SUPUESTOS'!$C$12*'⚙️ SUPUESTOS'!$C$11,0),"")) -> 747 | AC54: =IF($C54="","",IF(Y54>0,ROUND(Y54*(1-'⚙️ SUPUESTOS'!$C$12)*'⚙️ SUPUESTOS'!$C$13,0),"")) -> 1291 | AD54: =IF($C54="","",IF(AND(ISNUMBER(AA54),ISNUMBER(AE54),AA54>0,AE54>0),ROUND(AA54*MAX(0,25-AE54),0),"")) -> 19395 | AE54: =IF($C54="","",IF(AA54>0,Z54/AA54,"")) -> 15.480253 | AF54: =IF($C54="","",IF(AE54="","—",IF(AE54<='⚙️ SUPUESTOS'!$C$32,"✔ Muy recomendable",IF(AE54<='⚙️ SUPUESTOS'!$C$33,"✔ Recomendable","Valorar")))) -> ✔ Recomendable | AG54: =IF('📇 INVENTARIO'!O55="","",'📇 INVENTARIO'!O55) -> 41.64942 | AH54: =IF('📇 INVENTARIO'!P55="","",'📇 INVENTARIO'!P55) -> -4.71005
A55: =IF($C55="","",RANK(O55,$O$3:$O$265,0)+COUNTIF($O$3:O55,O55)-1) -> 53 | B55: =IF($C55="","",IF(A55<='⚙️ SUPUESTOS'!$C$29,"Fase 1",IF(A55<='⚙️ SUPUESTOS'!$C$30,"Fase 2","Fase 3"))) -> Fase 1 | C55: =IF('📇 INVENTARIO'!B56="","",'📇 INVENTARIO'!B56) -> C/ Garza, 4 | D55: =IF('📇 INVENTARIO'!C56="","",'📇 INVENTARIO'!C56) -> 7825410UM5172F | E55: =IF('📇 INVENTARIO'!D56="","",'📇 INVENTARIO'!D56) -> 4718606023 | F55: =IF('📇 INVENTARIO'!F56="","",'📇 INVENTARIO'!F56) -> F | G55: =IF('📇 INVENTARIO'!G56="","",'📇 INVENTARIO'!G56) -> 402 | H55: =IF('📇 INVENTARIO'!H56="","",'📇 INVENTARIO'!H56) -> 85 | I55: =IF('📇 INVENTARIO'!I56="","",'📇 INVENTARIO'!I56) -> 211.5 | J55: =IF('📇 INVENTARIO'!J56="","",'📇 INVENTARIO'!J56) -> 1965 | K55: =IF($C55="","",(G55-'⚙️ SUPUESTOS'!$C$20)/('⚙️ SUPUESTOS'!$C$25-'⚙️ SUPUESTOS'!$C$20)) -> 0.44578313 | L55: =IF($C55="","",VLOOKUP($E55,'📊 SECCIONES'!$B$4:$S$9,16,FALSE())) -> 0.54128061 | M55: =IF($C55="","",VLOOKUP($E55,'📊 SECCIONES'!$B$4:$S$9,17,FALSE())) -> 0.59585492 | N55: =IF($C55="","",VLOOKUP($E55,'📊 SECCIONES'!$B$4:$S$9,18,FALSE())) -> 0.28636364 | O55: =IF($C55="","",ROUND('⚙️ SUPUESTOS'!$C$21*K55+'⚙️ SUPUESTOS'!$C$22*L55+'⚙️ SUPUESTOS'!$C$23*M55+'⚙️ SUPUESTOS'!$C$24*N55,4)) -> 0.4735 | P55: =IF($C55="","",VLOOKUP($E55,'📊 SECCIONES'!$B$4:$S$9,7,FALSE())) -> 39.41 | Q55: =IF($C55="","",VLOOKUP($E55,'📊 SECCIONES'!$B$4:$S$9,8,FALSE())) -> 22486 | R55: =IF($C55="","",VLOOKUP($E55,'📊 SECCIONES'!$B$4:$S$9,10,FALSE())) -> 16.9 | S55: =IF('📇 INVENTARIO'!K56="","",'📇 INVENTARIO'!K56) -> 3 | T55: =IF($C55="","","Objetivo: alcanzar calificación C. Actual: Cal."&F55&". "&IF(OR(F55="G",F55="F"),"SATE integral + cubierta + carpinterías triple + aerotermia + instalación fotovoltaica",IF(F55="E","SATE fachada + carpinterías doble + instalación fotovoltaica",IF(F55="D","Mantenimiento de envolvente + instalación fotovoltaica en cubierta","Optimización energética + instalación fotovoltaica")))) -> Objetivo: alcanzar calificación C. Actual: Cal.F. SATE integral + cubierta + carpinterías triple + aerotermia + instalación fotovoltaica | U55: =IF($C55="","",IF(S55=0,"s/d",IF(S55>=4,"Valorar ascensor (verificar)","—"))) -> — | V55: =IF('📇 INVENTARIO'!L56="","",'📇 INVENTARIO'!L56) -> 101.2 | W55: =IF($C55="","",V55*'⚙️ SUPUESTOS'!$C$8*'⚙️ SUPUESTOS'!$C$9) -> 21.252 | X55: =IF('📇 INVENTARIO'!N56="","",'📇 INVENTARIO'!N56) -> 1382 | Y55: =IF($C55="","",W55*X55*'⚙️ SUPUESTOS'!$C$7) -> 26433.238 | Z55: =IF($C55="","",W55*'⚙️ SUPUESTOS'!$C$10) -> 28371.42 | AA55: =IF($C55="","",Y55*('⚙️ SUPUESTOS'!$C$12*'⚙️ SUPUESTOS'!$C$11+(1-'⚙️ SUPUESTOS'!$C$12)*'⚙️ SUPUESTOS'!$C$13)) -> 1802.7468 | AB55: =IF($C55="","",IF(Y55>0,ROUND(Y55*'⚙️ SUPUESTOS'!$C$12*'⚙️ SUPUESTOS'!$C$11,0),"")) -> 661 | AC55: =IF($C55="","",IF(Y55>0,ROUND(Y55*(1-'⚙️ SUPUESTOS'!$C$12)*'⚙️ SUPUESTOS'!$C$13,0),"")) -> 1142 | AD55: =IF($C55="","",IF(AND(ISNUMBER(AA55),ISNUMBER(AE55),AA55>0,AE55>0),ROUND(AA55*MAX(0,25-AE55),0),"")) -> 16697 | AE55: =IF($C55="","",IF(AA55>0,Z55/AA55,"")) -> 15.737884 | AF55: =IF($C55="","",IF(AE55="","—",IF(AE55<='⚙️ SUPUESTOS'!$C$32,"✔ Muy recomendable",IF(AE55<='⚙️ SUPUESTOS'!$C$33,"✔ Recomendable","Valorar")))) -> ✔ Recomendable | AG55: =IF('📇 INVENTARIO'!O56="","",'📇 INVENTARIO'!O56) -> 41.64941 | AH55: =IF('📇 INVENTARIO'!P56="","",'📇 INVENTARIO'!P56) -> -4.70836
A56: =IF($C56="","",RANK(O56,$O$3:$O$265,0)+COUNTIF($O$3:O56,O56)-1) -> 54 | B56: =IF($C56="","",IF(A56<='⚙️ SUPUESTOS'!$C$29,"Fase 1",IF(A56<='⚙️ SUPUESTOS'!$C$30,"Fase 2","Fase 3"))) -> Fase 1 | C56: =IF('📇 INVENTARIO'!B58="","",'📇 INVENTARIO'!B58) -> C/ Pingüino, 6 | D56: =IF('📇 INVENTARIO'!C58="","",'📇 INVENTARIO'!C58) -> 7925703UM5172F | E56: =IF('📇 INVENTARIO'!D58="","",'📇 INVENTARIO'!D58) -> 4718606023 | F56: =IF('📇 INVENTARIO'!F58="","",'📇 INVENTARIO'!F58) -> G | G56: =IF('📇 INVENTARIO'!G58="","",'📇 INVENTARIO'!G58) -> 401 | H56: =IF('📇 INVENTARIO'!H58="","",'📇 INVENTARIO'!H58) -> 85 | I56: =IF('📇 INVENTARIO'!I58="","",'📇 INVENTARIO'!I58) -> 202.5 | J56: =IF('📇 INVENTARIO'!J58="","",'📇 INVENTARIO'!J58) -> 1965 | K56: =IF($C56="","",(G56-'⚙️ SUPUESTOS'!$C$20)/('⚙️ SUPUESTOS'!$C$25-'⚙️ SUPUESTOS'!$C$20)) -> 0.44406196 | L56: =IF($C56="","",VLOOKUP($E56,'📊 SECCIONES'!$B$4:$S$9,16,FALSE())) -> 0.54128061 | M56: =IF($C56="","",VLOOKUP($E56,'📊 SECCIONES'!$B$4:$S$9,17,FALSE())) -> 0.59585492 | N56: =IF($C56="","",VLOOKUP($E56,'📊 SECCIONES'!$B$4:$S$9,18,FALSE())) -> 0.28636364 | O56: =IF($C56="","",ROUND('⚙️ SUPUESTOS'!$C$21*K56+'⚙️ SUPUESTOS'!$C$22*L56+'⚙️ SUPUESTOS'!$C$23*M56+'⚙️ SUPUESTOS'!$C$24*N56,4)) -> 0.4725 | P56: =IF($C56="","",VLOOKUP($E56,'📊 SECCIONES'!$B$4:$S$9,7,FALSE())) -> 39.41 | Q56: =IF($C56="","",VLOOKUP($E56,'📊 SECCIONES'!$B$4:$S$9,8,FALSE())) -> 22486 | R56: =IF($C56="","",VLOOKUP($E56,'📊 SECCIONES'!$B$4:$S$9,10,FALSE())) -> 16.9 | S56: =IF('📇 INVENTARIO'!K58="","",'📇 INVENTARIO'!K58) -> 3 | T56: =IF($C56="","","Objetivo: alcanzar calificación C. Actual: Cal."&F56&". "&IF(OR(F56="G",F56="F"),"SATE integral + cubierta + carpinterías triple + aerotermia + instalación fotovoltaica",IF(F56="E","SATE fachada + carpinterías doble + instalación fotovoltaica",IF(F56="D","Mantenimiento de envolvente + instalación fotovoltaica en cubierta","Optimización energética + instalación fotovoltaica")))) -> Objetivo: alcanzar calificación C. Actual: Cal.G. SATE integral + cubierta + carpinterías triple + aerotermia + instalación fotovoltaica | U56: =IF($C56="","",IF(S56=0,"s/d",IF(S56>=4,"Valorar ascensor (verificar)","—"))) -> — | V56: =IF('📇 INVENTARIO'!L58="","",'📇 INVENTARIO'!L58) -> 102 | W56: =IF($C56="","",V56*'⚙️ SUPUESTOS'!$C$8*'⚙️ SUPUESTOS'!$C$9) -> 21.42 | X56: =IF('📇 INVENTARIO'!N58="","",'📇 INVENTARIO'!N58) -> 1295 | Y56: =IF($C56="","",W56*X56*'⚙️ SUPUESTOS'!$C$7) -> 24965.01 | Z56: =IF($C56="","",W56*'⚙️ SUPUESTOS'!$C$10) -> 28595.7 | AA56: =IF($C56="","",Y56*('⚙️ SUPUESTOS'!$C$12*'⚙️ SUPUESTOS'!$C$11+(1-'⚙️ SUPUESTOS'!$C$12)*'⚙️ SUPUESTOS'!$C$13)) -> 1702.6137 | AB56: =IF($C56="","",IF(Y56>0,ROUND(Y56*'⚙️ SUPUESTOS'!$C$12*'⚙️ SUPUESTOS'!$C$11,0),"")) -> 624 | AC56: =IF($C56="","",IF(Y56>0,ROUND(Y56*(1-'⚙️ SUPUESTOS'!$C$12)*'⚙️ SUPUESTOS'!$C$13,0),"")) -> 1078 | AD56: =IF($C56="","",IF(AND(ISNUMBER(AA56),ISNUMBER(AE56),AA56>0,AE56>0),ROUND(AA56*MAX(0,25-AE56),0),"")) -> 13970 | AE56: =IF($C56="","",IF(AA56>0,Z56/AA56,"")) -> 16.795178 | AF56: =IF($C56="","",IF(AE56="","—",IF(AE56<='⚙️ SUPUESTOS'!$C$32,"✔ Muy recomendable",IF(AE56<='⚙️ SUPUESTOS'!$C$33,"✔ Recomendable","Valorar")))) -> Valorar | AG56: =IF('📇 INVENTARIO'!O57="","",'📇 INVENTARIO'!O57) -> 41.64876 | AH56: =IF('📇 INVENTARIO'!P57="","",'📇 INVENTARIO'!P57) -> -4.70852
A57: =IF($C57="","",RANK(O57,$O$3:$O$265,0)+COUNTIF($O$3:O57,O57)-1) -> 55 | B57: =IF($C57="","",IF(A57<='⚙️ SUPUESTOS'!$C$29,"Fase 1",IF(A57<='⚙️ SUPUESTOS'!$C$30,"Fase 2","Fase 3"))) -> Fase 1 | C57: =IF('📇 INVENTARIO'!B57="","",'📇 INVENTARIO'!B57) -> C/ Cigüeña, 45 | D57: =IF('📇 INVENTARIO'!C57="","",'📇 INVENTARIO'!C57) -> 7824503UM5172D | E57: =IF('📇 INVENTARIO'!D57="","",'📇 INVENTARIO'!D57) -> 4718606026 | F57: =IF('📇 INVENTARIO'!F57="","",'📇 INVENTARIO'!F57) -> E | G57: =IF('📇 INVENTARIO'!G57="","",'📇 INVENTARIO'!G57) -> 256 | H57: =IF('📇 INVENTARIO'!H57="","",'📇 INVENTARIO'!H57) -> 53.5 | I57: =IF('📇 INVENTARIO'!I57="","",'📇 INVENTARIO'!I57) -> 123.2 | J57: =IF('📇 INVENTARIO'!J57="","",'📇 INVENTARIO'!J57) -> 1965 | K57: =IF($C57="","",(G57-'⚙️ SUPUESTOS'!$C$20)/('⚙️ SUPUESTOS'!$C$25-'⚙️ SUPUESTOS'!$C$20)) -> 0.19449225 | L57: =IF($C57="","",VLOOKUP($E57,'📊 SECCIONES'!$B$4:$S$9,16,FALSE())) -> 1 | M57: =IF($C57="","",VLOOKUP($E57,'📊 SECCIONES'!$B$4:$S$9,17,FALSE())) -> 1 | N57: =IF($C57="","",VLOOKUP($E57,'📊 SECCIONES'!$B$4:$S$9,18,FALSE())) -> 0 | O57: =IF($C57="","",ROUND('⚙️ SUPUESTOS'!$C$21*K57+'⚙️ SUPUESTOS'!$C$22*L57+'⚙️ SUPUESTOS'!$C$23*M57+'⚙️ SUPUESTOS'!$C$24*N57,4)) -> 0.467 | P57: =IF($C57="","",VLOOKUP($E57,'📊 SECCIONES'!$B$4:$S$9,7,FALSE())) -> 66.51 | Q57: =IF($C57="","",VLOOKUP($E57,'📊 SECCIONES'!$B$4:$S$9,8,FALSE())) -> 17450 | R57: =IF($C57="","",VLOOKUP($E57,'📊 SECCIONES'!$B$4:$S$9,10,FALSE())) -> 10.6 | S57: =IF('📇 INVENTARIO'!K57="","",'📇 INVENTARIO'!K57) -> 3 | T57: =IF($C57="","","Objetivo: alcanzar calificación C. Actual: Cal."&F57&". "&IF(OR(F57="G",F57="F"),"SATE integral + cubierta + carpinterías triple + aerotermia + instalación fotovoltaica",IF(F57="E","SATE fachada + carpinterías doble + instalación fotovoltaica",IF(F57="D","Mantenimiento de envolvente + instalación fotovoltaica en cubierta","Optimización energética + instalación fotovoltaica")))) -> Objetivo: alcanzar calificación C. Actual: Cal.E. SATE fachada + carpinterías doble + instalación fotovoltaica | U57: =IF($C57="","",IF(S57=0,"s/d",IF(S57>=4,"Valorar ascensor (verificar)","—"))) -> — | V57: =IF('📇 INVENTARIO'!L57="","",'📇 INVENTARIO'!L57) -> 98.1 | W57: =IF($C57="","",V57*'⚙️ SUPUESTOS'!$C$8*'⚙️ SUPUESTOS'!$C$9) -> 20.601 | X57: =IF('📇 INVENTARIO'!N57="","",'📇 INVENTARIO'!N57) -> 1549 | Y57: =IF($C57="","",W57*X57*'⚙️ SUPUESTOS'!$C$7) -> 28719.854 | Z57: =IF($C57="","",W57*'⚙️ SUPUESTOS'!$C$10) -> 27502.335 | AA57: =IF($C57="","",Y57*('⚙️ SUPUESTOS'!$C$12*'⚙️ SUPUESTOS'!$C$11+(1-'⚙️ SUPUESTOS'!$C$12)*'⚙️ SUPUESTOS'!$C$13)) -> 1958.694 | AB57: =IF($C57="","",IF(Y57>0,ROUND(Y57*'⚙️ SUPUESTOS'!$C$12*'⚙️ SUPUESTOS'!$C$11,0),"")) -> 718 | AC57: =IF($C57="","",IF(Y57>0,ROUND(Y57*(1-'⚙️ SUPUESTOS'!$C$12)*'⚙️ SUPUESTOS'!$C$13,0),"")) -> 1241 | AD57: =IF($C57="","",IF(AND(ISNUMBER(AA57),ISNUMBER(AE57),AA57>0,AE57>0),ROUND(AA57*MAX(0,25-AE57),0),"")) -> 21465 | AE57: =IF($C57="","",IF(AA57>0,Z57/AA57,"")) -> 14.041159 | AF57: =IF($C57="","",IF(AE57="","—",IF(AE57<='⚙️ SUPUESTOS'!$C$32,"✔ Muy recomendable",IF(AE57<='⚙️ SUPUESTOS'!$C$33,"✔ Recomendable","Valorar")))) -> ✔ Muy recomendable | AG57: =IF('📇 INVENTARIO'!O58="","",'📇 INVENTARIO'!O58) -> 41.65007 | AH57: =IF('📇 INVENTARIO'!P58="","",'📇 INVENTARIO'!P58) -> -4.70838
A58: =IF($C58="","",RANK(O58,$O$3:$O$265,0)+COUNTIF($O$3:O58,O58)-1) -> 56 | B58: =IF($C58="","",IF(A58<='⚙️ SUPUESTOS'!$C$29,"Fase 1",IF(A58<='⚙️ SUPUESTOS'!$C$30,"Fase 2","Fase 3"))) -> Fase 1 | C58: =IF('📇 INVENTARIO'!B59="","",'📇 INVENTARIO'!B59) -> C/ Villabáñez, 19 | D58: =IF('📇 INVENTARIO'!C59="","",'📇 INVENTARIO'!C59) -> 7825417UM5172F | E58: =IF('📇 INVENTARIO'!D59="","",'📇 INVENTARIO'!D59) -> 4718606023 | F58: =IF('📇 INVENTARIO'!F59="","",'📇 INVENTARIO'!F59) -> G | G58: =IF('📇 INVENTARIO'!G59="","",'📇 INVENTARIO'!G59) -> 389 | H58: =IF('📇 INVENTARIO'!H59="","",'📇 INVENTARIO'!H59) -> 82 | I58: =IF('📇 INVENTARIO'!I59="","",'📇 INVENTARIO'!I59) -> 182.6 | J58: =IF('📇 INVENTARIO'!J59="","",'📇 INVENTARIO'!J59) -> 1965 | K58: =IF($C58="","",(G58-'⚙️ SUPUESTOS'!$C$20)/('⚙️ SUPUESTOS'!$C$25-'⚙️ SUPUESTOS'!$C$20)) -> 0.42340792 | L58: =IF($C58="","",VLOOKUP($E58,'📊 SECCIONES'!$B$4:$S$9,16,FALSE())) -> 0.54128061 | M58: =IF($C58="","",VLOOKUP($E58,'📊 SECCIONES'!$B$4:$S$9,17,FALSE())) -> 0.59585492 | N58: =IF($C58="","",VLOOKUP($E58,'📊 SECCIONES'!$B$4:$S$9,18,FALSE())) -> 0.28636364 | O58: =IF($C58="","",ROUND('⚙️ SUPUESTOS'!$C$21*K58+'⚙️ SUPUESTOS'!$C$22*L58+'⚙️ SUPUESTOS'!$C$23*M58+'⚙️ SUPUESTOS'!$C$24*N58,4)) -> 0.4611 | P58: =IF($C58="","",VLOOKUP($E58,'📊 SECCIONES'!$B$4:$S$9,7,FALSE())) -> 39.41 | Q58: =IF($C58="","",VLOOKUP($E58,'📊 SECCIONES'!$B$4:$S$9,8,FALSE())) -> 22486 | R58: =IF($C58="","",VLOOKUP($E58,'📊 SECCIONES'!$B$4:$S$9,10,FALSE())) -> 16.9 | S58: =IF('📇 INVENTARIO'!K59="","",'📇 INVENTARIO'!K59) -> 3 | T58: =IF($C58="","","Objetivo: alcanzar calificación C. Actual: Cal."&F58&". "&IF(OR(F58="G",F58="F"),"SATE integral + cubierta + carpinterías triple + aerotermia + instalación fotovoltaica",IF(F58="E","SATE fachada + carpinterías doble + instalación fotovoltaica",IF(F58="D","Mantenimiento de envolvente + instalación fotovoltaica en cubierta","Optimización energética + instalación fotovoltaica")))) -> Objetivo: alcanzar calificación C. Actual: Cal.G. SATE integral + cubierta + carpinterías triple + aerotermia + instalación fotovoltaica | U58: =IF($C58="","",IF(S58=0,"s/d",IF(S58>=4,"Valorar ascensor (verificar)","—"))) -> — | V58: =IF('📇 INVENTARIO'!L59="","",'📇 INVENTARIO'!L59) -> 115.8 | W58: =IF($C58="","",V58*'⚙️ SUPUESTOS'!$C$8*'⚙️ SUPUESTOS'!$C$9) -> 24.318 | X58: =IF('📇 INVENTARIO'!N59="","",'📇 INVENTARIO'!N59) -> 1420 | Y58: =IF($C58="","",W58*X58*'⚙️ SUPUESTOS'!$C$7) -> 31078.404 | Z58: =IF($C58="","",W58*'⚙️ SUPUESTOS'!$C$10) -> 32464.53 | AA58: =IF($C58="","",Y58*('⚙️ SUPUESTOS'!$C$12*'⚙️ SUPUESTOS'!$C$11+(1-'⚙️ SUPUESTOS'!$C$12)*'⚙️ SUPUESTOS'!$C$13)) -> 2119.5472 | AB58: =IF($C58="","",IF(Y58>0,ROUND(Y58*'⚙️ SUPUESTOS'!$C$12*'⚙️ SUPUESTOS'!$C$11,0),"")) -> 777 | AC58: =IF($C58="","",IF(Y58>0,ROUND(Y58*(1-'⚙️ SUPUESTOS'!$C$12)*'⚙️ SUPUESTOS'!$C$13,0),"")) -> 1343 | AD58: =IF($C58="","",IF(AND(ISNUMBER(AA58),ISNUMBER(AE58),AA58>0,AE58>0),ROUND(AA58*MAX(0,25-AE58),0),"")) -> 20524 | AE58: =IF($C58="","",IF(AA58>0,Z58/AA58,"")) -> 15.316729 | AF58: =IF($C58="","",IF(AE58="","—",IF(AE58<='⚙️ SUPUESTOS'!$C$32,"✔ Muy recomendable",IF(AE58<='⚙️ SUPUESTOS'!$C$33,"✔ Recomendable","Valorar")))) -> ✔ Recomendable | AG58: =IF('📇 INVENTARIO'!O59="","",'📇 INVENTARIO'!O59) -> 41.64925 | AH58: =IF('📇 INVENTARIO'!P59="","",'📇 INVENTARIO'!P59) -> -4.70886
A59: =IF($C59="","",RANK(O59,$O$3:$O$265,0)+COUNTIF($O$3:O59,O59)-1) -> 57 | B59: =IF($C59="","",IF(A59<='⚙️ SUPUESTOS'!$C$29,"Fase 1",IF(A59<='⚙️ SUPUESTOS'!$C$30,"Fase 2","Fase 3"))) -> Fase 1 | C59: =IF('📇 INVENTARIO'!B60="","",'📇 INVENTARIO'!B60) -> C/ Oropéndola, 2 | D59: =IF('📇 INVENTARIO'!C60="","",'📇 INVENTARIO'!C60) -> 7825408UM5172F | E59: =IF('📇 INVENTARIO'!D60="","",'📇 INVENTARIO'!D60) -> 4718606023 | F59: =IF('📇 INVENTARIO'!F60="","",'📇 INVENTARIO'!F60) -> G | G59: =IF('📇 INVENTARIO'!G60="","",'📇 INVENTARIO'!G60) -> 387 | H59: =IF('📇 INVENTARIO'!H60="","",'📇 INVENTARIO'!H60) -> 73 | I59: =IF('📇 INVENTARIO'!I60="","",'📇 INVENTARIO'!I60) -> 149.1 | J59: =IF('📇 INVENTARIO'!J60="","",'📇 INVENTARIO'!J60) -> 1965 | K59: =IF($C59="","",(G59-'⚙️ SUPUESTOS'!$C$20)/('⚙️ SUPUESTOS'!$C$25-'⚙️ SUPUESTOS'!$C$20)) -> 0.41996558 | L59: =IF($C59="","",VLOOKUP($E59,'📊 SECCIONES'!$B$4:$S$9,16,FALSE())) -> 0.54128061 | M59: =IF($C59="","",VLOOKUP($E59,'📊 SECCIONES'!$B$4:$S$9,17,FALSE())) -> 0.59585492 | N59: =IF($C59="","",VLOOKUP($E59,'📊 SECCIONES'!$B$4:$S$9,18,FALSE())) -> 0.28636364 | O59: =IF($C59="","",ROUND('⚙️ SUPUESTOS'!$C$21*K59+'⚙️ SUPUESTOS'!$C$22*L59+'⚙️ SUPUESTOS'!$C$23*M59+'⚙️ SUPUESTOS'!$C$24*N59,4)) -> 0.4593 | P59: =IF($C59="","",VLOOKUP($E59,'📊 SECCIONES'!$B$4:$S$9,7,FALSE())) -> 39.41 | Q59: =IF($C59="","",VLOOKUP($E59,'📊 SECCIONES'!$B$4:$S$9,8,FALSE())) -> 22486 | R59: =IF($C59="","",VLOOKUP($E59,'📊 SECCIONES'!$B$4:$S$9,10,FALSE())) -> 16.9 | S59: =IF('📇 INVENTARIO'!K60="","",'📇 INVENTARIO'!K60) -> 3 | T59: =IF($C59="","","Objetivo: alcanzar calificación C. Actual: Cal."&F59&". "&IF(OR(F59="G",F59="F"),"SATE integral + cubierta + carpinterías triple + aerotermia + instalación fotovoltaica",IF(F59="E","SATE fachada + carpinterías doble + instalación fotovoltaica",IF(F59="D","Mantenimiento de envolvente + instalación fotovoltaica en cubierta","Optimización energética + instalación fotovoltaica")))) -> Objetivo: alcanzar calificación C. Actual: Cal.G. SATE integral + cubierta + carpinterías triple + aerotermia + instalación fotovoltaica | U59: =IF($C59="","",IF(S59=0,"s/d",IF(S59>=4,"Valorar ascensor (verificar)","—"))) -> — | V59: =IF('📇 INVENTARIO'!L60="","",'📇 INVENTARIO'!L60) -> 99.8 | W59: =IF($C59="","",V59*'⚙️ SUPUESTOS'!$C$8*'⚙️ SUPUESTOS'!$C$9) -> 20.958 | X59: =IF('📇 INVENTARIO'!N60="","",'📇 INVENTARIO'!N60) -> 1260 | Y59: =IF($C59="","",W59*X59*'⚙️ SUPUESTOS'!$C$7) -> 23766.372 | Z59: =IF($C59="","",W59*'⚙️ SUPUESTOS'!$C$10) -> 27978.93 | AA59: =IF($C59="","",Y59*('⚙️ SUPUESTOS'!$C$12*'⚙️ SUPUESTOS'!$C$11+(1-'⚙️ SUPUESTOS'!$C$12)*'⚙️ SUPUESTOS'!$C$13)) -> 1620.8666 | AB59: =IF($C59="","",IF(Y59>0,ROUND(Y59*'⚙️ SUPUESTOS'!$C$12*'⚙️ SUPUESTOS'!$C$11,0),"")) -> 594 | AC59: =IF($C59="","",IF(Y59>0,ROUND(Y59*(1-'⚙️ SUPUESTOS'!$C$12)*'⚙️ SUPUESTOS'!$C$13,0),"")) -> 1027 | AD59: =IF($C59="","",IF(AND(ISNUMBER(AA59),ISNUMBER(AE59),AA59>0,AE59>0),ROUND(AA59*MAX(0,25-AE59),0),"")) -> 12543 | AE59: =IF($C59="","",IF(AA59>0,Z59/AA59,"")) -> 17.261711 | AF59: =IF($C59="","",IF(AE59="","—",IF(AE59<='⚙️ SUPUESTOS'!$C$32,"✔ Muy recomendable",IF(AE59<='⚙️ SUPUESTOS'!$C$33,"✔ Recomendable","Valorar")))) -> Valorar | AG59: =IF('📇 INVENTARIO'!O60="","",'📇 INVENTARIO'!O60) -> 41.64948 | AH59: =IF('📇 INVENTARIO'!P60="","",'📇 INVENTARIO'!P60) -> -4.70856
A60: =IF($C60="","",RANK(O60,$O$3:$O$265,0)+COUNTIF($O$3:O60,O60)-1) -> 58 | B60: =IF($C60="","",IF(A60<='⚙️ SUPUESTOS'!$C$29,"Fase 1",IF(A60<='⚙️ SUPUESTOS'!$C$30,"Fase 2","Fase 3"))) -> Fase 1 | C60: =IF('📇 INVENTARIO'!B63="","",'📇 INVENTARIO'!B63) -> C/ Colibrí, 1 | D60: =IF('📇 INVENTARIO'!C63="","",'📇 INVENTARIO'!C63) -> 7924211UM5172D | E60: =IF('📇 INVENTARIO'!D63="","",'📇 INVENTARIO'!D63) -> 4718606024 | F60: =IF('📇 INVENTARIO'!F63="","",'📇 INVENTARIO'!F63) -> G | G60: =IF('📇 INVENTARIO'!G63="","",'📇 INVENTARIO'!G63) -> 494 | H60: =IF('📇 INVENTARIO'!H63="","",'📇 INVENTARIO'!H63) -> 104 | I60: =IF('📇 INVENTARIO'!I63="","",'📇 INVENTARIO'!I63) -> 239.9 | J60: =IF('📇 INVENTARIO'!J63="","",'📇 INVENTARIO'!J63) -> 1965 | K60: =IF($C60="","",(G60-'⚙️ SUPUESTOS'!$C$20)/('⚙️ SUPUESTOS'!$C$25-'⚙️ SUPUESTOS'!$C$20)) -> 0.60413081 | L60: =IF($C60="","",VLOOKUP($E60,'📊 SECCIONES'!$B$4:$S$9,16,FALSE())) -> 0.13391193 | M60: =IF($C60="","",VLOOKUP($E60,'📊 SECCIONES'!$B$4:$S$9,17,FALSE())) -> 0.16476684 | N60: =IF($C60="","",VLOOKUP($E60,'📊 SECCIONES'!$B$4:$S$9,18,FALSE())) -> 0.79545455 | O60: =IF($C60="","",ROUND('⚙️ SUPUESTOS'!$C$21*K60+'⚙️ SUPUESTOS'!$C$22*L60+'⚙️ SUPUESTOS'!$C$23*M60+'⚙️ SUPUESTOS'!$C$24*N60,4)) -> 0.4564 | P60: =IF($C60="","",VLOOKUP($E60,'📊 SECCIONES'!$B$4:$S$9,7,FALSE())) -> 30.06 | Q60: =IF($C60="","",VLOOKUP($E60,'📊 SECCIONES'!$B$4:$S$9,8,FALSE())) -> 25132 | R60: =IF($C60="","",VLOOKUP($E60,'📊 SECCIONES'!$B$4:$S$9,10,FALSE())) -> 28.1 | S60: =IF('📇 INVENTARIO'!K63="","",'📇 INVENTARIO'!K63) -> 3 | T60: =IF($C60="","","Objetivo: alcanzar calificación C. Actual: Cal."&F60&". "&IF(OR(F60="G",F60="F"),"SATE integral + cubierta + carpinterías triple + aerotermia + instalación fotovoltaica",IF(F60="E","SATE fachada + carpinterías doble + instalación fotovoltaica",IF(F60="D","Mantenimiento de envolvente + instalación fotovoltaica en cubierta","Optimización energética + instalación fotovoltaica")))) -> Objetivo: alcanzar calificación C. Actual: Cal.G. SATE integral + cubierta + carpinterías triple + aerotermia + instalación fotovoltaica | U60: =IF($C60="","",IF(S60=0,"s/d",IF(S60>=4,"Valorar ascensor (verificar)","—"))) -> — | V60: =IF('📇 INVENTARIO'!L63="","",'📇 INVENTARIO'!L63) -> 97.8 | W60: =IF($C60="","",V60*'⚙️ SUPUESTOS'!$C$8*'⚙️ SUPUESTOS'!$C$9) -> 20.538 | X60: =IF('📇 INVENTARIO'!N63="","",'📇 INVENTARIO'!N63) -> 1415 | Y60: =IF($C60="","",W60*X60*'⚙️ SUPUESTOS'!$C$7) -> 26155.143 | Z60: =IF($C60="","",W60*'⚙️ SUPUESTOS'!$C$10) -> 27418.23 | AA60: =IF($C60="","",Y60*('⚙️ SUPUESTOS'!$C$12*'⚙️ SUPUESTOS'!$C$11+(1-'⚙️ SUPUESTOS'!$C$12)*'⚙️ SUPUESTOS'!$C$13)) -> 1783.7808 | AB60: =IF($C60="","",IF(Y60>0,ROUND(Y60*'⚙️ SUPUESTOS'!$C$12*'⚙️ SUPUESTOS'!$C$11,0),"")) -> 654 | AC60: =IF($C60="","",IF(Y60>0,ROUND(Y60*(1-'⚙️ SUPUESTOS'!$C$12)*'⚙️ SUPUESTOS'!$C$13,0),"")) -> 1130 | AD60: =IF($C60="","",IF(AND(ISNUMBER(AA60),ISNUMBER(AE60),AA60>0,AE60>0),ROUND(AA60*MAX(0,25-AE60),0),"")) -> 17176 | AE60: =IF($C60="","",IF(AA60>0,Z60/AA60,"")) -> 15.370852 | AF60: =IF($C60="","",IF(AE60="","—",IF(AE60<='⚙️ SUPUESTOS'!$C$32,"✔ Muy recomendable",IF(AE60<='⚙️ SUPUESTOS'!$C$33,"✔ Recomendable","Valorar")))) -> ✔ Recomendable | AG60: =IF('📇 INVENTARIO'!O61="","",'📇 INVENTARIO'!O61) -> 41.64834 | AH60: =IF('📇 INVENTARIO'!P61="","",'📇 INVENTARIO'!P61) -> -4.70911
A61: =IF($C61="","",RANK(O61,$O$3:$O$265,0)+COUNTIF($O$3:O61,O61)-1) -> 59 | B61: =IF($C61="","",IF(A61<='⚙️ SUPUESTOS'!$C$29,"Fase 1",IF(A61<='⚙️ SUPUESTOS'!$C$30,"Fase 2","Fase 3"))) -> Fase 1 | C61: =IF('📇 INVENTARIO'!B61="","",'📇 INVENTARIO'!B61) -> C/ Gaviota, 4 | D61: =IF('📇 INVENTARIO'!C61="","",'📇 INVENTARIO'!C61) -> 7824511UM5172D | E61: =IF('📇 INVENTARIO'!D61="","",'📇 INVENTARIO'!D61) -> 4718606026 | F61: =IF('📇 INVENTARIO'!F61="","",'📇 INVENTARIO'!F61) -> E | G61: =IF('📇 INVENTARIO'!G61="","",'📇 INVENTARIO'!G61) -> 239 | H61: =IF('📇 INVENTARIO'!H61="","",'📇 INVENTARIO'!H61) -> 50 | I61: =IF('📇 INVENTARIO'!I61="","",'📇 INVENTARIO'!I61) -> 86.8 | J61: =IF('📇 INVENTARIO'!J61="","",'📇 INVENTARIO'!J61) -> 1965 | K61: =IF($C61="","",(G61-'⚙️ SUPUESTOS'!$C$20)/('⚙️ SUPUESTOS'!$C$25-'⚙️ SUPUESTOS'!$C$20)) -> 0.16523236 | L61: =IF($C61="","",VLOOKUP($E61,'📊 SECCIONES'!$B$4:$S$9,16,FALSE())) -> 1 | M61: =IF($C61="","",VLOOKUP($E61,'📊 SECCIONES'!$B$4:$S$9,17,FALSE())) -> 1 | N61: =IF($C61="","",VLOOKUP($E61,'📊 SECCIONES'!$B$4:$S$9,18,FALSE())) -> 0 | O61: =IF($C61="","",ROUND('⚙️ SUPUESTOS'!$C$21*K61+'⚙️ SUPUESTOS'!$C$22*L61+'⚙️ SUPUESTOS'!$C$23*M61+'⚙️ SUPUESTOS'!$C$24*N61,4)) -> 0.4509 | P61: =IF($C61="","",VLOOKUP($E61,'📊 SECCIONES'!$B$4:$S$9,7,FALSE())) -> 66.51 | Q61: =IF($C61="","",VLOOKUP($E61,'📊 SECCIONES'!$B$4:$S$9,8,FALSE())) -> 17450 | R61: =IF($C61="","",VLOOKUP($E61,'📊 SECCIONES'!$B$4:$S$9,10,FALSE())) -> 10.6 | S61: =IF('📇 INVENTARIO'!K61="","",'📇 INVENTARIO'!K61) -> 3 | T61: =IF($C61="","","Objetivo: alcanzar calificación C. Actual: Cal."&F61&". "&IF(OR(F61="G",F61="F"),"SATE integral + cubierta + carpinterías triple + aerotermia + instalación fotovoltaica",IF(F61="E","SATE fachada + carpinterías doble + instalación fotovoltaica",IF(F61="D","Mantenimiento de envolvente + instalación fotovoltaica en cubierta","Optimización energética + instalación fotovoltaica")))) -> Objetivo: alcanzar calificación C. Actual: Cal.E. SATE fachada + carpinterías doble + instalación fotovoltaica | U61: =IF($C61="","",IF(S61=0,"s/d",IF(S61>=4,"Valorar ascensor (verificar)","—"))) -> — | V61: =IF('📇 INVENTARIO'!L61="","",'📇 INVENTARIO'!L61) -> 98.5 | W61: =IF($C61="","",V61*'⚙️ SUPUESTOS'!$C$8*'⚙️ SUPUESTOS'!$C$9) -> 20.685 | X61: =IF('📇 INVENTARIO'!N61="","",'📇 INVENTARIO'!N61) -> 1449 | Y61: =IF($C61="","",W61*X61*'⚙️ SUPUESTOS'!$C$7) -> 26975.308 | Z61: =IF($C61="","",W61*'⚙️ SUPUESTOS'!$C$10) -> 27614.475 | AA61: =IF($C61="","",Y61*('⚙️ SUPUESTOS'!$C$12*'⚙️ SUPUESTOS'!$C$11+(1-'⚙️ SUPUESTOS'!$C$12)*'⚙️ SUPUESTOS'!$C$13)) -> 1839.716 | AB61: =IF($C61="","",IF(Y61>0,ROUND(Y61*'⚙️ SUPUESTOS'!$C$12*'⚙️ SUPUESTOS'!$C$11,0),"")) -> 674 | AC61: =IF($C61="","",IF(Y61>0,ROUND(Y61*(1-'⚙️ SUPUESTOS'!$C$12)*'⚙️ SUPUESTOS'!$C$13,0),"")) -> 1165 | AD61: =IF($C61="","",IF(AND(ISNUMBER(AA61),ISNUMBER(AE61),AA61>0,AE61>0),ROUND(AA61*MAX(0,25-AE61),0),"")) -> 18378 | AE61: =IF($C61="","",IF(AA61>0,Z61/AA61,"")) -> 15.010183 | AF61: =IF($C61="","",IF(AE61="","—",IF(AE61<='⚙️ SUPUESTOS'!$C$32,"✔ Muy recomendable",IF(AE61<='⚙️ SUPUESTOS'!$C$33,"✔ Recomendable","Valorar")))) -> ✔ Recomendable | AG61: =IF('📇 INVENTARIO'!O62="","",'📇 INVENTARIO'!O62) -> 41.64937 | AH61: =IF('📇 INVENTARIO'!P62="","",'📇 INVENTARIO'!P62) -> -4.71118
